Workbook

Sheet PROFESSORES
A1: N. Inscr | B1: Nome | C1: Email | D1: Fone | E1: Disciplina | F1: Currículo | G1: Vídeo | H1: Diferencial | I1: Observação | J1: Inglês | L1: Pos Ger | M1: Apr. Ger | N1: Pos Dis | O1: Apr Dis (F) | P1: Dis (L) | Q1: Dis (G) | R1: Dis (A) | S1: Dis (O) | T1: Pos Obj | U1: Apr Obj | V1: OBJ CONT | W1: DISC CONT | X1: FINAL CONT | Y1: SET | Z1: IA | AA1: STATUS | AB1: Q1R | AC1: Q1L | AD1: Q1G | AE1: Q1A | AF1: Q1O | AG1: Q1F | AH1: Q2R | AI1: Q2L | AJ1: Q2G | AK1: Q2A | AL1: Q2O | AM1: Q2F | AN1: Q3R | AO1: Q3L | AP1: Q3G | AQ1: Q3A | AR1: Q3O | AS1: Q3F | AT1: Q4R | AU1: Q4L | AV1: Q4G | AW1: Q4A | AX1: Q4O | AY1: Q4F | BB1: Aferição Constante | BC1: Trabalhos em Grupo | BD1: Seminários | BE1: Devolutiva Individualizada | BF1: Trabalhos de Pesquisa (internet) | BG1: Participação Estimulada | BH1: Estímulo ao Erro | BI1: Filmes e Séries | BJ1: Diagnóstico de Pré-requisitos | BK1: Lousa Interativa | BL1: Análise de resultados por habilidade | BM1: Exercícios frequentes | BN1: Cronômetro / tempo | BO1: Sermões | BP1: Focar nos interessados | BQ1: Destacar erros publicamente | BR1: Corrigir comportamento imperceptível | BS1: Correção pública | BT1: Planejamento de aula | BV1: Empatia | BW1: Presença | BX1: Linguagem | BY1: Preparação | BZ1: Material | CA1: Aferição | CB1: Clareza | CC1: Paciência | CD1: Responsabilidade | CE1: Energia | CF1: Lousa | CG1: Resolução Exercício | CH1: Voz | CI1: Confiança
A2: 0 | B2: Nome do Candidato | C2: emaildocandidato@email.com | D2: 11999999999 | E2: Geografia | F2: https://drive.google.com/open?id=1bMc5VcZVidJfIEMLpSLQu-bXwQ4nvuTp | G2: https://drive.google.com/open?id=11oGrETO_ra2LKFsgtdazGKRuQz0FKj44 | H2: Tive a oportunidade de participar do projeto PIBID, promovido pela CAPES, enquanto estava na minha primeira graduação. | J2: A1-A2 (básico) | L2: 28 | M2: 4.4974138 | N2: 9 | O2: 4.9104167 | P2: 5.6666667 | Q2: 4.4166667 | R2: 4.8333333 | S2: 3.25 | T2: 30 | U2: 4.2058824 | V2: 7 | Y2: EMEFAF | AB2: 1) Uso de material digital (power point) 2) Breve retomada dos conceitos da aula anterior | AC2: 2 | AD2: 4 | AE2: 9 | AF2: 7 | AG2: 4.4 | AH2: 1) Antes de prosseguir com o conteúdo, peço para que três estudantes sintetizem os conceitos mais relevantes da aula anterior 2) Dinâmica com uso de ferramentas lúdicas de aprendizagem (Kahoot, Plickers) 3) Sondagem por meio de avaliações curtas ao longo da unidade letiva | AI2: 24 | AJ2: 15 | AK2: 15 | AL2: 11 | AM2: 18.8 | AN2: 1) Elaboração de resumos em ficha pautada ao térmico de cada módulo e/ou mapas conceituais 2) Realização de listas de exercícios para fixação dos conteúdos | AO2: 14 | AP2: 5 | AQ2: 14 | AR2: 7 | AS2: 11.425 | AT2: Recentemente, tenho aplicado as técnicas ensinadas no livro “Aula Nota 10”, do autor Doug Lemov, às quais têm sido bastante produtivas. | AU2: 28 | AV2: 29 | AW2: 20 | AX2: 14 | AY2: 24.3 | BB2: 3 | BC2: 6 | BD2: 4 | BE2: 0 | BF2: 3 | BG2: 3 | BH2: 12 | BI2: 6 | BJ2: 2 | BK2: 2.5 | BL2: 1.5 | BM2: 2 | BN2: 9 | BO2: 2.5 | BP2: 1 | BQ2: 0.5 | BR2: 3 | BS2: 7.5 | BT2: 3 | BV2: =IFERROR(AVERAGEIF(AULAS_TESTE!$F:$F,$B2,AULAS_TESTE!G:G),"") -> 6.7941176 | BW2: =IFERROR(AVERAGEIF(AULAS_TESTE!$F:$F,$B2,AULAS_TESTE!H:H),"") -> 7.3529412 | BX2: =IFERROR(AVERAGEIF(AULAS_TESTE!$F:$F,$B2,AULAS_TESTE!I:I),"") -> 8.1764706 | BY2: =IFERROR(AVERAGEIF(AULAS_TESTE!$F:$F,$B2,AULAS_TESTE!J:J),"") -> 7.65625 | BZ2: =IFERROR(AVERAGEIF(AULAS_TESTE!$F:$F,$B2,AULAS_TESTE!K:K),"") -> 7.7333333 | CA2: =IFERROR(AVERAGEIF(AULAS_TESTE!$F:$F,$B2,AULAS_TESTE!L:L),"") -> 6.8076923 | CB2: =IFERROR(AVERAGEIF(AULAS_TESTE!$F:$F,$B2,AULAS_TESTE!M:M),"") -> 8.1176471 | CC2: =IFERROR(AVERAGEIF(AULAS_TESTE!$F:$F,$B2,AULAS_TESTE!N:N),"") -> 8.3125 | CD2: =IFERROR(AVERAGEIF(AULAS_TESTE!$F:$F,$B2,AULAS_TESTE!O:O),"") -> 7.5588235 | CE2: =IFERROR(AVERAGEIF(AULAS_TESTE!$F:$F,$B2,AULAS_TESTE!P:P),"") -> 7.6875 | CF2: =IFERROR(AVERAGEIF(AULAS_TESTE!$F:$F,$B2,AULAS_TESTE!Q:Q),"") -> 7.5 | CG2: =IFERROR(AVERAGEIF(AULAS_TESTE!$F:$F,$B2,AULAS_TESTE!R:R),"") -> 6.2727273 | CH2: =IFERROR(AVERAGEIF(AULAS_TESTE!$F:$F,$B2,AULAS_TESTE!S:S),"") -> 8.0625 | CI2: =IFERROR(AVERAGEIF(AULAS_TESTE!$F:$F,$B2,AULAS_TESTE!T:T),"") -> 7.59375
A3: 0 | B3: Nome do Candidato | C3: emaildocandidato@email.com | D3: 11999999999 | E3: Português (Produção e Interpretação de Texto) | F3: https://drive.google.com/open?id=1x0wHCAV_5Oghj-J1hvioPUsxOnDzoxjy | G3: https://drive.google.com/open?id=1ztb4sVW7X9zI-u8fOGhj9YQxmPab7frZ | H3: Sou Marta Maria Ferreira Kagohara, formada em Comunicação Social, Pedagogia e Letras (Português), com duas pós-graduações em Cultura e Produção de Texto e Literatura. Sou mãe de uma filha de 25 anos, casada, e tenho experiência internacional: lecionei por dois anos no Japão, em escolas brasileiras, experiência que me proporcionou uma nova visão de mundo e o enriquecimento de vivências pedagógicas diversas. No Brasil, atuei em empresas na área educacional e, há oito anos e meio, trabalho em sala de aula, experiência que consolidou minha paixão e dedicação à educação. Resido próximo ao centro de Santo André e considero-me resiliente, organizada e de fácil aprendizado. Tenho grande interesse em integrar o quadro docente deste colégio, reconhecido por sua tradição, excelência e comprometimento com a formação de seus alunos, bem como pelo respeito e valorização de seus professores, elementos que considero fundamentais para o pleno desenvolvimento do trabalho pedagógico. Acredito possuir amor pela educação e competências pedagógicas sólidas, e espero contribuir com minha qualificação e experiência, colaborando para o crescimento e a formação integral de crianças e adolescentes. Tenho especial identificação e experiência para atuar com Ensino Fundamental I e II, e estou motivada a participar ativamente do projeto pedagógico desta instituição. | I3: Resposta acima. | J3: A1-A2 (básico) | L3: 31 | M3: 5.162931 | N3: 9 | O3: 5.1020833 | P3: 5.5 | Q3: 3.9166667 | R3: 5.3333333 | S3: 4.75 | T3: 39 | U3: 5.2058824 | Y3: EMEFAF | AB3: Planejo cada aula com objetivos claros e atividades sequenciadas, priorizando metodologias ativas para manter os alunos engajados. Uso recursos visuais e tecnológicos para facilitar a compreensão e monitoro constantemente o ritmo da turma, ajustando quando necessário para garantir aproveitamento do tempo. | AC3: 10 | AD3: 12 | AE3: 15 | AF3: 12 | AG3: 11.525 | AH3: Utilizo avaliações diversificadas, como exercícios escritos, produção de textos, leitura e interpretação, além de atividades orais e debates em sala. Observo o desempenho contínuo dos alunos em atividades práticas e proponho correções imediatas, garantindo que o domínio de habilidades e conceitos seja confirmado ao longo do processo e não apenas em avaliações finais. | AI3: 22 | AJ3: 10 | AK3: 12 | AL3: 15 | AM3: 17.225 | AN3: Ensino técnicas de estudo como organização de resumos, esquemas e mapas conceituais, leitura ativa e anotações estratégicas. Incentivo a gestão do tempo e a revisão periódica do conteúdo, garantindo que os alunos pratiquem essas estratégias em sala e fora dela, para desenvolver autonomia e responsabilidade pelo próprio aprendizado. | AO3: 14 | AP3: 14 | AQ3: 22 | AR3: 16 | AS3: 15.75 | AT3: Renovo minhas práticas pedagógicas participando de cursos de formação continuada, lendo artigos e livros de referência em educação e trocando experiências com colegas. Busco aplicar metodologias ativas e estratégias de ensino centradas no aluno. Entre minhas referências teóricas, destaco Piaget, Vygotsky e Freire, que fundamentam minhas práticas de aprendizagem significativa, desenvolvimento da autonomia e engajamento dos estudantes. | AU3: 20 | AV3: 11 | AW3: 15 | AX3: 14 | AY3: 16.725 | BB3: 9 | BC3: 6 | BD3: 6 | BE3: 0 | BF3: 3 | BG3: 3 | BH3: 9 | BI3: 6 | BJ3: 4 | BK3: 1.5 | BL3: 3 | BM3: 4 | BN3: 3 | BO3: 2 | BP3: 4 | BQ3: 2.5 | BR3: 6 | BS3: 7.5 | BT3: 9 | BV3: =IFERROR(AVERAGEIF(AULAS_TESTE!$F:$F,$B3,AULAS_TESTE!G:G),"") -> 6.7941176 | BW3: =IFERROR(AVERAGEIF(AULAS_TESTE!$F:$F,$B3,AULAS_TESTE!H:H),"") -> 7.3529412 | BX3: =IFERROR(AVERAGEIF(AULAS_TESTE!$F:$F,$B3,AULAS_TESTE!I:I),"") -> 8.1764706 | BY3: =IFERROR(AVERAGEIF(AULAS_TESTE!$F:$F,$B3,AULAS_TESTE!J:J),"") -> 7.65625 | BZ3: =IFERROR(AVERAGEIF(AULAS_TESTE!$F:$F,$B3,AULAS_TESTE!K:K),"") -> 7.7333333 | CA3: =IFERROR(AVERAGEIF(AULAS_TESTE!$F:$F,$B3,AULAS_TESTE!L:L),"") -> 6.8076923 | CB3: =IFERROR(AVERAGEIF(AULAS_TESTE!$F:$F,$B3,AULAS_TESTE!M:M),"") -> 8.1176471 | CC3: =IFERROR(AVERAGEIF(AULAS_TESTE!$F:$F,$B3,AULAS_TESTE!N:N),"") -> 8.3125 | CD3: =IFERROR(AVERAGEIF(AULAS_TESTE!$F:$F,$B3,AULAS_TESTE!O:O),"") -> 7.5588235 | CE3: =IFERROR(AVERAGEIF(AULAS_TESTE!$F:$F,$B3,AULAS_TESTE!P:P),"") -> 7.6875 | CF3: =IFERROR(AVERAGEIF(AULAS_TESTE!$F:$F,$B3,AULAS_TESTE!Q:Q),"") -> 7.5 | CG3: =IFERROR(AVERAGEIF(AULAS_TESTE!$F:$F,$B3,AULAS_TESTE!R:R),"") -> 6.2727273 | CH3: =IFERROR(AVERAGEIF(AULAS_TESTE!$F:$F,$B3,AULAS_TESTE!S:S),"") -> 8.0625 | CI3: =IFERROR(AVERAGEIF(AULAS_TESTE!$F:$F,$B3,AULAS_TESTE!T:T),"") -> 7.59375
A4: 0 | B4: Nome do Candidato | C4: emaildocandidato@email.com | D4: 11999999999 | E4: Português (Literatura) | F4: https://drive.google.com/open?id=1ZGUa46WZ4_1zRe6X8UMa6ywAi__i3GHl | G4: https://drive.google.com/open?id=1mFbQk4RaA4N1gkf2wD9SWheLqt5F3ftm | J4: A1-A2 (básico) | L4: 10 | M4: 4.9275862 | N4: 10 | O4: 2.8666667 | P4: 2.9166667 | Q4: 3.1666667 | R4: 2.75 | S4: 2.5833333 | T4: 9 | U4: 6.3823529 | Y4: EMEFAF | AB4: Antes de cada aula, planejo cuidadosamente o conteúdo, as atividades e os objetivos de aprendizado. Isso ajuda a garantir que o tempo seja utilizado de forma eficiente. | AC4: 7 | AD4: 11 | AE4: 5 | AF4: 8 | AG4: 7.425 | AH4: Utilizar atividades práticas, como projetos, trabalhos em grupo e experimentos, para avaliar a aplicação dos conceitos e habilidades. | AI4: 7 | AJ4: 9 | AK4: 8 | AL4: 6 | AM4: 7.3 | AN4: Ensinar os alunos a resumir e sintetizar informações, ajudando a compreender e reter melhor o conteúdo. | AO4: 8 | AP4: 17 | AQ4: 11 | AR4: 10 | AS4: 10.225 | AT4: Eu Participo de cursos, workshops e seminários para me atualizar sobre novas metodologias e tecnologias educacionais. | AU4: 13 | AV4: 1 | AW4: 9 | AX4: 7 | AY4: 9.45 | BB4: 15 | BC4: 2 | BD4: 2 | BE4: 0 | BF4: 2 | BG4: 4 | BH4: 15 | BI4: 2 | BJ4: 8 | BK4: 0.5 | BL4: 7.5 | BM4: 6 | BN4: 3 | BO4: 2.5 | BP4: 5 | BQ4: 2.5 | BR4: 9 | BS4: 7.5 | BT4: 15 | BV4: =IFERROR(AVERAGEIF(AULAS_TESTE!$F:$F,$B4,AULAS_TESTE!G:G),"") -> 6.7941176 | BW4: =IFERROR(AVERAGEIF(AULAS_TESTE!$F:$F,$B4,AULAS_TESTE!H:H),"") -> 7.3529412 | BX4: =IFERROR(AVERAGEIF(AULAS_TESTE!$F:$F,$B4,AULAS_TESTE!I:I),"") -> 8.1764706 | BY4: =IFERROR(AVERAGEIF(AULAS_TESTE!$F:$F,$B4,AULAS_TESTE!J:J),"") -> 7.65625 | BZ4: =IFERROR(AVERAGEIF(AULAS_TESTE!$F:$F,$B4,AULAS_TESTE!K:K),"") -> 7.7333333 | CA4: =IFERROR(AVERAGEIF(AULAS_TESTE!$F:$F,$B4,AULAS_TESTE!L:L),"") -> 6.8076923 | CB4: =IFERROR(AVERAGEIF(AULAS_TESTE!$F:$F,$B4,AULAS_TESTE!M:M),"") -> 8.1176471 | CC4: =IFERROR(AVERAGEIF(AULAS_TESTE!$F:$F,$B4,AULAS_TESTE!N:N),"") -> 8.3125 | CD4: =IFERROR(AVERAGEIF(AULAS_TESTE!$F:$F,$B4,AULAS_TESTE!O:O),"") -> 7.5588235 | CE4: =IFERROR(AVERAGEIF(AULAS_TESTE!$F:$F,$B4,AULAS_TESTE!P:P),"") -> 7.6875 | CF4: =IFERROR(AVERAGEIF(AULAS_TESTE!$F:$F,$B4,AULAS_TESTE!Q:Q),"") -> 7.5 | CG4: =IFERROR(AVERAGEIF(AULAS_TESTE!$F:$F,$B4,AULAS_TESTE!R:R),"") -> 6.2727273 | CH4: =IFERROR(AVERAGEIF(AULAS_TESTE!$F:$F,$B4,AULAS_TESTE!S:S),"") -> 8.0625 | CI4: =IFERROR(AVERAGEIF(AULAS_TESTE!$F:$F,$B4,AULAS_TESTE!T:T),"") -> 7.59375
A5: 0 | B5: Nome do Candidato | C5: emaildocandidato@email.com | D5: 11999999999 | E5: Matemática | F5: https://drive.google.com/open?id=1d748CJD57UYs1g8OyLgcE63w-mbMcbuz | G5: https://drive.google.com/open?id=1YHfLOmQMLQUPia-_TU3WV2bY7oT-S5Br | H5: Cursos | J5: A1-A2 (básico) | L5: 33 | M5: 4.1508621 | N5: 33 | O5: 1.28125 | P5: 0.83333333 | Q5: 0.41666667 | R5: 2.5833333 | S5: 2 | T5: 32 | U5: 6.1764706 | Y5: EMEFAF | AB5: Uso a criatividade e o dinamismo A matemática descomplicada faz toda diferença na vida do aluno Me preocupo com a aprendizagem da criança e procuro sanar suas dúvidas e medos | AC5: 2 | AD5: 0 | AE5: 3 | AF5: 5 | AG5: 2.4 | AH5: Através de exercícios em sala de aula com atividades práticas Tarefas para casa são também uma ferramenta avaliativa para o professor | AI5: 8 | AJ5: 3 | AK5: 12 | AL5: 5 | AM5: 7.425 | AN5: Conteúdo trabalhado na sua forma mais simples de entendimento Com palavras simples e objetivas para alcançar meu propósito Atividades em sala individuais e duplas Lição de casa Resumo do conteúdo Seminario | AO5: 0 | AP5: 1 | AQ5: 11 | AR5: 8 | AS5: 3.475 | AT5: Trabalho o lúdico e o real Apresentação Seminários Sugestões de pesquisas são bem vindos | AU5: 0 | AV5: 1 | AW5: 5 | AX5: 6 | AY5: 2.075 | BB5: 15 | BC5: 6 | BD5: 2 | BE5: 0 | BF5: 1 | BG5: 2 | BH5: 15 | BI5: 2 | BJ5: 8 | BK5: 1 | BL5: 4.5 | BM5: 10 | BN5: 3 | BO5: 2.5 | BP5: 5 | BQ5: 2.5 | BR5: 3 | BS5: 7.5 | BT5: 15 | BV5: =IFERROR(AVERAGEIF(AULAS_TESTE!$F:$F,$B5,AULAS_TESTE!G:G),"") -> 6.7941176 | BW5: =IFERROR(AVERAGEIF(AULAS_TESTE!$F:$F,$B5,AULAS_TESTE!H:H),"") -> 7.3529412 | BX5: =IFERROR(AVERAGEIF(AULAS_TESTE!$F:$F,$B5,AULAS_TESTE!I:I),"") -> 8.1764706 | BY5: =IFERROR(AVERAGEIF(AULAS_TESTE!$F:$F,$B5,AULAS_TESTE!J:J),"") -> 7.65625 | BZ5: =IFERROR(AVERAGEIF(AULAS_TESTE!$F:$F,$B5,AULAS_TESTE!K:K),"") -> 7.7333333 | CA5: =IFERROR(AVERAGEIF(AULAS_TESTE!$F:$F,$B5,AULAS_TESTE!L:L),"") -> 6.8076923 | CB5: =IFERROR(AVERAGEIF(AULAS_TESTE!$F:$F,$B5,AULAS_TESTE!M:M),"") -> 8.1176471 | CC5: =IFERROR(AVERAGEIF(AULAS_TESTE!$F:$F,$B5,AULAS_TESTE!N:N),"") -> 8.3125 | CD5: =IFERROR(AVERAGEIF(AULAS_TESTE!$F:$F,$B5,AULAS_TESTE!O:O),"") -> 7.5588235 | CE5: =IFERROR(AVERAGEIF(AULAS_TESTE!$F:$F,$B5,AULAS_TESTE!P:P),"") -> 7.6875 | CF5: =IFERROR(AVERAGEIF(AULAS_TESTE!$F:$F,$B5,AULAS_TESTE!Q:Q),"") -> 7.5 | CG5: =IFERROR(AVERAGEIF(AULAS_TESTE!$F:$F,$B5,AULAS_TESTE!R:R),"") -> 6.2727273 | CH5: =IFERROR(AVERAGEIF(AULAS_TESTE!$F:$F,$B5,AULAS_TESTE!S:S),"") -> 8.0625 | CI5: =IFERROR(AVERAGEIF(AULAS_TESTE!$F:$F,$B5,AULAS_TESTE!T:T),"") -> 7.59375
A6: 0 | B6: Nome do Candidato | C6: emaildocandidato@email.com | D6: 11999999999 | E6: Física | F6: https://drive.google.com/open?id=1JRC46tjsYfeGOYxiOH571a8Lo2KU30Gp | G6: https://drive.google.com/open?id=1ZCdS-rvhmyyQLhtXqoduhwfPkFWZGxZF | H6: Meu grande diferencial é que eu possuo uma bagagem em ensino a neuro divergentes, desde casos leves de TDAH até casos mais profundos com o ensino para pessoas com trissomia do 21 e paralisia parcial cerebral | I6: No vídeo, fala que estou na bela vista, mãe para me aproximar dos meus pais que já estão debilitados pela idade, eu me mudei para outro deles. | J6: B1-B2 (intermediário) | L6: 9 | M6: 5.7387931 | N6: 8 | O6: 3.9520833 | P6: 3.8333333 | Q6: 3.1666667 | R6: 4.8333333 | S6: 4.0833333 | T6: 11 | U6: 7 | V6: 5.5 | Y6: EMEFAF | AB6: Utilizo de simulações experimentais e tenho plano de aula pensando na dúvidas que podem aparecer durante a explicação. | AC6: 11 | AD6: 4 | AE6: 12 | AF6: 6 | AG6: 9.25 | AH6: Eu faço avaliações parciais durante o período letivo e faço uma série de perguntas no kahoot para estimular o convencimento. | AI6: 12 | AJ6: 2 | AK6: 8 | AL6: 9 | AM6: 9.275 | AN6: Eu gosto de aplicar a ideia de Feynman, que tenta explicar a física de forma simples e recuperação ativa com testes práticos e peço também para alguns alunos um pouco mais defasados explicarem o que entenderam da matéria. Nunca deixando a modelagem de conceitos físicos, com prática guiada e feedbacks regulares | AO6: 8 | AP6: 29 | AQ6: 24 | AR6: 23 | AS6: 16.575 | AT6: Eu gosto de trazer a tecnologia para a sala, como estamos numa geração no qual a tecnologia de faz presente desde seu nascimento, sinto que quando estamos vendo algo na internet, consigo ter uma atenção geral da sala satisfatória, sempre procuro aperfeiçoar minha lousas, já utilizei o app Miro para acompanhar desenvolvimento de turma em projetos e trabalhos sendo a uma das formas para avaliar o conhecimento prático dos alunos. | AU6: 15 | AV6: 3 | AW6: 14 | AX6: 11 | AY6: 12.325 | BB6: 12 | BC6: 2 | BD6: 4 | BE6: 0 | BF6: 1 | BG6: 5 | BH6: 15 | BI6: 2 | BJ6: 10 | BK6: 1 | BL6: 7.5 | BM6: 10 | BN6: 3 | BO6: 1.5 | BP6: 5 | BQ6: 2.5 | BR6: 15 | BS6: 7.5 | BT6: 15 | BV6: =IFERROR(AVERAGEIF(AULAS_TESTE!$F:$F,$B6,AULAS_TESTE!G:G),"") -> 6.7941176 | BW6: =IFERROR(AVERAGEIF(AULAS_TESTE!$F:$F,$B6,AULAS_TESTE!H:H),"") -> 7.3529412 | BX6: =IFERROR(AVERAGEIF(AULAS_TESTE!$F:$F,$B6,AULAS_TESTE!I:I),"") -> 8.1764706 | BY6: =IFERROR(AVERAGEIF(AULAS_TESTE!$F:$F,$B6,AULAS_TESTE!J:J),"") -> 7.65625 | BZ6: =IFERROR(AVERAGEIF(AULAS_TESTE!$F:$F,$B6,AULAS_TESTE!K:K),"") -> 7.7333333 | CA6: =IFERROR(AVERAGEIF(AULAS_TESTE!$F:$F,$B6,AULAS_TESTE!L:L),"") -> 6.8076923 | CB6: =IFERROR(AVERAGEIF(AULAS_TESTE!$F:$F,$B6,AULAS_TESTE!M:M),"") -> 8.1176471 | CC6: =IFERROR(AVERAGEIF(AULAS_TESTE!$F:$F,$B6,AULAS_TESTE!N:N),"") -> 8.3125 | CD6: =IFERROR(AVERAGEIF(AULAS_TESTE!$F:$F,$B6,AULAS_TESTE!O:O),"") -> 7.5588235 | CE6: =IFERROR(AVERAGEIF(AULAS_TESTE!$F:$F,$B6,AULAS_TESTE!P:P),"") -> 7.6875 | CF6: =IFERROR(AVERAGEIF(AULAS_TESTE!$F:$F,$B6,AULAS_TESTE!Q:Q),"") -> 7.5 | CG6: =IFERROR(AVERAGEIF(AULAS_TESTE!$F:$F,$B6,AULAS_TESTE!R:R),"") -> 6.2727273 | CH6: =IFERROR(AVERAGEIF(AULAS_TESTE!$F:$F,$B6,AULAS_TESTE!S:S),"") -> 8.0625 | CI6: =IFERROR(AVERAGEIF(AULAS_TESTE!$F:$F,$B6,AULAS_TESTE!T:T),"") -> 7.59375
A7: 0 | B7: Nome do Candidato | C7: emaildocandidato@email.com | D7: 11999999999 | E7: Matemática | F7: https://drive.google.com/open?id=1TshXV0s_ZP9rt435hFYfvk9h5Qy3L8X- | G7: https://drive.google.com/open?id=1MvfMsYjqET4jkQs23qWnj4n_bY_SG-It | H7: Palestrar em 3 congressos internacionais com minha pesquisa de mestrado. Ter palestrando 2 vezes na Unicamp, ter dado palestra curso e oficinas na Encontro Hotel Hilbert ( finalistas da OBMEP) Além de ter feito algumas formações e cursos para professores | I7: Gosto de trabalhar no formato de projeto e também no formato de preparação pra vestibular e olimpíadas, desde que fique bem claro e segregado o que trabalhar, como trabalhar e quando trabalhar em cada formato, pois creio que seja inviável tentar fazer tudo ao mesmo tempo | J7: B1-B2 (intermediário) | L7: 30 | M7: 5.0974138 | N7: 27 | O7: 3.06875 | P7: 2.1666667 | Q7: 3.4166667 | R7: 4.5 | S7: 3.9166667 | T7: 27 | U7: 6.5294118 | V7: 6.5 | W7: 1.7 | X7: 3.3 | Y7: EMEFAF | AB7: Gosto muito de utilizar metodologías ativas, e particularmente gosto muito da sala de aula invertida, o qual eu vejo uma aplicação e envolvimento grande da sala de aula, e também trabalhar projetos de maneira interdisciplinar. | AC7: 6 | AD7: 4 | AE7: 8 | AF7: 6 | AG7: 6.05 | AH7: Vou falar o que ocorre particularmente durante a sala de aula invertida . Durante esse processo, consigo passar de grupo em grupo escutando e observando a aplicação dedicação e envolvimento deles, durante a apresentação do trabalho e quando os grupos aplicam e criam atividades avaliativa em seis colegas consigo mensurar e perceber mais ainda como estão em seu engajamento e envolvimento no processo E no final realizo uma autoavaliação com a turma de maneira individual | AI7: 2 | AJ7: 5 | AK7: 12 | AL7: 13 | AM7: 6.125 | AN7: A importância de estudar pouco a pouco diariamente e a importância da constância de elaborar os processos , e que no final serão totalmente satisfatório. Trago para a turma e explico os passos que a sala de aula invertida vai de encontro com a técnica de estudo de Feynman o qual vejo ser bem eficaz e eficiente. | AO7: 6 | AP7: 23 | AQ7: 14 | AR7: 10 | AS7: 10.65 | AT7: Gosto de estudar e aprofundar em Neurociência, técnicas de estudos e metodologias ativas, procurando trazer uma educação que tenha significado e aplicabilidade na maioria das vezes, porque as vezes em matemática temos que aprender e desenvolver alguns conceitos que no início não tenha uma aplicação tão clara e direta para as turmas, mas sempre que possível procuro trazer isso, principalmente para desmistificar esse "bicho papão" que acham que a matemática é. E não posso deixar de citar a parte de jogos, que foi o tema de meu mestrado, mas nem sempre tenho abertura para aplicar jogos pedagógicos em sala de aula, mas quando tenho eu os uso | AU7: 12 | AV7: 9 | AW7: 20 | AX7: 18 | AY7: 14 | BB7: 9 | BC7: 4 | BD7: 4 | BE7: 0 | BF7: 2 | BG7: 2 | BH7: 15 | BI7: 6 | BJ7: 10 | BK7: 1 | BL7: 4.5 | BM7: 4 | BN7: 6 | BO7: 2.5 | BP7: 4 | BQ7: 2.5 | BR7: 12 | BS7: 7.5 | BT7: 15 | BV7: =IFERROR(AVERAGEIF(AULAS_TESTE!$F:$F,$B7,AULAS_TESTE!G:G),"") -> 6.7941176 | BW7: =IFERROR(AVERAGEIF(AULAS_TESTE!$F:$F,$B7,AULAS_TESTE!H:H),"") -> 7.3529412 | BX7: =IFERROR(AVERAGEIF(AULAS_TESTE!$F:$F,$B7,AULAS_TESTE!I:I),"") -> 8.1764706 | BY7: =IFERROR(AVERAGEIF(AULAS_TESTE!$F:$F,$B7,AULAS_TESTE!J:J),"") -> 7.65625 | BZ7: =IFERROR(AVERAGEIF(AULAS_TESTE!$F:$F,$B7,AULAS_TESTE!K:K),"") -> 7.7333333 | CA7: =IFERROR(AVERAGEIF(AULAS_TESTE!$F:$F,$B7,AULAS_TESTE!L:L),"") -> 6.8076923 | CB7: =IFERROR(AVERAGEIF(AULAS_TESTE!$F:$F,$B7,AULAS_TESTE!M:M),"") -> 8.1176471 | CC7: =IFERROR(AVERAGEIF(AULAS_TESTE!$F:$F,$B7,AULAS_TESTE!N:N),"") -> 8.3125 | CD7: =IFERROR(AVERAGEIF(AULAS_TESTE!$F:$F,$B7,AULAS_TESTE!O:O),"") -> 7.5588235 | CE7: =IFERROR(AVERAGEIF(AULAS_TESTE!$F:$F,$B7,AULAS_TESTE!P:P),"") -> 7.6875 | CF7: =IFERROR(AVERAGEIF(AULAS_TESTE!$F:$F,$B7,AULAS_TESTE!Q:Q),"") -> 7.5 | CG7: =IFERROR(AVERAGEIF(AULAS_TESTE!$F:$F,$B7,AULAS_TESTE!R:R),"") -> 6.2727273 | CH7: =IFERROR(AVERAGEIF(AULAS_TESTE!$F:$F,$B7,AULAS_TESTE!S:S),"") -> 8.0625 | CI7: =IFERROR(AVERAGEIF(AULAS_TESTE!$F:$F,$B7,AULAS_TESTE!T:T),"") -> 7.59375
A8: 0 | B8: Nome do Candidato | C8: emaildocandidato@email.com | D8: 11999999999 | E8: Geografia | F8: https://drive.google.com/open?id=16FLkrb6nx3SXssc5S4TDIt9A-NYomsYO | G8: https://drive.google.com/open?id=1aFRmrYS9mkMCTO44SYEazT1NRTYAAoPS | H8: Experiência em escolas particulares e participação ativa em projetos, mostras culturais e saídas pedagógicas. | J8: A1-A2 (básico) | L8: 11 | M8: 6.1327586 | N8: 23 | O8: 2.5708333 | P8: 3.1666667 | Q8: 1.3333333 | R8: 2.4166667 | S8: 2.0833333 | T8: 1 | U8: 8.6470588 | V8: 9 | W8: 8.75 | X8: 8.8333333 | Y8: EMEFAF | AB8: Metodologias ativas. | AC8: 0 | AD8: 0 | AE8: 2 | AF8: 2 | AG8: 0.7 | AH8: Atividades escritas, apresentações em grupo ou individuais, desempenho em avaliações, participação em aula, anotações de caderno. | AI8: 7 | AJ8: 2 | AK8: 8 | AL8: 7 | AM8: 6.425 | AN8: Leitura e resumo de textos, análise e anotações de vídeos explicativos, anotações de caderno e correções de prova. | AO8: 13 | AP8: 11 | AQ8: 11 | AR8: 7 | AS8: 11.3 | AT8: Estou sempre estudando novas metodologias, buscando formação ( tenho 3 pós graduações na área de educação) leitura de materiais sobre educação e troca de conhecimentos com outros professores. | AU8: 18 | AV8: 3 | AW8: 8 | AX8: 9 | AY8: 12.425 | BB8: 15 | BC8: 6 | BD8: 6 | BE8: 0 | BF8: 4 | BG8: 5 | BH8: 15 | BI8: 8 | BJ8: 8 | BK8: 0.5 | BL8: 7.5 | BM8: 10 | BN8: 15 | BO8: 2 | BP8: 5 | BQ8: 2.5 | BR8: 15 | BS8: 7.5 | BT8: 15 | BV8: =IFERROR(AVERAGEIF(AULAS_TESTE!$F:$F,$B8,AULAS_TESTE!G:G),"") -> 6.7941176 | BW8: =IFERROR(AVERAGEIF(AULAS_TESTE!$F:$F,$B8,AULAS_TESTE!H:H),"") -> 7.3529412 | BX8: =IFERROR(AVERAGEIF(AULAS_TESTE!$F:$F,$B8,AULAS_TESTE!I:I),"") -> 8.1764706 | BY8: =IFERROR(AVERAGEIF(AULAS_TESTE!$F:$F,$B8,AULAS_TESTE!J:J),"") -> 7.65625 | BZ8: =IFERROR(AVERAGEIF(AULAS_TESTE!$F:$F,$B8,AULAS_TESTE!K:K),"") -> 7.7333333 | CA8: =IFERROR(AVERAGEIF(AULAS_TESTE!$F:$F,$B8,AULAS_TESTE!L:L),"") -> 6.8076923 | CB8: =IFERROR(AVERAGEIF(AULAS_TESTE!$F:$F,$B8,AULAS_TESTE!M:M),"") -> 8.1176471 | CC8: =IFERROR(AVERAGEIF(AULAS_TESTE!$F:$F,$B8,AULAS_TESTE!N:N),"") -> 8.3125 | CD8: =IFERROR(AVERAGEIF(AULAS_TESTE!$F:$F,$B8,AULAS_TESTE!O:O),"") -> 7.5588235 | CE8: =IFERROR(AVERAGEIF(AULAS_TESTE!$F:$F,$B8,AULAS_TESTE!P:P),"") -> 7.6875 | CF8: =IFERROR(AVERAGEIF(AULAS_TESTE!$F:$F,$B8,AULAS_TESTE!Q:Q),"") -> 7.5 | CG8: =IFERROR(AVERAGEIF(AULAS_TESTE!$F:$F,$B8,AULAS_TESTE!R:R),"") -> 6.2727273 | CH8: =IFERROR(AVERAGEIF(AULAS_TESTE!$F:$F,$B8,AULAS_TESTE!S:S),"") -> 8.0625 | CI8: =IFERROR(AVERAGEIF(AULAS_TESTE!$F:$F,$B8,AULAS_TESTE!T:T),"") -> 7.59375
A9: 0 | B9: Nome do Candidato | C9: emaildocandidato@email.com | D9: 11999999999 | E9: Matemática | F9: https://drive.google.com/open?id=1vpLGLgpviG0QOh5LPBdixePdOr1dusv_ | G9: https://drive.google.com/open?id=1NZXBUKEnUaQi5DliehTzRzRZs7AdfrcO | J9: C1-C2 (avançado/fluente) | L9: 1 | M9: 7.7560345 | N9: 1 | O9: 8.3270833 | P9: 8.6666667 | Q9: 8.25 | R9: 8.5833333 | S9: 7.1666667 | T9: 18 | U9: 7.3529412 | V9: 8 | W9: 6.4 | X9: 6.9333333 | Y9: EMEFAF | AB9: Organizo as aulas com planejamento detalhado, dividindo o tempo entre revisão, explicação teórica, resolução de exemplos e prática guiada. Uso cronogramas visuais no quadro para orientar os alunos sobre cada etapa, preparo materiais antecipadamente e aplico atividades em dupla ou grupos para agilizar a troca de ideias. Também incorporo avaliações diagnósticas rápidas para ajustar o ritmo e garantir que todos avancem sem desperdício de tempo. | AC9: 26 | AD9: 22 | AE9: 25 | AF9: 20 | AG9: 24.175 | AH9: Utilizo avaliações formativas constantes, como exercícios rápidos ao final da explicação, perguntas direcionadas durante a aula, quizzes digitais e resolução de problemas no quadro pelos próprios alunos. Também proponho tarefas que exigem aplicação do conceito em situações novas, garantindo que não apenas memorizem, mas compreendam. Registro o desempenho em rubricas simples, identificando quem precisa de reforço, e faço retomadas curtas nos encontros seguintes para consolidar o aprendizado. | AI9: 27 | AJ9: 27 | AK9: 25 | AL9: 22 | AM9: 25.775 | AN9: Faço questão de ensinar os alunos a planejar o estudo com metas claras e revisões espaçadas, usar a prática de recuperação por meio de mini-testes, desenvolver anotações ativas e aplicar a técnica da autoexplicação para consolidar conceitos. Também incentivo hábitos de organização do tempo, como ciclos de estudo focados e revisões pós-provas, garantindo que eles não apenas estudem mais, mas aprendam a aprender de forma autônoma e eficaz. | AO9: 28 | AP9: 22 | AQ9: 28 | AR9: 23 | AS9: 26.225 | AT9: Busco aprimoramento por meio de cursos de formação e leituras constantes de autores como Richard Mayer, que enfatiza a organização cognitiva do conteúdo e Polya, referência na resolução estruturada de problemas matemáticos. Além disso, participo de congressos e mantenho uma prática reflexiva baseada em evidências, revisando continuamente minhas estratégias para garantir clareza, rigor e eficácia no ensino. | AU9: 23 | AV9: 28 | AW9: 25 | AX9: 21 | AY9: 23.75 | BB9: 15 | BC9: 4 | BD9: 6 | BE9: 0 | BF9: 3 | BG9: 2 | BH9: 12 | BI9: 8 | BJ9: 8 | BK9: 1.5 | BL9: 6 | BM9: 8 | BN9: 9 | BO9: 2.5 | BP9: 5 | BQ9: 2 | BR9: 12 | BS9: 6 | BT9: 15 | BV9: =IFERROR(AVERAGEIF(AULAS_TESTE!$F:$F,$B9,AULAS_TESTE!G:G),"") -> 6.7941176 | BW9: =IFERROR(AVERAGEIF(AULAS_TESTE!$F:$F,$B9,AULAS_TESTE!H:H),"") -> 7.3529412 | BX9: =IFERROR(AVERAGEIF(AULAS_TESTE!$F:$F,$B9,AULAS_TESTE!I:I),"") -> 8.1764706 | BY9: =IFERROR(AVERAGEIF(AULAS_TESTE!$F:$F,$B9,AULAS_TESTE!J:J),"") -> 7.65625 | BZ9: =IFERROR(AVERAGEIF(AULAS_TESTE!$F:$F,$B9,AULAS_TESTE!K:K),"") -> 7.7333333 | CA9: =IFERROR(AVERAGEIF(AULAS_TESTE!$F:$F,$B9,AULAS_TESTE!L:L),"") -> 6.8076923 | CB9: =IFERROR(AVERAGEIF(AULAS_TESTE!$F:$F,$B9,AULAS_TESTE!M:M),"") -> 8.1176471 | CC9: =IFERROR(AVERAGEIF(AULAS_TESTE!$F:$F,$B9,AULAS_TESTE!N:N),"") -> 8.3125 | CD9: =IFERROR(AVERAGEIF(AULAS_TESTE!$F:$F,$B9,AULAS_TESTE!O:O),"") -> 7.5588235 | CE9: =IFERROR(AVERAGEIF(AULAS_TESTE!$F:$F,$B9,AULAS_TESTE!P:P),"") -> 7.6875 | CF9: =IFERROR(AVERAGEIF(AULAS_TESTE!$F:$F,$B9,AULAS_TESTE!Q:Q),"") -> 7.5 | CG9: =IFERROR(AVERAGEIF(AULAS_TESTE!$F:$F,$B9,AULAS_TESTE!R:R),"") -> 6.2727273 | CH9: =IFERROR(AVERAGEIF(AULAS_TESTE!$F:$F,$B9,AULAS_TESTE!S:S),"") -> 8.0625 | CI9: =IFERROR(AVERAGEIF(AULAS_TESTE!$F:$F,$B9,AULAS_TESTE!T:T),"") -> 7.59375
A10: 0 | B10: Nome do Candidato | C10: emaildocandidato@email.com | D10: 11999999999 | E10: Química | F10: https://drive.google.com/open?id=1lySCUCg5ztV_Kq2-vXcA0VzUCIbnwxVp | G10: https://drive.google.com/open?id=1AiwSLzXo766CG1E2wli5XzSQSHIEwWk7 | H10: Eu lecionei como professor em disciplina da graduação na Ufabc, tenho publicações de artigos e prêmio de melhor apresentação de poster em congresso. | I10: Apesar de recente como professor tenho muita dedicação e gostaria da oportunidade para me aperfeiçoar cada vez mais. | J10: B1-B2 (intermediário) | L10: 12 | M10: 5.9508621 | N10: 14 | O10: 4.2979167 | P10: 5.1666667 | Q10: 2 | R10: 4.9166667 | S10: 3.1666667 | T10: 10 | U10: 7.1176471 | V10: 8 | Y10: EMEFAF | AB10: Sou um professor conteúdista gosto de passar conteúdo no quadro ou em slides, trazendo aspectos do cotidanos e fazendo comparações com a disciplina, utilizando meios digitais como vídeos, simuladores. A cada conteúdo coloco questões como forma de fixação para que os alunos compreendam o que estão aprendendo. | AC10: 17 | AD10: 5 | AE10: 12 | AF10: 6 | AG10: 12.4 | AH10: Através da resolução de exercícios ou utlizando métodos que eles expliquem com suas palavras o conteúdo aprendido. Posso realizar dinâmicas com experimentos, exercícios como forma de ponto extra para estimular aprendizagem. | AI10: 16 | AJ10: 7 | AK10: 16 | AL10: 11 | AM10: 13.775 | AN10: Dependendo do conteúdo abordado, posso utilizar mapas mentais ou até mesmo mini-testes como simulados de questões de vestibulares atuais para a fixação desse conteúdo, como flashcards ou jogos de memorização como em química orgânica para distinguir as funções orgâncas ou na própria inorgânica aulas experimentais sobre ácidos e bases. | AO10: 22 | AP10: 11 | AQ10: 20 | AR10: 10 | AS10: 17.9 | AT10: Eu gosto muito de sempre colocar o aluno em um protagonismo estudantil em um ambiente estimulante que tenha recursos didáticos como jogos ou meios digitais para auxiliar-lo. Com a disciplina da Química, podemos trazer experimentos para abordar o conteúdo. Sempre trazendo um ambiente também inclusivo para o aluno caso ele precise de uma abordagem diferente para ensino. | AU10: 7 | AV10: 1 | AW10: 11 | AX10: 11 | AY10: 7.5 | BB10: 15 | BC10: 6 | BD10: 6 | BE10: 0 | BF10: 2 | BG10: 3 | BH10: 9 | BI10: 6 | BJ10: 10 | BK10: 0.5 | BL10: 7.5 | BM10: 10 | BN10: 12 | BO10: 1 | BP10: 5 | BQ10: 2.5 | BR10: 3 | BS10: 7.5 | BT10: 15 | BV10: =IFERROR(AVERAGEIF(AULAS_TESTE!$F:$F,$B10,AULAS_TESTE!G:G),"") -> 6.7941176 | BW10: =IFERROR(AVERAGEIF(AULAS_TESTE!$F:$F,$B10,AULAS_TESTE!H:H),"") -> 7.3529412 | BX10: =IFERROR(AVERAGEIF(AULAS_TESTE!$F:$F,$B10,AULAS_TESTE!I:I),"") -> 8.1764706 | BY10: =IFERROR(AVERAGEIF(AULAS_TESTE!$F:$F,$B10,AULAS_TESTE!J:J),"") -> 7.65625 | BZ10: =IFERROR(AVERAGEIF(AULAS_TESTE!$F:$F,$B10,AULAS_TESTE!K:K),"") -> 7.7333333 | CA10: =IFERROR(AVERAGEIF(AULAS_TESTE!$F:$F,$B10,AULAS_TESTE!L:L),"") -> 6.8076923 | CB10: =IFERROR(AVERAGEIF(AULAS_TESTE!$F:$F,$B10,AULAS_TESTE!M:M),"") -> 8.1176471 | CC10: =IFERROR(AVERAGEIF(AULAS_TESTE!$F:$F,$B10,AULAS_TESTE!N:N),"") -> 8.3125 | CD10: =IFERROR(AVERAGEIF(AULAS_TESTE!$F:$F,$B10,AULAS_TESTE!O:O),"") -> 7.5588235 | CE10: =IFERROR(AVERAGEIF(AULAS_TESTE!$F:$F,$B10,AULAS_TESTE!P:P),"") -> 7.6875 | CF10: =IFERROR(AVERAGEIF(AULAS_TESTE!$F:$F,$B10,AULAS_TESTE!Q:Q),"") -> 7.5 | CG10: =IFERROR(AVERAGEIF(AULAS_TESTE!$F:$F,$B10,AULAS_TESTE!R:R),"") -> 6.2727273 | CH10: =IFERROR(AVERAGEIF(AULAS_TESTE!$F:$F,$B10,AULAS_TESTE!S:S),"") -> 8.0625 | CI10: =IFERROR(AVERAGEIF(AULAS_TESTE!$F:$F,$B10,AULAS_TESTE!T:T),"") -> 7.59375
A11: 0 | B11: Nome do Candidato | C11: emaildocandidato@email.com | D11: 11999999999 | E11: Química | F11: https://drive.google.com/open?id=1lySCUCg5ztV_Kq2-vXcA0VzUCIbnwxVp | G11: https://drive.google.com/open?id=1AiwSLzXo766CG1E2wli5XzSQSHIEwWk7 | H11: Eu lecionei como professor em disciplina da graduação na Ufabc, tenho publicações de artigos e prêmio de melhor apresentação de poster em congresso. | I11: Apesar de recente como professor tenho muita dedicação e gostaria da oportunidade para me aperfeiçoar cada vez mais. | J11: B1-B2 (intermediário) | L11: 11 | M11: 5.9560345 | N11: 13 | O11: 4.3104167 | P11: 5.1666667 | Q11: 2.0833333 | R11: 4.9166667 | S11: 3.1666667 | T11: 10 | U11: 7.1176471 | V11: 8 | Y11: EMEFAF | AB11: Sou um professor conteúdista gosto de passar conteúdo no quadro ou em slides, trazendo aspectos do cotidanos e fazendo comparações com a disciplina, utilizando meios digitais como vídeos, simuladores. A cada conteúdo coloco questões como forma de fixação para que os alunos compreendam o que estão aprendendo. | AC11: 17 | AD11: 5 | AE11: 12 | AF11: 6 | AG11: 12.4 | AH11: Através da resolução de exercícios ou utlizando métodos que eles expliquem com suas palavras o conteúdo aprendido. Posso realizar dinâmicas com experimentos, exercícios como forma de ponto extra para estimular aprendizagem. | AI11: 16 | AJ11: 8 | AK11: 16 | AL11: 11 | AM11: 13.925 | AN11: Dependendo do conteúdo abordado, posso utilizar mapas mentais ou até mesmo mini-testes como simulados de questões de vestibulares atuais para a fixação desse conteúdo, como flashcards ou jogos de memorização como em química orgânica para distinguir as funções orgâncas ou na própria inorgânica aulas experimentais sobre ácidos e bases. | AO11: 22 | AP11: 11 | AQ11: 20 | AR11: 10 | AS11: 17.9 | AT11: Eu gosto muito de sempre colocar o aluno em um protagonismo estudantil em um ambiente estimulante que tenha recursos didáticos como jogos ou meios digitais para auxiliar-lo. Com a disciplina da Química, podemos trazer experimentos para abordar o conteúdo. Sempre trazendo um ambiente também inclusivo para o aluno caso ele precise de uma abordagem diferente para ensino. | AU11: 7 | AV11: 1 | AW11: 11 | AX11: 11 | AY11: 7.5 | BB11: 15 | BC11: 6 | BD11: 6 | BE11: 0 | BF11: 2 | BG11: 3 | BH11: 9 | BI11: 6 | BJ11: 10 | BK11: 0.5 | BL11: 7.5 | BM11: 10 | BN11: 12 | BO11: 1 | BP11: 5 | BQ11: 2.5 | BR11: 3 | BS11: 7.5 | BT11: 15 | BV11: =IFERROR(AVERAGEIF(AULAS_TESTE!$F:$F,$B11,AULAS_TESTE!G:G),"") -> 6.7941176 | BW11: =IFERROR(AVERAGEIF(AULAS_TESTE!$F:$F,$B11,AULAS_TESTE!H:H),"") -> 7.3529412 | BX11: =IFERROR(AVERAGEIF(AULAS_TESTE!$F:$F,$B11,AULAS_TESTE!I:I),"") -> 8.1764706 | BY11: =IFERROR(AVERAGEIF(AULAS_TESTE!$F:$F,$B11,AULAS_TESTE!J:J),"") -> 7.65625 | BZ11: =IFERROR(AVERAGEIF(AULAS_TESTE!$F:$F,$B11,AULAS_TESTE!K:K),"") -> 7.7333333 | CA11: =IFERROR(AVERAGEIF(AULAS_TESTE!$F:$F,$B11,AULAS_TESTE!L:L),"") -> 6.8076923 | CB11: =IFERROR(AVERAGEIF(AULAS_TESTE!$F:$F,$B11,AULAS_TESTE!M:M),"") -> 8.1176471 | CC11: =IFERROR(AVERAGEIF(AULAS_TESTE!$F:$F,$B11,AULAS_TESTE!N:N),"") -> 8.3125 | CD11: =IFERROR(AVERAGEIF(AULAS_TESTE!$F:$F,$B11,AULAS_TESTE!O:O),"") -> 7.5588235 | CE11: =IFERROR(AVERAGEIF(AULAS_TESTE!$F:$F,$B11,AULAS_TESTE!P:P),"") -> 7.6875 | CF11: =IFERROR(AVERAGEIF(AULAS_TESTE!$F:$F,$B11,AULAS_TESTE!Q:Q),"") -> 7.5 | CG11: =IFERROR(AVERAGEIF(AULAS_TESTE!$F:$F,$B11,AULAS_TESTE!R:R),"") -> 6.2727273 | CH11: =IFERROR(AVERAGEIF(AULAS_TESTE!$F:$F,$B11,AULAS_TESTE!S:S),"") -> 8.0625 | CI11: =IFERROR(AVERAGEIF(AULAS_TESTE!$F:$F,$B11,AULAS_TESTE!T:T),"") -> 7.59375
A12: 0 | B12: Nome do Candidato | C12: emaildocandidato@email.com | D12: 11999999999 | E12: História | F12: https://drive.google.com/open?id=1ubUAlZW66DEIUYjh3--IbyrU9zQ0lCy3 | G12: https://drive.google.com/open?id=1Dm7C84uqq5zuKKeRMrm5HRCXG88KTcwl | H12: Sou escritor, dramaturgo, fotógrafo e arte educador, já fiz também projetos em audiovisual. | J12: B1-B2 (intermediário) | L12: 41 | M12: 4.6534483 | N12: 31 | O12: 2.8708333 | P12: 2.4166667 | Q12: 2.9166667 | R12: 3.4166667 | S12: 3.5833333 | T12: 42 | U12: 5.9117647 | V12: 9 | W12: 5.5 | X12: 6.6666667 | Y12: EMEFAF | AB12: Minha estratégia de aula é a da escola humanista. Ou seja, aulas dia ligadas com usos de várias referências dentro do universo cultural dos alunos (cultura pop, poesia, música etc) de modo a dialogar o conhecimento histórico com a atualidade. A partir desse diálogo preparo questões - a maioria discursivas - para entrega na aula seguinte e começamos a partir delas. | AC12: 4 | AD12: 4 | AE12: 8 | AF12: 6 | AG12: 5.05 | AH12: Dentro de uma proposta de ensino humanista de história há várias formas de avaliação: tem os seminários, no qual eu dou um tema para ser desenvolvido, mas a partir de uma pergunta problema, na qual eu busco ver como o grupo se coordenou, que fontes usou, o trabalho escrito, e a conclusão. E tem a avaliação escrita na qual eu sempre priorizo questões discursivas, pois entendo que o verbalizar apropria melhor os caminhos do saber. | AI12: 7 | AJ12: 17 | AK12: 15 | AL12: 10 | AM12: 10.425 | AN12: Interpretação de texto. Uso de fontes diversas. Análise crítica das fontes. Sensibilização artística e cultural. | AO12: 9 | AP12: 9 | AQ12: 7 | AR12: 13 | AS12: 9.35 | AT12: Além de professor de História, sou ator, dramaturgo, fotógrafo e escritor. Em resumo, eu vivo imerso no mundo das artes e estou me especializando em arte educação. Nesse sentido, acredito que os saberes estéticos são outras formas de criação de conhecimento - a ficção científica tá aí pra nos mostrar -, muito do que hoje chamamos filosofia, medicina nasceram junto com a religião e com a arte, então eu procuro trazer no meu fazer docente esses elementos. Eu recito cordel, e assisto Anime com os alunos e converso com eles, escuto rap na sala de aula, samba, mas não de forma gratuita. É pra mostrar que a cultura vem pela vida e vice-versa. | AU12: 9 | AV12: 5 | AW12: 11 | AX12: 14 | AY12: 9.625 | BB12: 15 | BC12: 2 | BD12: 2 | BE12: 0 | BF12: 3 | BG12: 1 | BH12: 15 | BI12: 4 | BJ12: 8 | BK12: 1.5 | BL12: 3 | BM12: 6 | BN12: 3 | BO12: 2 | BP12: 4 | BQ12: 2.5 | BR12: 9 | BS12: 4.5 | BT12: 15 | BV12: =IFERROR(AVERAGEIF(AULAS_TESTE!$F:$F,$B12,AULAS_TESTE!G:G),"") -> 6.7941176 | BW12: =IFERROR(AVERAGEIF(AULAS_TESTE!$F:$F,$B12,AULAS_TESTE!H:H),"") -> 7.3529412 | BX12: =IFERROR(AVERAGEIF(AULAS_TESTE!$F:$F,$B12,AULAS_TESTE!I:I),"") -> 8.1764706 | BY12: =IFERROR(AVERAGEIF(AULAS_TESTE!$F:$F,$B12,AULAS_TESTE!J:J),"") -> 7.65625 | BZ12: =IFERROR(AVERAGEIF(AULAS_TESTE!$F:$F,$B12,AULAS_TESTE!K:K),"") -> 7.7333333 | CA12: =IFERROR(AVERAGEIF(AULAS_TESTE!$F:$F,$B12,AULAS_TESTE!L:L),"") -> 6.8076923 | CB12: =IFERROR(AVERAGEIF(AULAS_TESTE!$F:$F,$B12,AULAS_TESTE!M:M),"") -> 8.1176471 | CC12: =IFERROR(AVERAGEIF(AULAS_TESTE!$F:$F,$B12,AULAS_TESTE!N:N),"") -> 8.3125 | CD12: =IFERROR(AVERAGEIF(AULAS_TESTE!$F:$F,$B12,AULAS_TESTE!O:O),"") -> 7.5588235 | CE12: =IFERROR(AVERAGEIF(AULAS_TESTE!$F:$F,$B12,AULAS_TESTE!P:P),"") -> 7.6875 | CF12: =IFERROR(AVERAGEIF(AULAS_TESTE!$F:$F,$B12,AULAS_TESTE!Q:Q),"") -> 7.5 | CG12: =IFERROR(AVERAGEIF(AULAS_TESTE!$F:$F,$B12,AULAS_TESTE!R:R),"") -> 6.2727273 | CH12: =IFERROR(AVERAGEIF(AULAS_TESTE!$F:$F,$B12,AULAS_TESTE!S:S),"") -> 8.0625 | CI12: =IFERROR(AVERAGEIF(AULAS_TESTE!$F:$F,$B12,AULAS_TESTE!T:T),"") -> 7.59375
A13: 0 | B13: Nome do Candidato | C13: emaildocandidato@email.com | D13: 11999999999 | E13: História | F13: https://drive.google.com/open?id=1R1nM7FNWN2R13PWFz6Lb7S9nQXN_bseT | G13: https://drive.google.com/open?id=1gOG8Jzwx5mSZ5k7PRaVTPrXO7TW8UriI | H13: Meu conhecimento na escrita (com publicações de livros e premiações literárias) e vasta experiência com storytelling são elementos agregadores à prática do ensino, pois os utilizo para potencializar o interesse dos alunos às aulas, criando um ambiente mais agradável e voltado para um processo de ensino estimulante, interativo e interessante. Também trabalhei por um tempo considerável no mercado publicitário, aprendendo técnicas de persuasão e retenção de atenção, o que é fundamental para manter o foco de crianças e adolescentes. Já ministrei algumas palestras, experiências que me auxiliaram no desenvolvimento de melhor postura. | J13: C1-C2 (avançado/fluente) | L13: 30 | M13: 5.2896552 | N13: 19 | O13: 3.6583333 | P13: 3.5 | Q13: 3 | R13: 4.75 | S13: 3.5833333 | T13: 33 | U13: 6.4411765 | V13: 5.5 | Y13: EMEFAF | AB13: Estudar História não é simplesmente analisar o passado; é estudar o passado para compreender o presente. Por essa razão, gosto de iniciar minhas aulas trazendo questões do nosso cotidiano e suas relações com o passado a ser analisado. Isso faz com o que o passado deixe de ser tão abstrato para os alunos. A partir daí, gosto de trazer elementos muito interessantes sobre as sociedades em questão, para aguçar a curiosidade e interesse dos estudantes. Então, utilizo variações de suporte para ao compartilhamento do conteúdo, como vídeos elucidativos com meus comentários, slides, análise de documentos históricos, lousa, exercícios e afins. | AC13: 2 | AD13: 6 | AE13: 15 | AF13: 5 | AG13: 5.4 | AH13: Penso que as estratégias de aferição, assim como as de ensino, devem ser variadas – afinal, cada aluno possui potencialidades distintas. Entre essas variações, implemento apresentações em grupo, seminários, produções textuais, chamadas orais, listas de exercícios, rodadas de dúvidas, além das provas habituais. Desta forma, qualquer defasagem no conteúdo apresentado será ressaltada, e poderemos trabalhar nestes pontos específicos com mais afinco. | AI13: 10 | AJ13: 9 | AK13: 14 | AL13: 11 | AM13: 10.725 | AN13: Equilíbrio é fundamental. Não há uma fórmula específica para técnicas de estudo que funcionem com a mesma eficácia para todos os alunos. Uma de nossas missões como professores é municiar os estudantes com ferramentas que funcionem para cada um deles. As técnicas podem variar entre a criação de mapas mentais, indicação de produções audiovisuais elucidativas, anotações de palavras-chave, mnemônicos, produção de pequenas canções tendo como tema os assuntos estudados, ensino do conteúdo analisado para retenção do conhecimento, debates, diálogo constante e muitas outras. | AO13: 13 | AP13: 12 | AQ13: 14 | AR13: 12 | AS13: 12.85 | AT13: Penso que a prática é a mãe da perfeição. Técnicas que funcionem com uma turma, não necessariamente darão certo com outra. Construir um ferramental teórico é fundamental para lidar com a intensa rotina docente. Entre algumas de minhas leituras na área do ensino, estão os clássicos, como Piaget e suas técnicas de construção do conhecimento por meio da autonomia do aluno; a colaboração e o uso do conhecimento social a nosso favor, como escreveu Vygotsky; a segurança, confiança e afeto no processo do ensino, descritos por Wallon; a resolução analítica e crítica de problemas, proposta por John Dewey; e o cotidiano com cada turma como farol. | AU13: 17 | AV13: 9 | AW13: 14 | AX13: 15 | AY13: 14.925 | BB13: 12 | BC13: 8 | BD13: 4 | BE13: 0 | BF13: 3 | BG13: 1 | BH13: 12 | BI13: 4 | BJ13: 4 | BK13: 1.5 | BL13: 4.5 | BM13: 8 | BN13: 6 | BO13: 2.5 | BP13: 5 | BQ13: 2.5 | BR13: 9 | BS13: 7.5 | BT13: 15 | BV13: =IFERROR(AVERAGEIF(AULAS_TESTE!$F:$F,$B13,AULAS_TESTE!G:G),"") -> 6.7941176 | BW13: =IFERROR(AVERAGEIF(AULAS_TESTE!$F:$F,$B13,AULAS_TESTE!H:H),"") -> 7.3529412 | BX13: =IFERROR(AVERAGEIF(AULAS_TESTE!$F:$F,$B13,AULAS_TESTE!I:I),"") -> 8.1764706 | BY13: =IFERROR(AVERAGEIF(AULAS_TESTE!$F:$F,$B13,AULAS_TESTE!J:J),"") -> 7.65625 | BZ13: =IFERROR(AVERAGEIF(AULAS_TESTE!$F:$F,$B13,AULAS_TESTE!K:K),"") -> 7.7333333 | CA13: =IFERROR(AVERAGEIF(AULAS_TESTE!$F:$F,$B13,AULAS_TESTE!L:L),"") -> 6.8076923 | CB13: =IFERROR(AVERAGEIF(AULAS_TESTE!$F:$F,$B13,AULAS_TESTE!M:M),"") -> 8.1176471 | CC13: =IFERROR(AVERAGEIF(AULAS_TESTE!$F:$F,$B13,AULAS_TESTE!N:N),"") -> 8.3125 | CD13: =IFERROR(AVERAGEIF(AULAS_TESTE!$F:$F,$B13,AULAS_TESTE!O:O),"") -> 7.5588235 | CE13: =IFERROR(AVERAGEIF(AULAS_TESTE!$F:$F,$B13,AULAS_TESTE!P:P),"") -> 7.6875 | CF13: =IFERROR(AVERAGEIF(AULAS_TESTE!$F:$F,$B13,AULAS_TESTE!Q:Q),"") -> 7.5 | CG13: =IFERROR(AVERAGEIF(AULAS_TESTE!$F:$F,$B13,AULAS_TESTE!R:R),"") -> 6.2727273 | CH13: =IFERROR(AVERAGEIF(AULAS_TESTE!$F:$F,$B13,AULAS_TESTE!S:S),"") -> 8.0625 | CI13: =IFERROR(AVERAGEIF(AULAS_TESTE!$F:$F,$B13,AULAS_TESTE!T:T),"") -> 7.59375
A14: 0 | B14: Nome do Candidato | C14: emaildocandidato@email.com | D14: 11999999999 | E14: História | F14: https://drive.google.com/open?id=1V-uG6OyWmrimoZF68raEXp2Y8p1VIv14 | G14: https://drive.google.com/open?id=1VGTpuh10GBU6CTwYfg943YtDsCKXVsQq | H14: Trabalhei de 2019 até 2024 no Programa de Ensino Integral da Rede Estadual de Ensino do Estado de São Paulo. Em setembro desse ano concluo o mestrado em Filosofia. | J14: A1-A2 (básico) | L14: 18 | M14: 5.7336207 | N14: 21 | O14: 3.3979167 | P14: #VALUE! | Q14: 4.5833333 | R14: 5.5833333 | S14: 4.5833333 | T14: 13 | U14: 7.3823529 | V14: 7 | W14: 4.25 | X14: 5.1666667 | Y14: EMEFAF | AB14: Adoto planejamento detalhado das aulas, com objetivos claros e estratégias ativas que favorecem a participação dos alunos. Estruturo o tempo em etapas bem definidas — apresentação, desenvolvimento e síntese — equilibrando teoria e prática. Utilizo recursos digitais e metodologias diversificadas, como debates, estudos de caso e trabalhos em grupo, para dinamizar o processo. Também faço revisões breves e diagnósticos rápidos de aprendizagem, ajustando o ritmo quando necessário, de modo a garantir foco, engajamento e melhor aproveitamento do tempo em sala. | AC14: ?? | AD14: 16 | AE14: 15 | AF14: 16 | AH14: A avaliação deve ser contínua e realizada por meio de diferentes instrumentos, como provas, seminários, debates, atividades em estações, produções textuais, entre outros. | AI14: 9 | AJ14: 3 | AK14: 8 | AL14: 6 | AM14: 7.4 | AN14: Faço questão de ensinar técnicas de leitura ativa, como grifar palavras-chave, elaborar resumos e mapas conceituais, além de estratégias de organização, como o uso de agendas e cronogramas de estudos. Incentivo a autoavaliação contínua por meio de diários de aprendizagem e revisões periódicas, para que o aluno acompanhe seu progresso. Também promovo a metacognição, orientando-os a refletirem sobre como aprendem, a reconhecerem suas dificuldades e a ajustarem suas próprias estratégias, desenvolvendo autonomia e responsabilidade no processo de aprendizagem. | AO14: 12 | AP14: 21 | AQ14: 26 | AR14: 17 | AS14: 16.675 | AT14: Minha principal forma de renovação e aperfeiçoamento é a formação acadêmica, em especial o Mestrado em Filosofia, que amplia constantemente minhas perspectivas teóricas e pedagógicas. Busco integrar a reflexão filosófica com práticas didáticas atualizadas, explorando metodologias ativas (Perrenoud, Zabala, Moran) e recursos digitais que dinamizam a sala de aula. Além disso, estudo autores como Paulo Freire, que inspiram práticas dialógicas, e Dewey, que fundamenta a aprendizagem pela experiência. | AU14: 17 | AV14: 15 | AW14: 18 | AX14: 16 | AY14: 16.7 | BB14: 15 | BC14: 2 | BD14: 6 | BE14: 0 | BF14: 3 | BG14: 3 | BH14: 15 | BI14: 4 | BJ14: 8 | BK14: 1.5 | BL14: 7.5 | BM14: 10 | BN14: 6 | BO14: 1 | BP14: 5 | BQ14: 2.5 | BR14: 15 | BS14: 6 | BT14: 15 | BV14: =IFERROR(AVERAGEIF(AULAS_TESTE!$F:$F,$B14,AULAS_TESTE!G:G),"") -> 6.7941176 | BW14: =IFERROR(AVERAGEIF(AULAS_TESTE!$F:$F,$B14,AULAS_TESTE!H:H),"") -> 7.3529412 | BX14: =IFERROR(AVERAGEIF(AULAS_TESTE!$F:$F,$B14,AULAS_TESTE!I:I),"") -> 8.1764706 | BY14: =IFERROR(AVERAGEIF(AULAS_TESTE!$F:$F,$B14,AULAS_TESTE!J:J),"") -> 7.65625 | BZ14: =IFERROR(AVERAGEIF(AULAS_TESTE!$F:$F,$B14,AULAS_TESTE!K:K),"") -> 7.7333333 | CA14: =IFERROR(AVERAGEIF(AULAS_TESTE!$F:$F,$B14,AULAS_TESTE!L:L),"") -> 6.8076923 | CB14: =IFERROR(AVERAGEIF(AULAS_TESTE!$F:$F,$B14,AULAS_TESTE!M:M),"") -> 8.1176471 | CC14: =IFERROR(AVERAGEIF(AULAS_TESTE!$F:$F,$B14,AULAS_TESTE!N:N),"") -> 8.3125 | CD14: =IFERROR(AVERAGEIF(AULAS_TESTE!$F:$F,$B14,AULAS_TESTE!O:O),"") -> 7.5588235 | CE14: =IFERROR(AVERAGEIF(AULAS_TESTE!$F:$F,$B14,AULAS_TESTE!P:P),"") -> 7.6875 | CF14: =IFERROR(AVERAGEIF(AULAS_TESTE!$F:$F,$B14,AULAS_TESTE!Q:Q),"") -> 7.5 | CG14: =IFERROR(AVERAGEIF(AULAS_TESTE!$F:$F,$B14,AULAS_TESTE!R:R),"") -> 6.2727273 | CH14: =IFERROR(AVERAGEIF(AULAS_TESTE!$F:$F,$B14,AULAS_TESTE!S:S),"") -> 8.0625 | CI14: =IFERROR(AVERAGEIF(AULAS_TESTE!$F:$F,$B14,AULAS_TESTE!T:T),"") -> 7.59375
A15: 0 | B15: Nome do Candidato | C15: emaildocandidato@email.com | D15: 11999999999 | E15: Português (Produção e Interpretação de Texto) | F15: https://drive.google.com/open?id=12YAp6H1zHZvozwtX8TI_3BT-55glGaH5 | G15: https://drive.google.com/open?id=1xzYN9fRWNZY1Pr2Ljy4ErYx9FPEx9RzV | H15: Ter trabalhado durante a graduação superior em projeto extensionista para melhorar a escrita entre profissionais de Letras em decorrência da minha vivência como jornalista; ter trabalhado no início da implantação da Escola Viva no ES no primeiro mandato do governador Casagrande; ter podido entrevistas grandes personalidades sempre sem o uso do gravador, o que me desenvolveu um poder de síntese anotada que me ajudava muito na fruição do desenvolvimento do meu estilo textual. | J15: B1-B2 (intermediário) | L15: 24 | M15: 5.7396552 | N15: 20 | O15: 3.8291667 | P15: 3.5 | Q15: 3.75 | R15: 4.4166667 | S15: 4.25 | T15: 26 | U15: 7.0882353 | V15: 5.5 | Y15: EMEFAF | AB15: Atualmente, tenho empregado IA para avanço em tempo hábil em Literatura, além disso exploro bastante metodologias ativas como forma de envolver os alunos em torno da matéria, em especial Gramática, a parte científica da Língua Portuguesa. | AC15: 8 | AD15: 7 | AE15: 8 | AF15: 6 | AG15: 7.5 | AH15: Adoto diagnósticas para mensurar o nível de conteúdo da turma no início do ano letivo, como forma de nivelar em conformidade com a graduação alcançada, durante, com o objetivo de confirmar o aprendizado, e ao final, tendo a certeza da consolidação de conhecimento. | AI15: 9 | AJ15: 4 | AK15: 10 | AL15: 7 | AM15: 8.075 | AN15: Fichamentos de pontos chaves para garantir coesões sequenciais, por exemplo, com cartões de conjunções para facilitar o emprego de conectivos de desenvolvimento e conclusão, esquelamento-textual, para forjar a estrutura no cotidiano das aulas, e mapas mentais em aulas expositivas para que o alunado colabore com seu raciocínio próprio no desenvolvimento teórico. | AO15: 9 | AP15: 24 | AQ15: 21 | AR15: 20 | AS15: 15.275 | AT15: Inspiro-me bastante no Dr. Sírio Possenti, a partir da leitura do livro "Por que não escrever Gramática na Escola", tendo confirmação certeira de que sou um professor gramatiqueiro, e em Evanildo Bechara (em memória), que pregou: tão importante quanto os mecanismos linguísticos é a leitura de bons escritores, aproveitando vossas estruturas para comunicar bem no papel. Adoto bastante os métodos de refacções textuais a partir da fala de Bechara. | AU15: 16 | AV15: 10 | AW15: 14 | AX15: 18 | AY15: 15.1 | BB15: 15 | BC15: 2 | BD15: 2 | BE15: 0 | BF15: 1 | BG15: 5 | BH15: 15 | BI15: 2 | BJ15: 10 | BK15: 0.5 | BL15: 7.5 | BM15: 10 | BN15: 3 | BO15: 2.5 | BP15: 5 | BQ15: 2.5 | BR15: 15 | BS15: 7.5 | BT15: 15 | BV15: =IFERROR(AVERAGEIF(AULAS_TESTE!$F:$F,$B15,AULAS_TESTE!G:G),"") -> 6.7941176 | BW15: =IFERROR(AVERAGEIF(AULAS_TESTE!$F:$F,$B15,AULAS_TESTE!H:H),"") -> 7.3529412 | BX15: =IFERROR(AVERAGEIF(AULAS_TESTE!$F:$F,$B15,AULAS_TESTE!I:I),"") -> 8.1764706 | BY15: =IFERROR(AVERAGEIF(AULAS_TESTE!$F:$F,$B15,AULAS_TESTE!J:J),"") -> 7.65625 | BZ15: =IFERROR(AVERAGEIF(AULAS_TESTE!$F:$F,$B15,AULAS_TESTE!K:K),"") -> 7.7333333 | CA15: =IFERROR(AVERAGEIF(AULAS_TESTE!$F:$F,$B15,AULAS_TESTE!L:L),"") -> 6.8076923 | CB15: =IFERROR(AVERAGEIF(AULAS_TESTE!$F:$F,$B15,AULAS_TESTE!M:M),"") -> 8.1176471 | CC15: =IFERROR(AVERAGEIF(AULAS_TESTE!$F:$F,$B15,AULAS_TESTE!N:N),"") -> 8.3125 | CD15: =IFERROR(AVERAGEIF(AULAS_TESTE!$F:$F,$B15,AULAS_TESTE!O:O),"") -> 7.5588235 | CE15: =IFERROR(AVERAGEIF(AULAS_TESTE!$F:$F,$B15,AULAS_TESTE!P:P),"") -> 7.6875 | CF15: =IFERROR(AVERAGEIF(AULAS_TESTE!$F:$F,$B15,AULAS_TESTE!Q:Q),"") -> 7.5 | CG15: =IFERROR(AVERAGEIF(AULAS_TESTE!$F:$F,$B15,AULAS_TESTE!R:R),"") -> 6.2727273 | CH15: =IFERROR(AVERAGEIF(AULAS_TESTE!$F:$F,$B15,AULAS_TESTE!S:S),"") -> 8.0625 | CI15: =IFERROR(AVERAGEIF(AULAS_TESTE!$F:$F,$B15,AULAS_TESTE!T:T),"") -> 7.59375
A16: 0 | B16: Nome do Candidato | C16: emaildocandidato@email.com | D16: 11999999999 | E16: Matemática | F16: https://drive.google.com/open?id=1VrvXw6AilScsfz9gQBRBhnHjnYD6j_s5 | G16: https://drive.google.com/open?id=13ho83ESHRrmtxxXp8DEAUgAkFWo0P2w2 | H16: Palestras sobre acessibilidade na educação pelo SESI | J16: C1-C2 (avançado/fluente) | L16: 12 | M16: 6.4086207 | N16: 20 | O16: 4.1541667 | P16: 3.75 | Q16: 3.9166667 | R16: 5.3333333 | S16: 4.3333333 | T16: 2 | U16: 8 | Y16: EMEFAF | AB16: Quando há material didático adotado pela escola me apoio nele ao realizar um bom planejamento. Quando a escola decide não adotar um material didático, utilizo slides autorais e listas de atividades. Priorizo que os exercícios de fixação estejam divididos entre aula e casa e as situações problemas sejam realizadas majoritariamente em aula. Isso faz com que as dúvidas estejam solucionadas antes dos períodos de prova. | AC16: 9 | AD16: 9 | AE16: 12 | AF16: 11 | AG16: 9.875 | AH16: Defino pelo menos 3 etapas de avaliações formais de acordo com o estabelecido com a gestão escolar diagnóstica (geralmente uma atividade escrita com pontos extras com uma pontuação propositalmente baixa); uma avaliação parcial e uma avaliação final. Além disso, ao longo do trimestre ou bimestre realizo atividades como mapas mentais, resumos, atividades que façam os alunos explicarem seus aprendizados e isso nortea o processo avaliativo. | AI16: 19 | AJ16: 13 | AK16: 15 | AL16: 15 | AM16: 16.7 | AN16: Técnica de soluções de problemas matemáticos, reviso isso em todas as salas pelo menos uma vez no ano. É uma técnica voltada para concurseiros e vestibulandos, mas adaptável para o ensino fundamental I I faz com que o desenvolvimento das crianças cresça bastante. Além de estimular a melhora em outros conteúdos. Consiste em analisar itens e interpretar o problema antes de iniciar as contas. Observar se é ou não uma questão com "pegadinha" e qual a melhor forma de responder ou executar o que se pede. Também gosto muito de trabalhar de forma pontual aprendizagem significativa com eles, trazendo o mundo deles para a sala de aula. | AO16: 8 | AP16: 18 | AQ16: 21 | AR16: 14 | AS16: 12.825 | AT16: Isso depende das condições de trabalho, não acredito que determinada teoria de aprendizagem seja melhor do que outra, mas as escolas tem prioridades e públicos distintos. Como profissional da educação já trabalhei com ABP ou PBL (aprendizagem baseada em projetos); com a abordagem de Reggio Emília; com abordagem montessoriana para pessoas com deficiência; com acessibilidade atitudinal da Renders; com aprendizagem significativa; com aprendizagem visível do John Hatite; Sendo o mais importante e minha prioridade o respeito as crianças durante esse momento de desenvolvimento delas. | AU16: 9 | AV16: 7 | AW16: 16 | AX16: 12 | AY16: 10.45 | BB16: 15 | BC16: 4 | BD16: 6 | BE16: 0 | BF16: 3 | BG16: 2 | BH16: 15 | BI16: 6 | BJ16: 8 | BK16: 1.5 | BL16: 6 | BM16: 10 | BN16: 15 | BO16: 2.5 | BP16: 5 | BQ16: 2.5 | BR16: 12 | BS16: 7.5 | BT16: 15 | BV16: =IFERROR(AVERAGEIF(AULAS_TESTE!$F:$F,$B16,AULAS_TESTE!G:G),"") -> 6.7941176 | BW16: =IFERROR(AVERAGEIF(AULAS_TESTE!$F:$F,$B16,AULAS_TESTE!H:H),"") -> 7.3529412 | BX16: =IFERROR(AVERAGEIF(AULAS_TESTE!$F:$F,$B16,AULAS_TESTE!I:I),"") -> 8.1764706 | BY16: =IFERROR(AVERAGEIF(AULAS_TESTE!$F:$F,$B16,AULAS_TESTE!J:J),"") -> 7.65625 | BZ16: =IFERROR(AVERAGEIF(AULAS_TESTE!$F:$F,$B16,AULAS_TESTE!K:K),"") -> 7.7333333 | CA16: =IFERROR(AVERAGEIF(AULAS_TESTE!$F:$F,$B16,AULAS_TESTE!L:L),"") -> 6.8076923 | CB16: =IFERROR(AVERAGEIF(AULAS_TESTE!$F:$F,$B16,AULAS_TESTE!M:M),"") -> 8.1176471 | CC16: =IFERROR(AVERAGEIF(AULAS_TESTE!$F:$F,$B16,AULAS_TESTE!N:N),"") -> 8.3125 | CD16: =IFERROR(AVERAGEIF(AULAS_TESTE!$F:$F,$B16,AULAS_TESTE!O:O),"") -> 7.5588235 | CE16: =IFERROR(AVERAGEIF(AULAS_TESTE!$F:$F,$B16,AULAS_TESTE!P:P),"") -> 7.6875 | CF16: =IFERROR(AVERAGEIF(AULAS_TESTE!$F:$F,$B16,AULAS_TESTE!Q:Q),"") -> 7.5 | CG16: =IFERROR(AVERAGEIF(AULAS_TESTE!$F:$F,$B16,AULAS_TESTE!R:R),"") -> 6.2727273 | CH16: =IFERROR(AVERAGEIF(AULAS_TESTE!$F:$F,$B16,AULAS_TESTE!S:S),"") -> 8.0625 | CI16: =IFERROR(AVERAGEIF(AULAS_TESTE!$F:$F,$B16,AULAS_TESTE!T:T),"") -> 7.59375
A17: 0 | B17: Nome do Candidato | C17: emaildocandidato@email.com | D17: 11999999999 | E17: História | F17: https://drive.google.com/open?id=1JVz7r42vuBx8hwy5thSDY6hBIWqHEwZK | G17: https://drive.google.com/open?id=1h99OvSsDSV4uKgTkEhiKsYFXJLncdaIb | H17: Curso de especialização que dão base teórica robusta para desenvolvimento daas aulas e cursos de extensão que permitem acesso rápido e prático a perspectivas de aprendizagem. | J17: A1-A2 (básico) | L17: 12 | M17: 5.9137931 | N17: 15 | O17: 4.2916667 | P17: 4.0833333 | Q17: 3.3333333 | R17: 5.6666667 | S17: 4.3333333 | T17: 24 | U17: 7.0588235 | V17: 6.5 | W17: 3.25 | X17: 4.3333333 | Y17: EMEFAF | AB17: Planejamento de aula com previsão para intervenção e interação dos estudantes; rotero pré definido do que será abordado e com quais recursos; comunicação objetiva e rotina de acompanhamento da evolução da aprendizagem. | AC17: 19 | AD17: 16 | AE17: 15 | AF17: 14 | AG17: 16.975 | AH17: Costumo aplicar métododos diversificados para obter um panorama mais completo. Avaliação formativa (para identificar possiveis dificuldades e conhecimento prévio dos estudantes); Avaliação formativa, para verificar o que se aprendeu de cada etapa de ensino-aprendizagem (podendo ser obtida pos avaliações, pesquisas e projetos); Avaliação diagnóstica, afim de avaliar o desenvolviento dos estudates e o que foi consolidado dos estudos. Todo processo instrumentalizados pelos diferentes recursos como produção textual, pesquisa, interpretação de imagens, uso de mapas, abordagem baseada em problemas e projetos. | AI17: 8 | AJ17: 9 | AK17: 16 | AL17: 10 | AM17: 9.9 | AN17: Estimular os estudantes a uma capacidade de gerir melhor seu tempo e aprendizado estimulando a curisidade crítica (para que aprender) e ao desenvolvimento e engajamento sobre seu conhecimento adquirido (o que faço com que aprendi). Estimular o protagonismo e o autogestão do conhecimento são fundamentais para colaboração entre estudantes e professores. Isto passa por metodologias ativas, escuta ativa (sobre como os estudantes aprendem); senso crítico (sempre estimulando a pensar sobre o pensamento e reflexão sobre nossa realidade e possibilidades). | AO17: 4 | AP17: 11 | AQ17: 23 | AR17: 13 | AS17: 9.95 | AT17: Para o desenvolvimento de habilidades docentes, penso que é importante estar interado dos recursos tecnológicos, discutir sobre o mundo do trabalho, dar atenção ao desenvolvimento socioemocional tanto quanto ao desenvolvimento cognitivo, buscar cursos e trocas com colegas de trabalho sobretudo para o aprendizado interdisciplinar e manter-se atualizado e alinhado com o método da instituição. | AU17: 18 | AV17: 4 | AW17: 14 | AX17: 15 | AY17: 14.675 | BB17: 15 | BC17: 4 | BD17: 4 | BE17: 0 | BF17: 3 | BG17: 5 | BH17: 15 | BI17: 4 | BJ17: 10 | BK17: 1.5 | BL17: 4.5 | BM17: 10 | BN17: 3 | BO17: 2 | BP17: 5 | BQ17: 2.5 | BR17: 9 | BS17: 7.5 | BT17: 15 | BV17: =IFERROR(AVERAGEIF(AULAS_TESTE!$F:$F,$B17,AULAS_TESTE!G:G),"") -> 6.7941176 | BW17: =IFERROR(AVERAGEIF(AULAS_TESTE!$F:$F,$B17,AULAS_TESTE!H:H),"") -> 7.3529412 | BX17: =IFERROR(AVERAGEIF(AULAS_TESTE!$F:$F,$B17,AULAS_TESTE!I:I),"") -> 8.1764706 | BY17: =IFERROR(AVERAGEIF(AULAS_TESTE!$F:$F,$B17,AULAS_TESTE!J:J),"") -> 7.65625 | BZ17: =IFERROR(AVERAGEIF(AULAS_TESTE!$F:$F,$B17,AULAS_TESTE!K:K),"") -> 7.7333333 | CA17: =IFERROR(AVERAGEIF(AULAS_TESTE!$F:$F,$B17,AULAS_TESTE!L:L),"") -> 6.8076923 | CB17: =IFERROR(AVERAGEIF(AULAS_TESTE!$F:$F,$B17,AULAS_TESTE!M:M),"") -> 8.1176471 | CC17: =IFERROR(AVERAGEIF(AULAS_TESTE!$F:$F,$B17,AULAS_TESTE!N:N),"") -> 8.3125 | CD17: =IFERROR(AVERAGEIF(AULAS_TESTE!$F:$F,$B17,AULAS_TESTE!O:O),"") -> 7.5588235 | CE17: =IFERROR(AVERAGEIF(AULAS_TESTE!$F:$F,$B17,AULAS_TESTE!P:P),"") -> 7.6875 | CF17: =IFERROR(AVERAGEIF(AULAS_TESTE!$F:$F,$B17,AULAS_TESTE!Q:Q),"") -> 7.5 | CG17: =IFERROR(AVERAGEIF(AULAS_TESTE!$F:$F,$B17,AULAS_TESTE!R:R),"") -> 6.2727273 | CH17: =IFERROR(AVERAGEIF(AULAS_TESTE!$F:$F,$B17,AULAS_TESTE!S:S),"") -> 8.0625 | CI17: =IFERROR(AVERAGEIF(AULAS_TESTE!$F:$F,$B17,AULAS_TESTE!T:T),"") -> 7.59375
A18: 0 | B18: Nome do Candidato | C18: emaildocandidato@email.com | D18: 11999999999 | E18: História | F18: https://drive.google.com/open?id=1fPFN2ncylLn3iK89Al7LKk8u1OqCeKXU | G18: https://drive.google.com/open?id=1U5Ks7g_xi3L6GkybI0nFINYio-jQYASX | J18: C1-C2 (avançado/fluente) | L18: 19 | M18: 5.7310345 | N18: 20 | O18: 3.6416667 | P18: 3 | Q18: 3 | R18: 5.5833333 | S18: 4.0833333 | T18: 18 | U18: 7.2058824 | V18: 8 | W18: 4.75 | X18: 5.8333333 | Y18: EMEFAF | AB18: Utilizo recursos de mídia quando pertinente para melhor representar os assuntos sendo ensinados aos alunos, com um foco na abordagem crítica da sala de aula de modo a melhorar as habilidades de multiletramento dos estudantes. Reservo períodos dentro da aula para que os alunos possam interagir de forma guiada e ativa tanto comigo enquanto professor quanto com seus colegas. O objetivo deste método é estimular a aplicação e discução do conteúdo apresentado, o levantamento de dúvidas e a melhor integração do conhecimento no repertório dos estudantes através da interação prática com a disciplina. | AC18: 9 | AD18: 8 | AE18: 12 | AF18: 10 | AG18: 9.55 | AH18: Me utilizo de pequenos questionamentos retomando temas abordadas em aulas anteriores e com relevância no contexto da aula presente. Por exemplo: durante uma aula que tocano trabaho servil medieva, pergunto por uma instituição romana que pode ter influenciado a formação da servidão e que características dessa instituição a servidão carrega. A ideia sendo que se os alunos de fato internalizaram o conteúdo de Roma e não precisam de uma revisão aprofunda, eles podem relacionar coisas como o colonato, com fazendeiros prezos a terra, e o clientelismo, com relações de submição política e troca de favores, com a servidão medieval apresentada em sala, | AI18: 13 | AJ18: 16 | AK18: 15 | AL18: 13 | AM18: 13.8 | AN18: Minha primeira técnica essencial é do imediatismo do estudo, ou seja, matéria dada é matéria estudada hoje. É importante que após o período de aula, mesmo que por apenas quinze minutos, o aluno revise o conteúdo estudado no dia pois isto ajuda na fixação da matéria de longo prazo e tornna estudos posteriores e mais aprofundados mais fáceis. A segunda técnica envolve buscar, quando possível, material de estudo, como vídeos e livros, que o aluno possa relaconar à própria vida ou que ao menos acha interessante. Mesmo um aluno dedicado tem dificuldade de estudar uma matéria que a todo momento parece não apenas chata, mas inútil. | AO18: 11 | AP18: 6 | AQ18: 20 | AR18: 10 | AS18: 11.65 | AT18: É vital que eu observe e estude o engajamento dos alunos em sala. Não há duas turmas que operem na mesma exata dinâmica, logo a metodologia quefunciona em uma não funcionará na outra. Portanto, me atento para se os alunos estão participando da aula e se prestam atenção. Se uma sala lida melhor com projeções de Power Point, eu trago prrojeções, se preferem a loua escrita, uso a lousa. Se precisam de um momento de descontração de vez em quando, ofereço este momnto; mas se demoram para retornar ao tema uma vez que ocorre a descontração, já não a utilizo. A ideia é ir se adaptando de sala à sala. | AU18: 3 | AV18: 6 | AW18: 20 | AX18: 16 | AY18: 8.7 | BB18: 12 | BC18: 4 | BD18: 2 | BE18: 0 | BF18: 2 | BG18: 4 | BH18: 15 | BI18: 6 | BJ18: 8 | BK18: 1.5 | BL18: 6 | BM18: 6 | BN18: 9 | BO18: 2 | BP18: 5 | BQ18: 2.5 | BR18: 15 | BS18: 7.5 | BT18: 15 | BV18: =IFERROR(AVERAGEIF(AULAS_TESTE!$F:$F,$B18,AULAS_TESTE!G:G),"") -> 6.7941176 | BW18: =IFERROR(AVERAGEIF(AULAS_TESTE!$F:$F,$B18,AULAS_TESTE!H:H),"") -> 7.3529412 | BX18: =IFERROR(AVERAGEIF(AULAS_TESTE!$F:$F,$B18,AULAS_TESTE!I:I),"") -> 8.1764706 | BY18: =IFERROR(AVERAGEIF(AULAS_TESTE!$F:$F,$B18,AULAS_TESTE!J:J),"") -> 7.65625 | BZ18: =IFERROR(AVERAGEIF(AULAS_TESTE!$F:$F,$B18,AULAS_TESTE!K:K),"") -> 7.7333333 | CA18: =IFERROR(AVERAGEIF(AULAS_TESTE!$F:$F,$B18,AULAS_TESTE!L:L),"") -> 6.8076923 | CB18: =IFERROR(AVERAGEIF(AULAS_TESTE!$F:$F,$B18,AULAS_TESTE!M:M),"") -> 8.1176471 | CC18: =IFERROR(AVERAGEIF(AULAS_TESTE!$F:$F,$B18,AULAS_TESTE!N:N),"") -> 8.3125 | CD18: =IFERROR(AVERAGEIF(AULAS_TESTE!$F:$F,$B18,AULAS_TESTE!O:O),"") -> 7.5588235 | CE18: =IFERROR(AVERAGEIF(AULAS_TESTE!$F:$F,$B18,AULAS_TESTE!P:P),"") -> 7.6875 | CF18: =IFERROR(AVERAGEIF(AULAS_TESTE!$F:$F,$B18,AULAS_TESTE!Q:Q),"") -> 7.5 | CG18: =IFERROR(AVERAGEIF(AULAS_TESTE!$F:$F,$B18,AULAS_TESTE!R:R),"") -> 6.2727273 | CH18: =IFERROR(AVERAGEIF(AULAS_TESTE!$F:$F,$B18,AULAS_TESTE!S:S),"") -> 8.0625 | CI18: =IFERROR(AVERAGEIF(AULAS_TESTE!$F:$F,$B18,AULAS_TESTE!T:T),"") -> 7.59375
A19: 0 | B19: Nome do Candidato | C19: emaildocandidato@email.com | D19: 11999999999 | E19: História | F19: https://drive.google.com/open?id=1t8NYgyfSFXC6r_kgznnR0Hg_2B4lMQZM | G19: https://drive.google.com/open?id=1qZQW6eiMeshUOQNKh_BSuM4ZrvcZM6hu | H19: Olá, possuo Doutorado em Ciências Humanas pela USP; MBA em Gestão de Pessoas, Licenciatura Plena em História, Geografia e Filosofia; graduação em Pedagogia. Atuei como Editor de Publicações; com 23 anos experiência docente e administrativa no Ensino Superior, Fundamental II, Médio e Técnico Profissionalizante. Exerci também atividades como pesquisador da FAPESP e assessoria para instituições de Ensino Superior para o aprimoramento do desempenho no ENADE e para Educação Básica voltada ao desenvolvimento do Novo Ensino Médio (Lei n 13.415/2017 - Nova BNCC). Colaborei com programas de TV, rádio, revistas e jornais. Recebi um Prêmio Jabuti; um Casa Grande e Senzala; dois Padre Geraldo Magela para práticas inovadoras em sala de aula; um Mérito Docente; e uma Menção Honrosa da USP. Tenho 18 livros e mais de 200 artigos publicados; constantemente citados e objeto de questões de vestibulares e concursos públicos. Em anexo segue currículo para análise. Estou a disposição para colaborar com a formação dos alunos da escola. Grato: Prof. Dr. Fábio Pestana Ramos. | J19: A1-A2 (básico) | L19: 44 | M19: 4.5672414 | N19: 49 | O19: 0.9125 | P19: 0.58333333 | Q19: 0.25 | R19: 2.1666667 | S19: 1.1666667 | T19: 20 | U19: 7.1470588 | V19: 7 | W19: 8.25 | X19: 7.8333333 | Y19: EMEFAF | AB19: Aula teórica, atividades em sala, correção da tarefa para Casa. | AC19: 3 | AD19: 0 | AE19: 5 | AF19: 4 | AG19: 3.075 | AH19: Observação e processo de avaliação diversificado. | AI19: 2 | AJ19: 0 | AK19: 5 | AL19: 4 | AM19: 2.575 | AN19: Verificações de aprendizagem e revisão se necessário. | AO19: 2 | AP19: 2 | AQ19: 11 | AR19: 3 | AS19: 3.75 | AT19: Reciclagem teórica. | AU19: 0 | AV19: 1 | AW19: 5 | AX19: 3 | AY19: 1.55 | BB19: 15 | BC19: 4 | BD19: 6 | BE19: 0 | BF19: 3 | BG19: 5 | BH19: 15 | BI19: 8 | BJ19: 6 | BK19: 0.5 | BL19: 7.5 | BM19: 10 | BN19: 3 | BO19: 2.5 | BP19: 5 | BQ19: 2.5 | BR19: 6 | BS19: 7.5 | BT19: 15 | BV19: =IFERROR(AVERAGEIF(AULAS_TESTE!$F:$F,$B19,AULAS_TESTE!G:G),"") -> 6.7941176 | BW19: =IFERROR(AVERAGEIF(AULAS_TESTE!$F:$F,$B19,AULAS_TESTE!H:H),"") -> 7.3529412 | BX19: =IFERROR(AVERAGEIF(AULAS_TESTE!$F:$F,$B19,AULAS_TESTE!I:I),"") -> 8.1764706 | BY19: =IFERROR(AVERAGEIF(AULAS_TESTE!$F:$F,$B19,AULAS_TESTE!J:J),"") -> 7.65625 | BZ19: =IFERROR(AVERAGEIF(AULAS_TESTE!$F:$F,$B19,AULAS_TESTE!K:K),"") -> 7.7333333 | CA19: =IFERROR(AVERAGEIF(AULAS_TESTE!$F:$F,$B19,AULAS_TESTE!L:L),"") -> 6.8076923 | CB19: =IFERROR(AVERAGEIF(AULAS_TESTE!$F:$F,$B19,AULAS_TESTE!M:M),"") -> 8.1176471 | CC19: =IFERROR(AVERAGEIF(AULAS_TESTE!$F:$F,$B19,AULAS_TESTE!N:N),"") -> 8.3125 | CD19: =IFERROR(AVERAGEIF(AULAS_TESTE!$F:$F,$B19,AULAS_TESTE!O:O),"") -> 7.5588235 | CE19: =IFERROR(AVERAGEIF(AULAS_TESTE!$F:$F,$B19,AULAS_TESTE!P:P),"") -> 7.6875 | CF19: =IFERROR(AVERAGEIF(AULAS_TESTE!$F:$F,$B19,AULAS_TESTE!Q:Q),"") -> 7.5 | CG19: =IFERROR(AVERAGEIF(AULAS_TESTE!$F:$F,$B19,AULAS_TESTE!R:R),"") -> 6.2727273 | CH19: =IFERROR(AVERAGEIF(AULAS_TESTE!$F:$F,$B19,AULAS_TESTE!S:S),"") -> 8.0625 | CI19: =IFERROR(AVERAGEIF(AULAS_TESTE!$F:$F,$B19,AULAS_TESTE!T:T),"") -> 7.59375
A20: 0 | B20: Nome do Candidato | C20: emaildocandidato@email.com | D20: 11999999999 | E20: Português (Literatura) | F20: https://drive.google.com/open?id=1CFvf3ddGH8lJ9dspVEqs1Rh1a5BEyjnb | G20: https://drive.google.com/open?id=1GzIXdPY73Msj1gEsY0_fPFmszWeoy1Nh | H20: Fui professoras voluntária de Literatura em curso popular pré-Enem e vestibulares e atuo junto à Univesp como facilitadora, trabalho no qual auxilio futuros professores de Língua Portuguesa a planejar aulas, atividades, aferir aprendizagem e evidenciar resultados. | J20: B1-B2 (intermediário) | L20: 3 | M20: 6.5948276 | N20: 2 | O20: 5.2291667 | P20: 4.6666667 | Q20: 4.9166667 | R20: 6.5833333 | S20: 5.75 | T20: 2 | U20: 7.5588235 | V20: 5.5 | Y20: EMEFAF | AB20: Proponho combinados com relação a momentos de conversa paralela, procurando reduzir interrupções para tratar dessas questões, divido as aulas em sessões pré-determinadas (introdução ao assunto, levantamento de conhecimento prévio, abordagem teórica, exercícios, correção, síntese etc.) e faço acompanhamento individual de rendimento dos alunos a fim de evitar que as dúvidas se acumulem. Ao solicitar a resolução de exercícios, por exemplo, sugiro uma quantidade específica de minutos para a sua realização. | AC20: 22 | AD20: 15 | AE20: 22 | AF20: 20 | AG20: 20.6 | AH20: Busco evidenciar a aprendizagem de conceitos e do exercício de habilidades sempre que possível de modo a tornar a evolução do aluno algo nítido para qualquer pessoa que se propuser a acompanhar o processo. Para tanto, utilizo estratégias como comparação entre dois momentos de aplicação de conceito, atividades que permitam o uso do conceito ou habilidade em contextos mais amplos e tarefas que ajudem o aluno a destacar e sintetizar os principais pontos do assunto. Todos os quesitos a serem avaliados são baseados nas indicações da BNCC. | AI20: 5 | AJ20: 13 | AK20: 14 | AL20: 10 | AM20: 8.65 | AN20: Faço questão de que meus alunos sejam hábeis em criar explicações e exemplos pessoais sobre os conceitos a fim de que a aprendizagem se torne eficaz e significativa. Para tarefas dissertativas, não abro mão da prática do planejamento e da revisão textual, etapas fundamentais para a construção de uma mensagem eficiente. | AO20: 12 | AP20: 23 | AQ20: 23 | AR20: 17 | AS20: 16.45 | AT20: Procuro preparar minhas aulas tendo em vista a questão dos multiletramentos, a exemplo do que propôs Maria Helena de Moura Neves, Magda Soares e Roxane Rojo. Ao usá-los, o objetivo é o de que meus alunos se tornem poliglotas dentro de sua própria língua, sendo hábeis na escolha dos repertórios ideiais para se atingir o objetivo proposto. Para literatura, tenho me baseado nas pesquisas realizadas por José Nicolau Gregorin e Vima Lia de Rossi Martin, cuja frente principal foi/é a investigação quanto à ressignificação da literatura para as novas gerações. | AU20: 17 | AV20: 8 | AW20: 20 | AX20: 22 | AY20: 17.05 | BB20: 12 | BC20: 6 | BD20: 6 | BE20: 0 | BF20: 4 | BG20: 3 | BH20: 15 | BI20: 8 | BJ20: 10 | BK20: 2.5 | BL20: 6 | BM20: 6 | BN20: 9 | BO20: 2 | BP20: 5 | BQ20: 2.5 | BR20: 9 | BS20: 7.5 | BT20: 15 | BV20: =IFERROR(AVERAGEIF(AULAS_TESTE!$F:$F,$B20,AULAS_TESTE!G:G),"") -> 6.7941176 | BW20: =IFERROR(AVERAGEIF(AULAS_TESTE!$F:$F,$B20,AULAS_TESTE!H:H),"") -> 7.3529412 | BX20: =IFERROR(AVERAGEIF(AULAS_TESTE!$F:$F,$B20,AULAS_TESTE!I:I),"") -> 8.1764706 | BY20: =IFERROR(AVERAGEIF(AULAS_TESTE!$F:$F,$B20,AULAS_TESTE!J:J),"") -> 7.65625 | BZ20: =IFERROR(AVERAGEIF(AULAS_TESTE!$F:$F,$B20,AULAS_TESTE!K:K),"") -> 7.7333333 | CA20: =IFERROR(AVERAGEIF(AULAS_TESTE!$F:$F,$B20,AULAS_TESTE!L:L),"") -> 6.8076923 | CB20: =IFERROR(AVERAGEIF(AULAS_TESTE!$F:$F,$B20,AULAS_TESTE!M:M),"") -> 8.1176471 | CC20: =IFERROR(AVERAGEIF(AULAS_TESTE!$F:$F,$B20,AULAS_TESTE!N:N),"") -> 8.3125 | CD20: =IFERROR(AVERAGEIF(AULAS_TESTE!$F:$F,$B20,AULAS_TESTE!O:O),"") -> 7.5588235 | CE20: =IFERROR(AVERAGEIF(AULAS_TESTE!$F:$F,$B20,AULAS_TESTE!P:P),"") -> 7.6875 | CF20: =IFERROR(AVERAGEIF(AULAS_TESTE!$F:$F,$B20,AULAS_TESTE!Q:Q),"") -> 7.5 | CG20: =IFERROR(AVERAGEIF(AULAS_TESTE!$F:$F,$B20,AULAS_TESTE!R:R),"") -> 6.2727273 | CH20: =IFERROR(AVERAGEIF(AULAS_TESTE!$F:$F,$B20,AULAS_TESTE!S:S),"") -> 8.0625 | CI20: =IFERROR(AVERAGEIF(AULAS_TESTE!$F:$F,$B20,AULAS_TESTE!T:T),"") -> 7.59375
A21: 0 | B21: Nome do Candidato | C21: emaildocandidato@email.com | D21: 11999999999 | E21: Português (Literatura) | F21: https://drive.google.com/open?id=1CUUzfMjcDHWmWp5DR1FP9EzJZKHIbh_T | G21: https://drive.google.com/open?id=1sd6NhPWIS8k6veFPgwR9pD_xLx8Mfrdv | H21: Ministro aulas sobre os livros literários exigidos pela FUVEST e UNICAMP. | J21: A1-A2 (básico) | L21: 2 | M21: 6.6181034 | N21: 1 | O21: 5.3270833 | P21: 5.3333333 | Q21: 4.4166667 | R21: 6.25 | S21: 5.1666667 | T21: 3 | U21: 7.5294118 | Y21: EMEFAF | AB21: Nas aulas de Literatura, busco organizar o tempo de maneira produtiva por meio de um planejamento cuidadosamente estruturado. Explicitação dialogada dos objetivos e do conteúdo, propostas que incentivem a análise crítica e a aplicação do que foi discutido visando a compreensão do aluno sobre o percurso estimulado em sala de aula. Visando a uma participação ativa e reflexiva dos estudantes, valho-me de estratégias didáticas que incentivem a interação e o pensamento crítico. Leitura orientada de trechos literários, perguntas norteadoras, atividades de comparação e interpretação. | AC21: 13 | AD21: 12 | AE21: 15 | AF21: 11 | AG21: 12.85 | AH21: Utilizo formas variadas de avaliação contínua, integradas ao próprio andamento das aulas. A verificação da aprendizagem não se limita a provas ou atividades formais, mas ocorre também por meio de observações e interações constantes. Aplicação de estratégias diagnósticas informais — como perguntas abertas, retomadas orais e intervenções pontuais — permitem avaliar se os estudantes compreendem os conceitos e conseguem relacioná-los ao que já foi estudado. Momentos de análises de trechos literários servem não apenas para estimular o pensamento crítico, mas também para aferir a qualidade das interpretações e a articulação das ideias. | AI21: 18 | AJ21: 11 | AK21: 17 | AL21: 14 | AM21: 16.075 | AN21: Na condução das aulas de literatura, adoto métodos que estimulam a autonomia e a criticidade dos alunos. Por exemplo: 1. Leitura ativa e anotação consciente, promovendo a prática de leitura atenta, registros de dúvidas e organização de ideias em fichamentos e esquemas, reconhecendo os aspectos centrais da obra (narrador, tempo, espaço, linguagem, temas) e desenvolva interpretação crítica. 2. Estimulo a criação de rotinas de estudo realistas, dividindo o conteúdo em etapas menores, seja via checklists de leitura e prazos parciais, para que os estudantes cultivem disciplina e evitem a concentração de tarefas em última hora. | AO21: 15 | AP21: 14 | AQ21: 23 | AR21: 21 | AS21: 17.3 | AT21: Minha prática docente se renova a partir da formação continuada, da experimentação pedagógica e da reflexão crítica: mantenho atualização constante em literatura e metodologias, aplico estratégias diversificadas como metodologias ativas e adapto o ensino aos diferentes perfis de estudante. Esse percurso se inspira em referenciais como Paulo Freire (autonomia, criticidade e diálogo), Vygotsky (aprendizagem como processo social e professor como mediador), Dewey (vínculo entre experiência, reflexão e educação democrática) e Donald Schön (professor reflexivo orientado pela investigação e transformação da sua prática). | AU21: 18 | AV21: 16 | AW21: 20 | AX21: 16 | AY21: 17.7 | BB21: 15 | BC21: 6 | BD21: 6 | BE21: 0 | BF21: 3 | BG21: 4 | BH21: 15 | BI21: 6 | BJ21: 8 | BK21: 1 | BL21: 6 | BM21: 8 | BN21: 9 | BO21: 2 | BP21: 5 | BQ21: 2.5 | BR21: 9 | BS21: 7.5 | BT21: 15 | BV21: =IFERROR(AVERAGEIF(AULAS_TESTE!$F:$F,$B21,AULAS_TESTE!G:G),"") -> 6.7941176 | BW21: =IFERROR(AVERAGEIF(AULAS_TESTE!$F:$F,$B21,AULAS_TESTE!H:H),"") -> 7.3529412 | BX21: =IFERROR(AVERAGEIF(AULAS_TESTE!$F:$F,$B21,AULAS_TESTE!I:I),"") -> 8.1764706 | BY21: =IFERROR(AVERAGEIF(AULAS_TESTE!$F:$F,$B21,AULAS_TESTE!J:J),"") -> 7.65625 | BZ21: =IFERROR(AVERAGEIF(AULAS_TESTE!$F:$F,$B21,AULAS_TESTE!K:K),"") -> 7.7333333 | CA21: =IFERROR(AVERAGEIF(AULAS_TESTE!$F:$F,$B21,AULAS_TESTE!L:L),"") -> 6.8076923 | CB21: =IFERROR(AVERAGEIF(AULAS_TESTE!$F:$F,$B21,AULAS_TESTE!M:M),"") -> 8.1176471 | CC21: =IFERROR(AVERAGEIF(AULAS_TESTE!$F:$F,$B21,AULAS_TESTE!N:N),"") -> 8.3125 | CD21: =IFERROR(AVERAGEIF(AULAS_TESTE!$F:$F,$B21,AULAS_TESTE!O:O),"") -> 7.5588235 | CE21: =IFERROR(AVERAGEIF(AULAS_TESTE!$F:$F,$B21,AULAS_TESTE!P:P),"") -> 7.6875 | CF21: =IFERROR(AVERAGEIF(AULAS_TESTE!$F:$F,$B21,AULAS_TESTE!Q:Q),"") -> 7.5 | CG21: =IFERROR(AVERAGEIF(AULAS_TESTE!$F:$F,$B21,AULAS_TESTE!R:R),"") -> 6.2727273 | CH21: =IFERROR(AVERAGEIF(AULAS_TESTE!$F:$F,$B21,AULAS_TESTE!S:S),"") -> 8.0625 | CI21: =IFERROR(AVERAGEIF(AULAS_TESTE!$F:$F,$B21,AULAS_TESTE!T:T),"") -> 7.59375
A22: 0 | B22: Nome do Candidato | C22: emaildocandidato@email.com | D22: 11999999999 | E22: Matemática | F22: https://drive.google.com/open?id=1ynqLt4G1Tm4kCTXd7XzHoVK2TqAuEfyN | G22: https://drive.google.com/open?id=1kADAYQy5lH-V1BSmue-pklLLUPwSP38M | H22: Sou editor e formador de professores | J22: B1-B2 (intermediário) | L22: 34 | M22: 3.1275862 | N22: 34 | O22: 1.1833333 | P22: 0.5 | Q22: 1.1666667 | R22: 2.6666667 | S22: 1.6666667 | T22: 34 | U22: 4.5 | Y22: EMEFAF | AB22: Fazendo planejamento com antecedência | AC22: 0 | AD22: 3 | AE22: 5 | AF22: 5 | AG22: 2.2 | AH22: Lição de casa , trabalho e prova | AI22: 2 | AJ22: 2 | AK22: 5 | AL22: 4 | AM22: 2.875 | AN22: Matemática de Cingapura, letramento e lógica | AO22: 0 | AP22: 6 | AQ22: 14 | AR22: 5 | AS22: 4.225 | AT22: Lecionei no Japão para trazer técnicas de aprendizagem diferenciada | AU22: 4 | AV22: 3 | AW22: 8 | AX22: 6 | AY22: 4.9 | BB22: 3 | BC22: 10 | BD22: 8 | BE22: 0 | BF22: 4 | BG22: 1 | BH22: 9 | BI22: 6 | BJ22: 2 | BK22: 2.5 | BL22: 1.5 | BM22: 2 | BN22: 9 | BO22: 1.5 | BP22: 5 | BQ22: 1.5 | BR22: 3 | BS22: 4.5 | BT22: 3 | BV22: =IFERROR(AVERAGEIF(AULAS_TESTE!$F:$F,$B22,AULAS_TESTE!G:G),"") -> 6.7941176 | BW22: =IFERROR(AVERAGEIF(AULAS_TESTE!$F:$F,$B22,AULAS_TESTE!H:H),"") -> 7.3529412 | BX22: =IFERROR(AVERAGEIF(AULAS_TESTE!$F:$F,$B22,AULAS_TESTE!I:I),"") -> 8.1764706 | BY22: =IFERROR(AVERAGEIF(AULAS_TESTE!$F:$F,$B22,AULAS_TESTE!J:J),"") -> 7.65625 | BZ22: =IFERROR(AVERAGEIF(AULAS_TESTE!$F:$F,$B22,AULAS_TESTE!K:K),"") -> 7.7333333 | CA22: =IFERROR(AVERAGEIF(AULAS_TESTE!$F:$F,$B22,AULAS_TESTE!L:L),"") -> 6.8076923 | CB22: =IFERROR(AVERAGEIF(AULAS_TESTE!$F:$F,$B22,AULAS_TESTE!M:M),"") -> 8.1176471 | CC22: =IFERROR(AVERAGEIF(AULAS_TESTE!$F:$F,$B22,AULAS_TESTE!N:N),"") -> 8.3125 | CD22: =IFERROR(AVERAGEIF(AULAS_TESTE!$F:$F,$B22,AULAS_TESTE!O:O),"") -> 7.5588235 | CE22: =IFERROR(AVERAGEIF(AULAS_TESTE!$F:$F,$B22,AULAS_TESTE!P:P),"") -> 7.6875 | CF22: =IFERROR(AVERAGEIF(AULAS_TESTE!$F:$F,$B22,AULAS_TESTE!Q:Q),"") -> 7.5 | CG22: =IFERROR(AVERAGEIF(AULAS_TESTE!$F:$F,$B22,AULAS_TESTE!R:R),"") -> 6.2727273 | CH22: =IFERROR(AVERAGEIF(AULAS_TESTE!$F:$F,$B22,AULAS_TESTE!S:S),"") -> 8.0625 | CI22: =IFERROR(AVERAGEIF(AULAS_TESTE!$F:$F,$B22,AULAS_TESTE!T:T),"") -> 7.59375
A23: 0 | B23: Nome do Candidato | C23: emaildocandidato@email.com | D23: 11999999999 | E23: Química | F23: https://drive.google.com/open?id=1Q6hi1UwtTeqDSgNAanxxpFrPpJajmQ4l | G23: https://drive.google.com/open?id=1n6zDhyhqjDo8uiBpX-EjrtzXCA55Yyj3 | J23: B1-B2 (intermediário) | L23: 15 | M23: 5.6077586 | N23: 11 | O23: 4.4270833 | P23: 3.8333333 | Q23: 4.5833333 | R23: 6.25 | S23: 4.1666667 | T23: 20 | U23: 6.4411765 | V23: 8.5 | Y23: EMEFAF | AB23: Acredito que o aluno deve ser um indivíduo ativo no processo de ensino aprendizagem. Deste modo, durante as aulas divido o percurso em 3 momentos: 1 - Exploração do conteúdo - para que seja possível fornecer as ferramentas necessárias para que o aluno possa aplicar o conhecimento da resolução de problemas. 2 - Atuação do aluno na resolução de situações problemas envolvendo os conceitos explorados. Este momento também torna-se importante para visualizar as dificuldades enfrentadas por alguns estudantes. 3 - Fechamento da aula -realização de uma síntese coletiva, incentivando a participação dos alunos. | AC23: 6 | AD23: 13 | AE23: 22 | AF23: 12 | AG23: 10.9 | AH23: Acredito que a avaliação pode ser realizada por meios formais, como provas e trabalhos, mas também deve acontecer de forma contínua durante o processo de ensino-aprendizagem. Para isso, utilizo diferentes estratégias: observação da realização de exercícios, participação em discussões orais e compartilhamento de ideias, além de atividades práticas, como experimentos em laboratório, que permitem aos alunos visualizar e aplicar o objeto de estudo. | AI23: 7 | AJ23: 11 | AK23: 11 | AL23: 8 | AM23: 8.475 | AN23: Acredito que uma das formas mais eficazes para que o aluno identifique suas principais dificuldades e reconheça suas potencialidades é praticando o que aprende por meio de exercícios. Por isso, faço questão de ensinar e reforçar técnicas de estudo como: organização de resumos, esquemas e mapas conceituais; resolução frequente de exercícios; revisão periódica do conteúdo; e autoavaliação, para que o estudante possa acompanhar sua própria evolução. | AO23: 15 | AP23: 19 | AQ23: 22 | AR23: 15 | AS23: 16.825 | AT23: Busco constantemente me aperfeiçoar por meio de cursos, leituras e formações continuadas que abordam metodologias ativas e novas estratégias de avaliação. Recentemente concluí dois cursos de extensão sobre metodologias ativas e aprendizagem baseada em projetos, que têm contribuído significativamente para o meu desempenho como mediadora do processo de ensino-aprendizagem e para a motivação dos estudantes. | AU23: 18 | AV23: 12 | AW23: 20 | AX23: 15 | AY23: 16.925 | BB23: 9 | BC23: 8 | BD23: 8 | BE23: 0 | BF23: 5 | BG23: 3 | BH23: 9 | BI23: 8 | BJ23: 6 | BK23: 1.5 | BL23: 4.5 | BM23: 6 | BN23: 6 | BO23: 2.5 | BP23: 5 | BQ23: 2.5 | BR23: 9 | BS23: 7.5 | BT23: 9 | BV23: =IFERROR(AVERAGEIF(AULAS_TESTE!$F:$F,$B23,AULAS_TESTE!G:G),"") -> 6.7941176 | BW23: =IFERROR(AVERAGEIF(AULAS_TESTE!$F:$F,$B23,AULAS_TESTE!H:H),"") -> 7.3529412 | BX23: =IFERROR(AVERAGEIF(AULAS_TESTE!$F:$F,$B23,AULAS_TESTE!I:I),"") -> 8.1764706 | BY23: =IFERROR(AVERAGEIF(AULAS_TESTE!$F:$F,$B23,AULAS_TESTE!J:J),"") -> 7.65625 | BZ23: =IFERROR(AVERAGEIF(AULAS_TESTE!$F:$F,$B23,AULAS_TESTE!K:K),"") -> 7.7333333 | CA23: =IFERROR(AVERAGEIF(AULAS_TESTE!$F:$F,$B23,AULAS_TESTE!L:L),"") -> 6.8076923 | CB23: =IFERROR(AVERAGEIF(AULAS_TESTE!$F:$F,$B23,AULAS_TESTE!M:M),"") -> 8.1176471 | CC23: =IFERROR(AVERAGEIF(AULAS_TESTE!$F:$F,$B23,AULAS_TESTE!N:N),"") -> 8.3125 | CD23: =IFERROR(AVERAGEIF(AULAS_TESTE!$F:$F,$B23,AULAS_TESTE!O:O),"") -> 7.5588235 | CE23: =IFERROR(AVERAGEIF(AULAS_TESTE!$F:$F,$B23,AULAS_TESTE!P:P),"") -> 7.6875 | CF23: =IFERROR(AVERAGEIF(AULAS_TESTE!$F:$F,$B23,AULAS_TESTE!Q:Q),"") -> 7.5 | CG23: =IFERROR(AVERAGEIF(AULAS_TESTE!$F:$F,$B23,AULAS_TESTE!R:R),"") -> 6.2727273 | CH23: =IFERROR(AVERAGEIF(AULAS_TESTE!$F:$F,$B23,AULAS_TESTE!S:S),"") -> 8.0625 | CI23: =IFERROR(AVERAGEIF(AULAS_TESTE!$F:$F,$B23,AULAS_TESTE!T:T),"") -> 7.59375
A24: 0 | B24: Nome do Candidato | C24: emaildocandidato@email.com | D24: 11999999999 | E24: Biologia | F24: https://drive.google.com/open?id=1AP_5Omy19mXjzt-cSQJBj3ISfCHyUrrp | G24: https://drive.google.com/open?id=1jLNWLLGzf9_vkLayE2xaNUwj1whsDPcb | H24: Sou palestrante de assuntos relacionados com Ciência e Fé, Bioética e Fisiologia Humana e Comparada, | J24: B1-B2 (intermediário) | L24: 28 | M24: 5.212069 | N24: 23 | O24: 3.5125 | P24: 3.3333333 | Q24: 3.1666667 | R24: 4.5 | S24: 3.3333333 | T24: 36 | U24: 6.4117647 | V24: 6.5 | Y24: EMEFAF | AB24: Evitar conversas longas sobre assuntos científicos midiáticos; conscientizar os alunos da importância do bom uso do tempo; trazer a atenção para os assuntos do conteúdo; limitar o tempo das conversas de assuntos extra-classe. | AC24: 7 | AD24: 6 | AE24: 12 | AF24: 7 | AG24: 7.725 | AH24: Habilidade: expor os alunos a diferentes conteúdos e associação deles com o cotidiano - de que maneira os alunos conseguem resolver problemas diferentes com aquela habilidade. Conceito: usar diferentes habilidades e aplicações variadas daquele conceito no conteúdo formal e no cotidiano. | AI24: 2 | AJ24: 0 | AK24: 9 | AL24: 6 | AM24: 3.625 | AN24: Verificar quanto tempo leva para a resolução de questões de diferentes níveis de exigência; fazer exercícios, ainda que fáceis, todos os dias; verificar e resolver exercícios de anos anteriores dos vestibulares. Pedir que o aluno me explique como ele resolveu esses exercícios. | AO24: 13 | AP24: 27 | AQ24: 23 | AR24: 18 | AS24: 17.725 | AT24: Gosto muito da aula operatória de Ausubel, principalmente no início e fechamento de algum assunto. Para alguns conteudos, Skinner parece ajudar bastante. Piaget também é importante no início e fechamento de alguns temas. Vygotsky ajuda na interação com os colegas e aprendizado mútuo. | AU24: 18 | AV24: 5 | AW24: 10 | AX24: 9 | AY24: 13.075 | BB24: 12 | BC24: 6 | BD24: 4 | BE24: 0 | BF24: 4 | BG24: 2 | BH24: 12 | BI24: 4 | BJ24: 8 | BK24: 1.5 | BL24: 4.5 | BM24: 8 | BN24: 9 | BO24: 2 | BP24: 4 | BQ24: 2.5 | BR24: 3 | BS24: 7.5 | BT24: 15 | BV24: =IFERROR(AVERAGEIF(AULAS_TESTE!$F:$F,$B24,AULAS_TESTE!G:G),"") -> 6.7941176 | BW24: =IFERROR(AVERAGEIF(AULAS_TESTE!$F:$F,$B24,AULAS_TESTE!H:H),"") -> 7.3529412 | BX24: =IFERROR(AVERAGEIF(AULAS_TESTE!$F:$F,$B24,AULAS_TESTE!I:I),"") -> 8.1764706 | BY24: =IFERROR(AVERAGEIF(AULAS_TESTE!$F:$F,$B24,AULAS_TESTE!J:J),"") -> 7.65625 | BZ24: =IFERROR(AVERAGEIF(AULAS_TESTE!$F:$F,$B24,AULAS_TESTE!K:K),"") -> 7.7333333 | CA24: =IFERROR(AVERAGEIF(AULAS_TESTE!$F:$F,$B24,AULAS_TESTE!L:L),"") -> 6.8076923 | CB24: =IFERROR(AVERAGEIF(AULAS_TESTE!$F:$F,$B24,AULAS_TESTE!M:M),"") -> 8.1176471 | CC24: =IFERROR(AVERAGEIF(AULAS_TESTE!$F:$F,$B24,AULAS_TESTE!N:N),"") -> 8.3125 | CD24: =IFERROR(AVERAGEIF(AULAS_TESTE!$F:$F,$B24,AULAS_TESTE!O:O),"") -> 7.5588235 | CE24: =IFERROR(AVERAGEIF(AULAS_TESTE!$F:$F,$B24,AULAS_TESTE!P:P),"") -> 7.6875 | CF24: =IFERROR(AVERAGEIF(AULAS_TESTE!$F:$F,$B24,AULAS_TESTE!Q:Q),"") -> 7.5 | CG24: =IFERROR(AVERAGEIF(AULAS_TESTE!$F:$F,$B24,AULAS_TESTE!R:R),"") -> 6.2727273 | CH24: =IFERROR(AVERAGEIF(AULAS_TESTE!$F:$F,$B24,AULAS_TESTE!S:S),"") -> 8.0625 | CI24: =IFERROR(AVERAGEIF(AULAS_TESTE!$F:$F,$B24,AULAS_TESTE!T:T),"") -> 7.59375
A25: 0 | B25: Nome do Candidato | C25: emaildocandidato@email.com | D25: 11999999999 | E25: Português (Produção e Interpretação de Texto) | F25: https://drive.google.com/open?id=1vIhpUpFxzLro6U51XzKDcoPWbth4c1cV | G25: https://drive.google.com/open?id=1RDw1xB38oVDEn4R1_uWP2_ImPUzV0N-D | H25: Tudo o que aconteceu na minha trajetoria até entao é importante | J25: A1-A2 (básico) | L25: 40 | M25: 4.2698276 | N25: 41 | O25: 0.94375 | P25: 0.25 | Q25: 0.5 | R25: 2.75 | S25: 1.5 | T25: 38 | U25: 6.6176471 | Y25: EMEFAF | AB25: Várias, uso as metodologias ativas/disruptivas os resultados tem sido surpreendentes. | AC25: 0 | AD25: 0 | AE25: 3 | AF25: 4 | AG25: 1.225 | AH25: avaliações padroes exigidas e previamente agendadas no calendario escolar e atraves de dinamicas e projetos conforme contudo e ano escolar. | AI25: 3 | AJ25: 0 | AK25: 5 | AL25: 3 | AM25: 2.9 | AN25: Apresento aos alunos todas, e a cada termino de conteudo eles usam uma delas e me apresentam ate que encontrem a que melhor se identifiquem e que aprendam obtendo melhor resultado. | AO25: 0 | AP25: 4 | AQ25: 20 | AR25: 8 | AS25: 5.5 | AT25: aprendizado e aperfeiçoamento constantes. | AU25: 0 | AV25: 2 | AW25: 5 | AX25: 3 | AY25: 1.7 | BB25: 6 | BC25: 6 | BD25: 4 | BE25: 0 | BF25: 3 | BG25: 5 | BH25: 15 | BI25: 2 | BJ25: 8 | BK25: 1.5 | BL25: 7.5 | BM25: 10 | BN25: 3 | BO25: 2.5 | BP25: 5 | BQ25: 2.5 | BR25: 12 | BS25: 4.5 | BT25: 15 | BV25: =IFERROR(AVERAGEIF(AULAS_TESTE!$F:$F,$B25,AULAS_TESTE!G:G),"") -> 6.7941176 | BW25: =IFERROR(AVERAGEIF(AULAS_TESTE!$F:$F,$B25,AULAS_TESTE!H:H),"") -> 7.3529412 | BX25: =IFERROR(AVERAGEIF(AULAS_TESTE!$F:$F,$B25,AULAS_TESTE!I:I),"") -> 8.1764706 | BY25: =IFERROR(AVERAGEIF(AULAS_TESTE!$F:$F,$B25,AULAS_TESTE!J:J),"") -> 7.65625 | BZ25: =IFERROR(AVERAGEIF(AULAS_TESTE!$F:$F,$B25,AULAS_TESTE!K:K),"") -> 7.7333333 | CA25: =IFERROR(AVERAGEIF(AULAS_TESTE!$F:$F,$B25,AULAS_TESTE!L:L),"") -> 6.8076923 | CB25: =IFERROR(AVERAGEIF(AULAS_TESTE!$F:$F,$B25,AULAS_TESTE!M:M),"") -> 8.1176471 | CC25: =IFERROR(AVERAGEIF(AULAS_TESTE!$F:$F,$B25,AULAS_TESTE!N:N),"") -> 8.3125 | CD25: =IFERROR(AVERAGEIF(AULAS_TESTE!$F:$F,$B25,AULAS_TESTE!O:O),"") -> 7.5588235 | CE25: =IFERROR(AVERAGEIF(AULAS_TESTE!$F:$F,$B25,AULAS_TESTE!P:P),"") -> 7.6875 | CF25: =IFERROR(AVERAGEIF(AULAS_TESTE!$F:$F,$B25,AULAS_TESTE!Q:Q),"") -> 7.5 | CG25: =IFERROR(AVERAGEIF(AULAS_TESTE!$F:$F,$B25,AULAS_TESTE!R:R),"") -> 6.2727273 | CH25: =IFERROR(AVERAGEIF(AULAS_TESTE!$F:$F,$B25,AULAS_TESTE!S:S),"") -> 8.0625 | CI25: =IFERROR(AVERAGEIF(AULAS_TESTE!$F:$F,$B25,AULAS_TESTE!T:T),"") -> 7.59375
A26: 0 | B26: Nome do Candidato | C26: emaildocandidato@email.com | D26: 11999999999 | E26: Geografia | F26: https://drive.google.com/open?id=1499TBC-oF3GUaY7LHbwyS6Fkjta6hExr | G26: https://drive.google.com/open?id=1lS91yO4YQXJ2QvGyYQB7XQx3TPXbYhpU | H26: Possuo experiência ampla e diversificada, formação sólida e constante atualização. Tenho experiência na elaboração de avaliações autorais, projetos interdisciplinares e atividades específicas. Minha experiência internacional, aliada à produção acadêmica, proporcionou-me uma visão global que enriquece minha prática docente. | I26: Em janeiro participei de um processo seletivo no colégio, inclusive utilizando o mesmo vídeo de apresentação, mas senti que não era o momento adequado para mim. Estou me candidatando para futuras oportunidades, pois acredito na instituição e sinto que compartilho os mesmos ideais e valores do colégio. | J26: A1-A2 (básico) | L26: 4 | M26: 6.7310345 | N26: 10 | O26: 4.8916667 | P26: 4.6666667 | Q26: 5 | R26: 5.5833333 | S26: 4.75 | T26: 3 | U26: 8.0294118 | Y26: EMEFAF | AB26: Para otimizar o tempo em sala de aula, a principal estratégia é o planejamento, com objetivos claros, materiais preparados e a previsão de imprevistos. Durante a aula, é fundamental manter o foco no conteúdo e estabelecer uma rotina de início e fim. Costumo anotar no canto esquerdo da lousa a página do livro referente aos conteúdos e a tarefa para a próxima aula. Na aula seguinte, começamos com a correção da lição de casa e novas orientações. Para aproveitar melhor o tempo, é possível organizar a aula em blocos, definindo metas específicas para cada etapa. | AC26: 12 | AD26: 19 | AE26: 15 | AF26: 15 | AG26: 14.1 | AH26: Tenho experiência em elaborar provas autorais, por habilidades e na Taxonomia de Bloom, aplicadas a cada trimestre e alinhadas ao planejamento anual construído com os demais professores. Além das avaliações, utilizo projetos interdisciplinares, saídas pedagógicas e atividades específicas da disciplina, que permitem observar o desempenho dos alunos de diferentes formas e confirmar o domínio das habilidades e conceitos. Para a verificação da aprendizagem é preciso identificar se o estudante apresentou bom desempenho nas avaliações, se é capaz de aplicar o que aprendeu na prática, bem como de relacionar essa aprendizagem à sua vivência. | AI26: 8 | AJ26: 7 | AK26: 15 | AL26: 12 | AM26: 9.775 | AN26: Procuro diversificar as técnicas de estudo conforme os temas de cada trimestre e as especificidades da turma, como lições de casa em forma de resumos, mapas mentais, exercícios de fixação e leituras. Em aula, realizo revisões periódicas e esquemas que facilitam a compreensão e memorização. Para desenvolver a autonomia, os estudantes precisam organizar seu estudo, planejar o tempo, definir metas, avaliar seu desempenho e ajustar estratégias. Acompanho esse processo com orientações e o uso de autoavaliação, especialmente por rubricas. | AO26: 18 | AP26: 27 | AQ26: 23 | AR26: 19 | AS26: 20.4 | AT26: Na última escola particular em que lecionei, participei de inúmeras formações, palestras e cursos, incluindo o uso de tecnologias educacionais, que aprimoraram minha prática docente. O colégio adotava metodologias ativas, que posso comparar às ideias de John Dewey, e utilizava a Taxonomia de Benjamin Bloom em todas as avaliações. Entretanto, acredito que a prática pedagógica deve considerar também a base cognitiva, crítica e sociocultural, mantendo Piaget, Freire e Vygotsky como referenciais essenciais para o desenvolvimento e aprendizagem dos alunos. | AU26: 18 | AV26: 7 | AW26: 14 | AX26: 11 | AY26: 14.425 | BB26: 15 | BC26: 6 | BD26: 4 | BE26: 0 | BF26: 2 | BG26: 3 | BH26: 15 | BI26: 8 | BJ26: 6 | BK26: 2.5 | BL26: 7.5 | BM26: 8 | BN26: 12 | BO26: 2.5 | BP26: 5 | BQ26: 2.5 | BR26: 15 | BS26: 7.5 | BT26: 15 | BV26: =IFERROR(AVERAGEIF(AULAS_TESTE!$F:$F,$B26,AULAS_TESTE!G:G),"") -> 6.7941176 | BW26: =IFERROR(AVERAGEIF(AULAS_TESTE!$F:$F,$B26,AULAS_TESTE!H:H),"") -> 7.3529412 | BX26: =IFERROR(AVERAGEIF(AULAS_TESTE!$F:$F,$B26,AULAS_TESTE!I:I),"") -> 8.1764706 | BY26: =IFERROR(AVERAGEIF(AULAS_TESTE!$F:$F,$B26,AULAS_TESTE!J:J),"") -> 7.65625 | BZ26: =IFERROR(AVERAGEIF(AULAS_TESTE!$F:$F,$B26,AULAS_TESTE!K:K),"") -> 7.7333333 | CA26: =IFERROR(AVERAGEIF(AULAS_TESTE!$F:$F,$B26,AULAS_TESTE!L:L),"") -> 6.8076923 | CB26: =IFERROR(AVERAGEIF(AULAS_TESTE!$F:$F,$B26,AULAS_TESTE!M:M),"") -> 8.1176471 | CC26: =IFERROR(AVERAGEIF(AULAS_TESTE!$F:$F,$B26,AULAS_TESTE!N:N),"") -> 8.3125 | CD26: =IFERROR(AVERAGEIF(AULAS_TESTE!$F:$F,$B26,AULAS_TESTE!O:O),"") -> 7.5588235 | CE26: =IFERROR(AVERAGEIF(AULAS_TESTE!$F:$F,$B26,AULAS_TESTE!P:P),"") -> 7.6875 | CF26: =IFERROR(AVERAGEIF(AULAS_TESTE!$F:$F,$B26,AULAS_TESTE!Q:Q),"") -> 7.5 | CG26: =IFERROR(AVERAGEIF(AULAS_TESTE!$F:$F,$B26,AULAS_TESTE!R:R),"") -> 6.2727273 | CH26: =IFERROR(AVERAGEIF(AULAS_TESTE!$F:$F,$B26,AULAS_TESTE!S:S),"") -> 8.0625 | CI26: =IFERROR(AVERAGEIF(AULAS_TESTE!$F:$F,$B26,AULAS_TESTE!T:T),"") -> 7.59375
A27: 0 | B27: Nome do Candidato | C27: emaildocandidato@email.com | D27: 11999999999 | E27: Física | F27: https://drive.google.com/open?id=1cpkq-hov2JGqx2THK-Iq01gE4PdRjaJB | G27: https://drive.google.com/open?id=1XpoJbBy_RocIYDhPg2XrEyExrMaIsgXT | J27: C1-C2 (avançado/fluente) | L27: 1 | M27: 6.8422414 | N27: 4 | O27: 4.99375 | P27: 5.3333333 | Q27: 3.75 | R27: 5.8333333 | S27: 4.25 | T27: 1 | U27: 8.1470588 | V27: 7.5 | W27: 2.5 | X27: 4.1666667 | Y27: EMEFAF | AB27: - Com planejamento de aula e - criação de rotinas em sala para que os alunos saibam o que é esperado e ajam de acordo. - chamada durante algum exercício proposto aos alunos ou ao fim da aula - uso do quadro apenas para o necessário; sempre que possível uso projetor com material já pronto. - disponibilização de material ao alunos por meios digitais | AC27: 19 | AD27: 19 | AE27: 17 | AF27: 12 | AG27: 17.425 | AH27: - Interagindo com os alunos durante a explicação. - Andando pela sala e conversando com os alunos durante atividades e exercícios propostos em sala. - Tarefas, trabalhos e outras atividades para casa. | AI27: 17 | AJ27: 2 | AK27: 8 | AL27: 6 | AM27: 11.25 | AN27: - mapas mentais - resolução estruturada de problemas - rotina de estudo. Estudar um pouco toda semana, ao invés de estudar muito antes da prova. Estudar aos poucos e com consistencia. | AO27: 11 | AP27: 17 | AQ27: 24 | AR27: 18 | AS27: 15.4 | AT27: Quando monto uma aula busco por novidades e depoimentos e experiências de outros professores na internet. Mas sempre procuro estruturar as atividades usando métodos comprovados. - Procuro investigar os conceitos prévios (Piaget) e o senso comum (Bachelard). - Ao começar um novo tópico procuro partir de exemplos já conhecidos para facilitar o entendimento (Ausubel) - Quando o tempo permite, proponho atividades em grupo para que os alunos possam discutir e desenvolver seus conhecimentos juntos (Vygotsky) | AU27: 17 | AV27: 7 | AW27: 21 | AX27: 15 | AY27: 15.85 | BB27: 15 | BC27: 6 | BD27: 6 | BE27: 0 | BF27: 4 | BG27: 1 | BH27: 15 | BI27: 8 | BJ27: 10 | BK27: 1.5 | BL27: 7.5 | BM27: 8 | BN27: 9 | BO27: 2.5 | BP27: 5 | BQ27: 2.5 | BR27: 15 | BS27: 7.5 | BT27: 15 | BV27: =IFERROR(AVERAGEIF(AULAS_TESTE!$F:$F,$B27,AULAS_TESTE!G:G),"") -> 6.7941176 | BW27: =IFERROR(AVERAGEIF(AULAS_TESTE!$F:$F,$B27,AULAS_TESTE!H:H),"") -> 7.3529412 | BX27: =IFERROR(AVERAGEIF(AULAS_TESTE!$F:$F,$B27,AULAS_TESTE!I:I),"") -> 8.1764706 | BY27: =IFERROR(AVERAGEIF(AULAS_TESTE!$F:$F,$B27,AULAS_TESTE!J:J),"") -> 7.65625 | BZ27: =IFERROR(AVERAGEIF(AULAS_TESTE!$F:$F,$B27,AULAS_TESTE!K:K),"") -> 7.7333333 | CA27: =IFERROR(AVERAGEIF(AULAS_TESTE!$F:$F,$B27,AULAS_TESTE!L:L),"") -> 6.8076923 | CB27: =IFERROR(AVERAGEIF(AULAS_TESTE!$F:$F,$B27,AULAS_TESTE!M:M),"") -> 8.1176471 | CC27: =IFERROR(AVERAGEIF(AULAS_TESTE!$F:$F,$B27,AULAS_TESTE!N:N),"") -> 8.3125 | CD27: =IFERROR(AVERAGEIF(AULAS_TESTE!$F:$F,$B27,AULAS_TESTE!O:O),"") -> 7.5588235 | CE27: =IFERROR(AVERAGEIF(AULAS_TESTE!$F:$F,$B27,AULAS_TESTE!P:P),"") -> 7.6875 | CF27: =IFERROR(AVERAGEIF(AULAS_TESTE!$F:$F,$B27,AULAS_TESTE!Q:Q),"") -> 7.5 | CG27: =IFERROR(AVERAGEIF(AULAS_TESTE!$F:$F,$B27,AULAS_TESTE!R:R),"") -> 6.2727273 | CH27: =IFERROR(AVERAGEIF(AULAS_TESTE!$F:$F,$B27,AULAS_TESTE!S:S),"") -> 8.0625 | CI27: =IFERROR(AVERAGEIF(AULAS_TESTE!$F:$F,$B27,AULAS_TESTE!T:T),"") -> 7.59375
A28: 0 | B28: Nome do Candidato | C28: emaildocandidato@email.com | D28: 11999999999 | E28: História | F28: https://drive.google.com/open?id=1c8k4GUC3WdGv9AdUDHg9pVN2JqlfbA3M | G28: https://drive.google.com/open?id=1h1sd_qWAOR3P1JeoYdE6bY88N8PndINg | H28: Considero como diferencial no meu currículo a participação no Programa Residência Pedagógica da CAPES, que me proporcionou experiência prática e aprofundamento metodológico desde a graduação. Além disso, desenvolvi uma iniciação científica e atualmente sou mestrando em História, pesquisando a cultura histórica indígena a partir das ideias de Ailton Krenak, o que amplia minha visão crítica sobre educação e diversidade cultural. Também já ministrei atividades em feiras culturais e projetos interdisciplinares, sempre valorizando metodologias ativas e a relação entre história, sociedade e cidadania. | J28: B1-B2 (intermediário) | L28: 24 | M28: 5.5931034 | N28: 12 | O28: 4.5166667 | P28: 4.25 | Q28: 4.0833333 | R28: 5.1666667 | S28: 5 | T28: 36 | U28: 6.3529412 | V28: 6 | Y28: EMEFAF | AB28: Busco sempre planejar a aula de forma organizada, estruturando cada momento (introdução, desenvolvimento e fechamento) e deixando objetivos claros para os alunos. Utilizo metodologias ativas, como debates, trabalhos em grupo e resolução de problemas, que tornam a aprendizagem mais dinâmica e evitam dispersão. Além disso, estabeleço rotinas e combinados desde o início, o que contribui para manter o foco e aproveitar melhor o tempo. | AC28: 7 | AD28: 16 | AE28: 18 | AF28: 14 | AG28: 11.5 | AH28: Trabalho com avaliações contínuas, que vão além da prova tradicional. Utilizo atividades diagnósticas, produções escritas, apresentações, rodas de conversa e exercícios práticos em sala. Também valorizo a autoavaliação e a avaliação por pares, pois acredito que ajudam o aluno a perceber seu próprio progresso. Dessa forma, consigo verificar não apenas o acerto de respostas, mas a capacidade de argumentar, relacionar conteúdos e aplicar conceitos em diferentes situações. | AI28: 12 | AJ28: 11 | AK28: 13 | AL28: 11 | AM28: 11.85 | AN28: Procuro ensinar técnicas de organização, como resumo, mapas mentais, fichamentos e cronogramas de estudo, incentivando a autonomia do aluno. Também reforço a importância da leitura crítica, da revisão periódica e da relação entre diferentes conteúdos. Outro ponto essencial é o uso consciente de recursos digitais, sempre como aliados no processo de aprendizagem. | AO28: 14 | AP28: 11 | AQ28: 17 | AR28: 16 | AS28: 14.425 | AT28: Acredito que a docência exige constante atualização. Participo de cursos de formação continuada, congressos e grupos de estudo. Além disso, busco refletir sobre minha prática por meio de trocas com colegas e pelo feedback dos próprios alunos. Teoricamente, me apoio em Paulo Freire, que destaca a educação como prática da liberdade; em Lev Vygotsky, com a ênfase na aprendizagem mediada e no papel social do conhecimento; e em José Carlos Libâneo, que contribui com a didática voltada para a realidade da escola. Essas referências me ajudam a manter uma postura crítica e inovadora em sala de aula. | AU28: 18 | AV28: 11 | AW28: 14 | AX28: 19 | AY28: 16.425 | BB28: 15 | BC28: 2 | BD28: 4 | BE28: 0 | BF28: 2 | BG28: 4 | BH28: 6 | BI28: 2 | BJ28: 8 | BK28: 0.5 | BL28: 7.5 | BM28: 10 | BN28: 9 | BO28: 1.5 | BP28: 4 | BQ28: 2.5 | BR28: 9 | BS28: 6 | BT28: 15 | BV28: =IFERROR(AVERAGEIF(AULAS_TESTE!$F:$F,$B28,AULAS_TESTE!G:G),"") -> 6.7941176 | BW28: =IFERROR(AVERAGEIF(AULAS_TESTE!$F:$F,$B28,AULAS_TESTE!H:H),"") -> 7.3529412 | BX28: =IFERROR(AVERAGEIF(AULAS_TESTE!$F:$F,$B28,AULAS_TESTE!I:I),"") -> 8.1764706 | BY28: =IFERROR(AVERAGEIF(AULAS_TESTE!$F:$F,$B28,AULAS_TESTE!J:J),"") -> 7.65625 | BZ28: =IFERROR(AVERAGEIF(AULAS_TESTE!$F:$F,$B28,AULAS_TESTE!K:K),"") -> 7.7333333 | CA28: =IFERROR(AVERAGEIF(AULAS_TESTE!$F:$F,$B28,AULAS_TESTE!L:L),"") -> 6.8076923 | CB28: =IFERROR(AVERAGEIF(AULAS_TESTE!$F:$F,$B28,AULAS_TESTE!M:M),"") -> 8.1176471 | CC28: =IFERROR(AVERAGEIF(AULAS_TESTE!$F:$F,$B28,AULAS_TESTE!N:N),"") -> 8.3125 | CD28: =IFERROR(AVERAGEIF(AULAS_TESTE!$F:$F,$B28,AULAS_TESTE!O:O),"") -> 7.5588235 | CE28: =IFERROR(AVERAGEIF(AULAS_TESTE!$F:$F,$B28,AULAS_TESTE!P:P),"") -> 7.6875 | CF28: =IFERROR(AVERAGEIF(AULAS_TESTE!$F:$F,$B28,AULAS_TESTE!Q:Q),"") -> 7.5 | CG28: =IFERROR(AVERAGEIF(AULAS_TESTE!$F:$F,$B28,AULAS_TESTE!R:R),"") -> 6.2727273 | CH28: =IFERROR(AVERAGEIF(AULAS_TESTE!$F:$F,$B28,AULAS_TESTE!S:S),"") -> 8.0625 | CI28: =IFERROR(AVERAGEIF(AULAS_TESTE!$F:$F,$B28,AULAS_TESTE!T:T),"") -> 7.59375
A29: 0 | B29: Nome do Candidato | C29: emaildocandidato@email.com | D29: 11999999999 | E29: Física | F29: https://drive.google.com/open?id=14AduAinDShS_ydhjqNikuXAp7NThjJiF | G29: https://drive.google.com/open?id=12r8HwkXUvr7yY8MoZYyfLpNsT0FE0Q5_ | H29: Meu diferencial é a capacidade de integrar conteúdos de economia, negócios e matemática com temas do cotidiano. Isso aproxima o aluno da realidade e torna o aprendizado muito mais significativo. | J29: C1-C2 (avançado/fluente) | L29: 5 | M29: 6.4275862 | N29: 5 | O29: 4.7833333 | P29: 4.8333333 | Q29: 4.5 | R29: 4.9166667 | S29: 4.75 | T29: 5 | U29: 7.5882353 | Y29: EMEFAF | AB29: Procuro criar uma rotina clara em sala de aula: começo com a contextualização, passo para o conteúdo principal e finalizo com uma atividade de fixação. Essa organização ajuda a manter o ritmo, evita atrasos e aproveita melhor o tempo disponível. | AC29: 3 | AD29: 11 | AE29: 12 | AF29: 12 | AG29: 7.35 | AH29: Procuro observar a participação dos alunos nas discussões, analisar exercícios aplicados em sala e propor tarefas práticas. Esses momentos me ajudam a identificar quem já domina a habilidade e quem ainda precisa de reforço. | AI29: 14 | AJ29: 9 | AK29: 9 | AL29: 7 | AM29: 11.15 | AN29: Eu ensino os alunos a planejar a semana com metas simples e blocos de 25–30 minutos (Pomodoro). Cobro revisão em 24 horas, depois em 7 dias e antes da prova. Confiro o planner e faço checagens rápidas para garantir que a rotina está acontecendo. | AO29: 24 | AP29: 23 | AQ29: 26 | AR29: 21 | AS29: 23.675 | AT29: Busco atualização em metodologias ativas, como aprendizagem baseada em projetos e sala de aula invertida. Referências como Paulo Freire e John Dewey são fundamentais, pois reforçam a importância de uma prática participativa e centrada no aluno. | AU29: 17 | AV29: 11 | AW29: 12 | AX29: 17 | AY29: 15.225 | BB29: 15 | BC29: 2 | BD29: 2 | BE29: 0 | BF29: 1 | BG29: 5 | BH29: 15 | BI29: 4 | BJ29: 10 | BK29: 1 | BL29: 7.5 | BM29: 10 | BN29: 9 | BO29: 2.5 | BP29: 5 | BQ29: 2.5 | BR29: 15 | BS29: 7.5 | BT29: 15 | BV29: =IFERROR(AVERAGEIF(AULAS_TESTE!$F:$F,$B29,AULAS_TESTE!G:G),"") -> 6.7941176 | BW29: =IFERROR(AVERAGEIF(AULAS_TESTE!$F:$F,$B29,AULAS_TESTE!H:H),"") -> 7.3529412 | BX29: =IFERROR(AVERAGEIF(AULAS_TESTE!$F:$F,$B29,AULAS_TESTE!I:I),"") -> 8.1764706 | BY29: =IFERROR(AVERAGEIF(AULAS_TESTE!$F:$F,$B29,AULAS_TESTE!J:J),"") -> 7.65625 | BZ29: =IFERROR(AVERAGEIF(AULAS_TESTE!$F:$F,$B29,AULAS_TESTE!K:K),"") -> 7.7333333 | CA29: =IFERROR(AVERAGEIF(AULAS_TESTE!$F:$F,$B29,AULAS_TESTE!L:L),"") -> 6.8076923 | CB29: =IFERROR(AVERAGEIF(AULAS_TESTE!$F:$F,$B29,AULAS_TESTE!M:M),"") -> 8.1176471 | CC29: =IFERROR(AVERAGEIF(AULAS_TESTE!$F:$F,$B29,AULAS_TESTE!N:N),"") -> 8.3125 | CD29: =IFERROR(AVERAGEIF(AULAS_TESTE!$F:$F,$B29,AULAS_TESTE!O:O),"") -> 7.5588235 | CE29: =IFERROR(AVERAGEIF(AULAS_TESTE!$F:$F,$B29,AULAS_TESTE!P:P),"") -> 7.6875 | CF29: =IFERROR(AVERAGEIF(AULAS_TESTE!$F:$F,$B29,AULAS_TESTE!Q:Q),"") -> 7.5 | CG29: =IFERROR(AVERAGEIF(AULAS_TESTE!$F:$F,$B29,AULAS_TESTE!R:R),"") -> 6.2727273 | CH29: =IFERROR(AVERAGEIF(AULAS_TESTE!$F:$F,$B29,AULAS_TESTE!S:S),"") -> 8.0625 | CI29: =IFERROR(AVERAGEIF(AULAS_TESTE!$F:$F,$B29,AULAS_TESTE!T:T),"") -> 7.59375
A30: 0 | B30: Nome do Candidato | C30: emaildocandidato@email.com | D30: 11999999999 | E30: Biologia | F30: https://drive.google.com/open?id=15Dl2Bji0hrvjf1G6gyMTJl-4VOTHUIi- | G30: https://drive.google.com/open?id=1WRcjF_pB8Em3r-axSD76NV0ZQTj4USdR | H30: Considero importante estar em formação contínua, por esse motivo ser uma pesquisadora mestra em Ensino de Ciências e Matemática, pode contribuir muito para o compartilhamento de conhecimento com os estudantes. | J30: A1-A2 (básico) | L30: 1 | M30: 7.625 | N30: 2 | O30: 6.3020833 | P30: 7.5 | Q30: 5.25 | R30: 5.25 | S30: 4.8333333 | T30: 1 | U30: 8.5588235 | V30: 4.5 | Y30: EMEFAF | AB30: Para otimizar o tempo em sala de aula, realizo um planejamento de aulas com objetivos claros e blocos de tempo definidos, priorizando tarefas importantes e tendo atividades extras para o caso de terminarem cedo. Costumo utilizar ferramentas para automatizar tarefas, estabelecer rotinas e transições rápidas entre as atividades. O uso do dever de casa para reforçar o conteúdo, também é uma de minhas estratégias de ensino. | AC30: 14 | AD30: 18 | AE30: 15 | AF30: 17 | AG30: 15.3 | AH30: Questionamentos orais e discussões guiadas, atividades rápidas (checkpoints), estudos de caso ou situações-problema, aprendizagem entre pares entre outras. | AI30: 22 | AJ30: 14 | AK30: 11 | AL30: 8 | AM30: 16.425 | AN30: Ensinar os alunos a definirem metas SMART (específicas, mensuráveis, alcançáveis, relevantes e temporais). Métodos como o Pomodoro. Mapas mentais e resumos visuais. Ensinar alguém (explicar o conteúdo para colegas ou familiares). Prática distribuída: revisar várias vezes em intervalos de tempo, ao invés de estudar tudo de uma vez. Questionários e autoavaliação. Essas são algumas tecnicas entre outras utilizadas. | AO30: 28 | AP30: 16 | AQ30: 22 | AR30: 13 | AS30: 22.525 | AT30: Inspirada em Donald Schön (1983), com o conceito de “professor reflexivo”. É imprescindível o professor analisar suas ações, identificar erros e acertos, ajustar metodologias e se tornar pesquisador da própria prática. Outro conceito que considero importante é a participação em cursos, oficinas, grupos de estudo e congressos. António Nóvoa (1992, 2009) destaca que a identidade docente se constrói em um processo contínuo de formação e troca entre pares. Consirero crucial a aplicação de estratégias como sala invertida, aprendizagem baseada em projetos, rotação por estações, aprendizagem por pares. | AU30: 26 | AV30: 15 | AW30: 15 | AX30: 20 | AY30: 21.375 | BB30: 15 | BC30: 4 | BD30: 2 | BE30: 0 | BF30: 5 | BG30: 4 | BH30: 15 | BI30: 10 | BJ30: 10 | BK30: 0.5 | BL30: 7.5 | BM30: 10 | BN30: 15 | BO30: 2.5 | BP30: 5 | BQ30: 2.5 | BR30: 15 | BS30: 7.5 | BT30: 15 | BV30: =IFERROR(AVERAGEIF(AULAS_TESTE!$F:$F,$B30,AULAS_TESTE!G:G),"") -> 6.7941176 | BW30: =IFERROR(AVERAGEIF(AULAS_TESTE!$F:$F,$B30,AULAS_TESTE!H:H),"") -> 7.3529412 | BX30: =IFERROR(AVERAGEIF(AULAS_TESTE!$F:$F,$B30,AULAS_TESTE!I:I),"") -> 8.1764706 | BY30: =IFERROR(AVERAGEIF(AULAS_TESTE!$F:$F,$B30,AULAS_TESTE!J:J),"") -> 7.65625 | BZ30: =IFERROR(AVERAGEIF(AULAS_TESTE!$F:$F,$B30,AULAS_TESTE!K:K),"") -> 7.7333333 | CA30: =IFERROR(AVERAGEIF(AULAS_TESTE!$F:$F,$B30,AULAS_TESTE!L:L),"") -> 6.8076923 | CB30: =IFERROR(AVERAGEIF(AULAS_TESTE!$F:$F,$B30,AULAS_TESTE!M:M),"") -> 8.1176471 | CC30: =IFERROR(AVERAGEIF(AULAS_TESTE!$F:$F,$B30,AULAS_TESTE!N:N),"") -> 8.3125 | CD30: =IFERROR(AVERAGEIF(AULAS_TESTE!$F:$F,$B30,AULAS_TESTE!O:O),"") -> 7.5588235 | CE30: =IFERROR(AVERAGEIF(AULAS_TESTE!$F:$F,$B30,AULAS_TESTE!P:P),"") -> 7.6875 | CF30: =IFERROR(AVERAGEIF(AULAS_TESTE!$F:$F,$B30,AULAS_TESTE!Q:Q),"") -> 7.5 | CG30: =IFERROR(AVERAGEIF(AULAS_TESTE!$F:$F,$B30,AULAS_TESTE!R:R),"") -> 6.2727273 | CH30: =IFERROR(AVERAGEIF(AULAS_TESTE!$F:$F,$B30,AULAS_TESTE!S:S),"") -> 8.0625 | CI30: =IFERROR(AVERAGEIF(AULAS_TESTE!$F:$F,$B30,AULAS_TESTE!T:T),"") -> 7.59375
A31: 0 | B31: Nome do Candidato | C31: emaildocandidato@email.com | D31: 11999999999 | E31: Filosofia / Sociologia | F31: https://drive.google.com/open?id=1fmn7XQq2omexV5h85BNXZmQumPmLIJvq | G31: https://drive.google.com/open?id=1paohDx6ypI4ZhS8EFAR2JFipgvNGVL-4 | H31: Fui consultor de planejamento estratégico do PNUD/ONU | I31: grato | J31: A1-A2 (básico) | L31: 19 | M31: 5.1413793 | N31: 18 | O31: 2.675 | P31: 3.0833333 | Q31: 1.9166667 | R31: 3.0833333 | S31: 1.75 | T31: 16 | U31: 6.8823529 | V31: 8.5 | W31: 2.5 | X31: 4.5 | Y31: EMEFAF | AB31: contrato pedagógico, foco e utilização, caso necessário, de algumas metodologias ativas. | AC31: 3 | AD31: 7 | AE31: 6 | AF31: 4 | AG31: 4.3 | AH31: Bem, a aula é fruto de um planejamento, de um plano cujo o acompanhamento deve ser contínuo e permanente a fim de permitir a correção e ou o aperfeiçoamento no decorrer de sua aplicação, isto é de sua prática, no caso a própria aula. Portanto, questionários rápidos, exercícios de reflexão, debates em grupo, mapas mentais e auto avaliações, podem ser úteis para identificar dificuldades em tempo real e ajustar a abordagem de ensino. Avaliações diagnósticas, antes do começo de um novo conteúdo, também podem fornecer feedbacks valiosos sobre a aprendizagem dos alunos. | AI31: 12 | AJ31: 10 | AK31: 13 | AL31: 12 | AM31: 11.875 | AN31: Acredito que a melhor forma ainda é estimular a curiosidade, o espanto, a perplexidade e o encanto perante o novo conhecimento, em suma: o thaumatsen. Além disso, a revisão constante do que foi visto, o aperfeiçoamento que permitirá fazer relações com outros temas a fim de abrir novas dimensões e ganchos, elos de saberes. Tudo isso, advém de uma prática contínua de estudo que só é internalizada pelo aluno com o amor pela sabedoria, em suma: a autogestão da aprendizagem e, a tão almejada autonomia só virá através de um plano de estudos permanente, já que o processo de conhecimento não cessa nunca, portanto, acontece por toda a vida. | AO31: 10 | AP31: 6 | AQ31: 11 | AR31: 4 | AS31: 8.525 | AT31: Pegando uma carona com Hegel: Assim como todo ser humano, em cada atividade, seja ela política, religiosa, artística, científica ou pedagógica é um filho de sua época e tem a tarefa de elaborar o Conteúdo Essencial e, desse modo, a forma necessária deste, assim também permanece como determinação do professor que ele encontre a expressão didaticamente adequada para o espirito de seus alunos. Ou seja, a renovação e o aperfeiçoamento de técnicas de sala de aula devem estar galgadas, alicerçadas ao perfil, interesses, necessidades e vicissitudes de seus alunos/púbico. | AU31: 12 | AV31: 0 | AW31: 7 | AX31: 1 | AY31: 7.4 | BB31: 15 | BC31: 2 | BD31: 2 | BE31: 0 | BF31: 1 | BG31: 3 | BH31: 9 | BI31: 6 | BJ31: 10 | BK31: 2.5 | BL31: 7.5 | BM31: 6 | BN31: 9 | BO31: 2 | BP31: 5 | BQ31: 2.5 | BR31: 12 | BS31: 7.5 | BT31: 15 | BV31: =IFERROR(AVERAGEIF(AULAS_TESTE!$F:$F,$B31,AULAS_TESTE!G:G),"") -> 6.7941176 | BW31: =IFERROR(AVERAGEIF(AULAS_TESTE!$F:$F,$B31,AULAS_TESTE!H:H),"") -> 7.3529412 | BX31: =IFERROR(AVERAGEIF(AULAS_TESTE!$F:$F,$B31,AULAS_TESTE!I:I),"") -> 8.1764706 | BY31: =IFERROR(AVERAGEIF(AULAS_TESTE!$F:$F,$B31,AULAS_TESTE!J:J),"") -> 7.65625 | BZ31: =IFERROR(AVERAGEIF(AULAS_TESTE!$F:$F,$B31,AULAS_TESTE!K:K),"") -> 7.7333333 | CA31: =IFERROR(AVERAGEIF(AULAS_TESTE!$F:$F,$B31,AULAS_TESTE!L:L),"") -> 6.8076923 | CB31: =IFERROR(AVERAGEIF(AULAS_TESTE!$F:$F,$B31,AULAS_TESTE!M:M),"") -> 8.1176471 | CC31: =IFERROR(AVERAGEIF(AULAS_TESTE!$F:$F,$B31,AULAS_TESTE!N:N),"") -> 8.3125 | CD31: =IFERROR(AVERAGEIF(AULAS_TESTE!$F:$F,$B31,AULAS_TESTE!O:O),"") -> 7.5588235 | CE31: =IFERROR(AVERAGEIF(AULAS_TESTE!$F:$F,$B31,AULAS_TESTE!P:P),"") -> 7.6875 | CF31: =IFERROR(AVERAGEIF(AULAS_TESTE!$F:$F,$B31,AULAS_TESTE!Q:Q),"") -> 7.5 | CG31: =IFERROR(AVERAGEIF(AULAS_TESTE!$F:$F,$B31,AULAS_TESTE!R:R),"") -> 6.2727273 | CH31: =IFERROR(AVERAGEIF(AULAS_TESTE!$F:$F,$B31,AULAS_TESTE!S:S),"") -> 8.0625 | CI31: =IFERROR(AVERAGEIF(AULAS_TESTE!$F:$F,$B31,AULAS_TESTE!T:T),"") -> 7.59375
A32: 0 | B32: Nome do Candidato | C32: emaildocandidato@email.com | D32: 11999999999 | E32: História | F32: https://drive.google.com/open?id=1zLQzUoDTVFqEPlT483IEuym2X_MyolPk | G32: https://drive.google.com/open?id=1NBNjuE-jMm3dih-qvY3oP1XaU1omvEsR | H32: Além da formação na área, atuo também como assistente social, com ampla experiência no trabalho com crianças e adolescentes. Essa trajetória me proporcionou um forte engajamento com os jovens, desenvolvendo sensibilidade para compreender e dialogar na linguagem deles, favorecendo a construção de vínculos e o processo de aprendizagem. | J32: A1-A2 (básico) | L32: 11 | M32: 5.95 | N32: 30 | O32: 2.8791667 | P32: #VALUE! | Q32: 4.75 | R32: 6.3333333 | S32: 4.9166667 | T32: 2 | U32: 8.1176471 | Y32: EMEFAF | AB32: 1. Planejamento prévio • Ter um plano de aula bem estruturado, com objetivos claros e atividades previstas. • Preparar materiais com antecedência (apostilas, slides, dinâmicas, vídeos). • Prever possíveis dúvidas e já ter recursos prontos. 2. Rotina e organização • Criar uma rotina fixa (início, desenvolvimento e encerramento) ajuda os alunos a saberem o que esperar. • Usar recursos como cronômetro ou quadro com a sequência das atividades para manter o ritmo. | AC32: 22 | AD32: 17 | AE32: 15 | AF32: 20 | AG32: 19.675 | AH32: Durante o processo letivo, busco confirmar se meus alunos realmente dominaram uma habilidade ou conceito por meio de avaliações formativas e diversificadas, que me permitem acompanhar o aprendizado de forma contínua. Entre as estratégias que utilizo, destaco: • Perguntas diagnósticas durante a aula: faço questionamentos orais ou escritos que me ajudam a identificar rapidamente se os alunos compreenderam o conteúdo. • Atividades práticas: proponho exercícios, estudos de caso, debates, dinâmicas. | AI32: 20 | AJ32: 8 | AK32: 12 | AL32: 9 | AM32: 14.875 | AN32: 1. Técnicas de Estudo Mapeamento do conhecimento prévio • Antes de iniciar um conteúdo, o aluno registra o que já sabe e o que gostaria de saber (técnica KWL – Know, Want, Learned). • Isso ajuda a ativar a memória e dá direção ao estudo. Mapas mentais e esquemas • Ensinar a organizar informações de forma visual, conectando ideias principais e secundárias. • Garantir que o aluno saiba criar o próprio mapa, não apenas copiar. | AO32: GPT | AP32: 17 | AQ32: 26 | AR32: 12 | AT32: 1. Reflexão crítica e autoavaliação • Registro de experiências (diário de bordo docente ou portfólio reflexivo). • Avaliação constante da eficácia das estratégias de ensino com base no feedback dos alunos. • Inspiração em Donald Schön (1992) e sua ideia de “profissional reflexivo”, que aprende a partir da própria prática. 2. Formação continuada • Participação em cursos, oficinas, simpósios e comunidades de prática. • Busca de certificações em metodologias inovadoras (ensino híbrido, gamificação, design thinking, aprendizagem baseada em projetos). | AU32: GPT | AV32: 15 | AW32: 23 | AX32: 18 | BB32: 15 | BC32: 4 | BD32: 6 | BE32: 0 | BF32: 3 | BG32: 4 | BH32: 15 | BI32: 8 | BJ32: 10 | BK32: 1 | BL32: 7.5 | BM32: 10 | BN32: 12 | BO32: 2 | BP32: 5 | BQ32: 2.5 | BR32: 12 | BS32: 6 | BT32: 15 | BV32: =IFERROR(AVERAGEIF(AULAS_TESTE!$F:$F,$B32,AULAS_TESTE!G:G),"") -> 6.7941176 | BW32: =IFERROR(AVERAGEIF(AULAS_TESTE!$F:$F,$B32,AULAS_TESTE!H:H),"") -> 7.3529412 | BX32: =IFERROR(AVERAGEIF(AULAS_TESTE!$F:$F,$B32,AULAS_TESTE!I:I),"") -> 8.1764706 | BY32: =IFERROR(AVERAGEIF(AULAS_TESTE!$F:$F,$B32,AULAS_TESTE!J:J),"") -> 7.65625 | BZ32: =IFERROR(AVERAGEIF(AULAS_TESTE!$F:$F,$B32,AULAS_TESTE!K:K),"") -> 7.7333333 | CA32: =IFERROR(AVERAGEIF(AULAS_TESTE!$F:$F,$B32,AULAS_TESTE!L:L),"") -> 6.8076923 | CB32: =IFERROR(AVERAGEIF(AULAS_TESTE!$F:$F,$B32,AULAS_TESTE!M:M),"") -> 8.1176471 | CC32: =IFERROR(AVERAGEIF(AULAS_TESTE!$F:$F,$B32,AULAS_TESTE!N:N),"") -> 8.3125 | CD32: =IFERROR(AVERAGEIF(AULAS_TESTE!$F:$F,$B32,AULAS_TESTE!O:O),"") -> 7.5588235 | CE32: =IFERROR(AVERAGEIF(AULAS_TESTE!$F:$F,$B32,AULAS_TESTE!P:P),"") -> 7.6875 | CF32: =IFERROR(AVERAGEIF(AULAS_TESTE!$F:$F,$B32,AULAS_TESTE!Q:Q),"") -> 7.5 | CG32: =IFERROR(AVERAGEIF(AULAS_TESTE!$F:$F,$B32,AULAS_TESTE!R:R),"") -> 6.2727273 | CH32: =IFERROR(AVERAGEIF(AULAS_TESTE!$F:$F,$B32,AULAS_TESTE!S:S),"") -> 8.0625 | CI32: =IFERROR(AVERAGEIF(AULAS_TESTE!$F:$F,$B32,AULAS_TESTE!T:T),"") -> 7.59375
A33: 0 | B33: Nome do Candidato | C33: emaildocandidato@email.com | D33: 11999999999 | E33: Português (Produção e Interpretação de Texto) | F33: https://drive.google.com/open?id=1VRDUoYQRJNeASlTuzFsld14YR5aIiUbv | G33: https://drive.google.com/open?id=1P9Ka0dc_kkeNaKJThcZESvsbmTnWatpp | H33: Meu diferencial é a facilidade de desenvolver projetos. Ao longo de minha atuação, coordenei palestras e auxiliei a gestão de eventos acadêmicos. Consigo tanto atuar em conjunto, em projetos interdisciplinares, quando liderar e propor iniciativas no domínio da minha disciplina. | J33: A1-A2 (básico) | L33: 10 | M33: 6.5172414 | N33: 4 | O33: 5.75 | P33: 3.25 | Q33: 4.75 | R33: 6.5833333 | S33: 4.8333333 | T33: 27 | U33: 7.0588235 | V33: 5.5 | Y33: EMEFAF | AB33: Eu estruturo a aula em roteiro, com tempo delimitado para cada ação. No início, contextualizo, apresentando objetivo e relevância da aula, o assunto com base em atualidades ou textos. Na sequência, sistematizo o conteúdo, apoiando-me em lousa/quadro e/ou em material digital. Por fim, retomo objetivos e conteúdos para concluir a aula. Importante também expor todo o processo de ensino-aprendizagem à turma, para que tenha consciência das etapas e do tempo necessário. | AC33: 20 | AD33: 15 | AE33: 18 | AF33: 12 | AG33: 17.5 | AH33: No ensino de língua, sobretudo, é fundamental avaliar níveis de leitura e de escrita, em variados gêneros. Dessa forma, mobilizo diferentes meios e métodos ao longo do processo letivo. Avaliações orais em grupo, provas objetivas e dissertativas, trabalhos escritos são alternativas em sala. Ainda, práticas em metodologias ativas, como cultura maker, possibilitam outra análise dos estudantes. Organizo os dados em planilhas, para entender, com precisão, o avanço (ou possível estagnação) do estudante. Assim, aplico, repensando o método, retomada de conteúdo, a depender do caso, em diálogo com a Coordenação. | AI33: 19 | AJ33: 14 | AK33: 22 | AL33: 12 | AM33: 17.55 | AN33: Resumo, mapa mental e fichamentos são formas que pratico para estudo. Explico a estrutura dessas técnicas, de modo que os estudantes reconheçam a ideia principal a ser focada. Estudo precisa ser ativo, com intenção e contextualizado. Além disso, oferto os materiais usados em sala e outras referências para embasar o estudo. Como são nativos digitais, podem reforçar/aprofundar ideias e conceitos com vídeos em Youtube. Recomendo sempre Carol Jesper e Jana Viscardi, produtoras de conteúdo de excelência. Além disso, a agenda da disciplina é crucial para que a turma tenha ciência de datas importantes e consiga organizar rotinas de estudos. | AP33: 12 | AQ33: 18 | AR33: 13 | AS33: 14.45 | AT33: Mantenho leitura de Marcuschi, Koch, Geraldi e demais clássicos do ensino de português e acompanho grupos de pesquisa (Márcia Mendonça/UNICAMP e Suzana Cortez/UFPE). Além disso, participo de eventos e cursos, como o Seminário do GEL e programação da Companhia na Educação. O contato direto, no LinkedIn e na escola, com outros docentes também me auxilia na formação. O diálogo entre pares é enriquecedor e oferece um ponto de vista singular. Além do conteúdo específico, acompanho e leio produções em educação antirracista (Fernanda Sousa, editora e professora), propondo um ensino de valor democrático. | AV33: 16 | AW33: 21 | AX33: 21 | AY33: 19.5 | BB33: 12 | BC33: 4 | BD33: 4 | BE33: 0 | BF33: 2 | BG33: 5 | BH33: 15 | BI33: 4 | BJ33: 8 | BK33: 0.5 | BL33: 7.5 | BM33: 8 | BN33: 15 | BO33: 2 | BP33: 5 | BQ33: 2.5 | BR33: 3 | BS33: 7.5 | BT33: 15 | BV33: =IFERROR(AVERAGEIF(AULAS_TESTE!$F:$F,$B33,AULAS_TESTE!G:G),"") -> 6.7941176 | BW33: =IFERROR(AVERAGEIF(AULAS_TESTE!$F:$F,$B33,AULAS_TESTE!H:H),"") -> 7.3529412 | BX33: =IFERROR(AVERAGEIF(AULAS_TESTE!$F:$F,$B33,AULAS_TESTE!I:I),"") -> 8.1764706 | BY33: =IFERROR(AVERAGEIF(AULAS_TESTE!$F:$F,$B33,AULAS_TESTE!J:J),"") -> 7.65625 | BZ33: =IFERROR(AVERAGEIF(AULAS_TESTE!$F:$F,$B33,AULAS_TESTE!K:K),"") -> 7.7333333 | CA33: =IFERROR(AVERAGEIF(AULAS_TESTE!$F:$F,$B33,AULAS_TESTE!L:L),"") -> 6.8076923 | CB33: =IFERROR(AVERAGEIF(AULAS_TESTE!$F:$F,$B33,AULAS_TESTE!M:M),"") -> 8.1176471 | CC33: =IFERROR(AVERAGEIF(AULAS_TESTE!$F:$F,$B33,AULAS_TESTE!N:N),"") -> 8.3125 | CD33: =IFERROR(AVERAGEIF(AULAS_TESTE!$F:$F,$B33,AULAS_TESTE!O:O),"") -> 7.5588235 | CE33: =IFERROR(AVERAGEIF(AULAS_TESTE!$F:$F,$B33,AULAS_TESTE!P:P),"") -> 7.6875 | CF33: =IFERROR(AVERAGEIF(AULAS_TESTE!$F:$F,$B33,AULAS_TESTE!Q:Q),"") -> 7.5 | CG33: =IFERROR(AVERAGEIF(AULAS_TESTE!$F:$F,$B33,AULAS_TESTE!R:R),"") -> 6.2727273 | CH33: =IFERROR(AVERAGEIF(AULAS_TESTE!$F:$F,$B33,AULAS_TESTE!S:S),"") -> 8.0625 | CI33: =IFERROR(AVERAGEIF(AULAS_TESTE!$F:$F,$B33,AULAS_TESTE!T:T),"") -> 7.59375
A34: 0 | B34: Nome do Candidato | C34: emaildocandidato@email.com | D34: 11999999999 | E34: Português (Produção e Interpretação de Texto) | F34: https://drive.google.com/open?id=1KbG9fBoOrYi_Cl9LxhNgc-zDU_PkXoxP | G34: https://drive.google.com/open?id=1UAZquQ5UedhlLb_NS_6x3UGhwORu0FKq | I34: Agradeço a oportunidade de participar do processo | J34: A1-A2 (básico) | L34: 26 | M34: 5.6275862 | N34: 36 | O34: 2.2666667 | P34: 1.5 | Q34: 1.1666667 | R34: 2.4166667 | S34: 1.9166667 | T34: 9 | U34: 8 | V34: 6.5 | W34: 2.3 | X34: 3.7 | Y34: EMEFAF | AB34: Organização e disciplina são fundamentais para o andamento do planejamento de aula. | AC34: 10 | AD34: 0 | AE34: 5 | AF34: 4 | AG34: 6.575 | AH34: A participação em sala com retomada de conceitos e exercícios práticos individuais e em grupo. | AI34: 8 | AJ34: 7 | AK34: 5 | AL34: 4 | AM34: 6.625 | AN34: Cronograma de estudos, geralmente com a ajuda da coordenação pedagógica. | AP34: 2 | AQ34: 9 | AR34: 3 | AS34: 4.8 | AT34: Estudo constante. Participo de cursos de aperfeiçoamento. Em sala, tento me valer de parte do método freiriano, respeitando os saberes dos estudantes e abrindo espaço para que eu possa conhecer parte da cultura e vivência de cada um. A participação e confiança em sala costumam ser maiores e os resultados mais positivos. | AV34: 5 | AW34: 10 | AX34: 12 | AY34: 9.2 | BB34: 15 | BC34: 4 | BD34: 6 | BE34: 0 | BF34: 3 | BG34: 5 | BH34: 15 | BI34: 6 | BJ34: 8 | BK34: 2 | BL34: 7.5 | BM34: 10 | BN34: 12 | BO34: 0.5 | BP34: 5 | BQ34: 2.5 | BR34: 12 | BS34: 7.5 | BT34: 15 | BV34: =IFERROR(AVERAGEIF(AULAS_TESTE!$F:$F,$B34,AULAS_TESTE!G:G),"") -> 6.7941176 | BW34: =IFERROR(AVERAGEIF(AULAS_TESTE!$F:$F,$B34,AULAS_TESTE!H:H),"") -> 7.3529412 | BX34: =IFERROR(AVERAGEIF(AULAS_TESTE!$F:$F,$B34,AULAS_TESTE!I:I),"") -> 8.1764706 | BY34: =IFERROR(AVERAGEIF(AULAS_TESTE!$F:$F,$B34,AULAS_TESTE!J:J),"") -> 7.65625 | BZ34: =IFERROR(AVERAGEIF(AULAS_TESTE!$F:$F,$B34,AULAS_TESTE!K:K),"") -> 7.7333333 | CA34: =IFERROR(AVERAGEIF(AULAS_TESTE!$F:$F,$B34,AULAS_TESTE!L:L),"") -> 6.8076923 | CB34: =IFERROR(AVERAGEIF(AULAS_TESTE!$F:$F,$B34,AULAS_TESTE!M:M),"") -> 8.1176471 | CC34: =IFERROR(AVERAGEIF(AULAS_TESTE!$F:$F,$B34,AULAS_TESTE!N:N),"") -> 8.3125 | CD34: =IFERROR(AVERAGEIF(AULAS_TESTE!$F:$F,$B34,AULAS_TESTE!O:O),"") -> 7.5588235 | CE34: =IFERROR(AVERAGEIF(AULAS_TESTE!$F:$F,$B34,AULAS_TESTE!P:P),"") -> 7.6875 | CF34: =IFERROR(AVERAGEIF(AULAS_TESTE!$F:$F,$B34,AULAS_TESTE!Q:Q),"") -> 7.5 | CG34: =IFERROR(AVERAGEIF(AULAS_TESTE!$F:$F,$B34,AULAS_TESTE!R:R),"") -> 6.2727273 | CH34: =IFERROR(AVERAGEIF(AULAS_TESTE!$F:$F,$B34,AULAS_TESTE!S:S),"") -> 8.0625 | CI34: =IFERROR(AVERAGEIF(AULAS_TESTE!$F:$F,$B34,AULAS_TESTE!T:T),"") -> 7.59375
A35: 0 | B35: Nome do Candidato | C35: emaildocandidato@email.com | D35: 11999999999 | E35: Português (Produção e Interpretação de Texto) | F35: https://drive.google.com/open?id=1bRxEjay1v7HVjlJWHHOI--7mSBk224-v | G35: https://drive.google.com/open?id=1mVBXijBpoMck4R_yP7bsSTSJM3xmdLpK | H35: Faço curso de aprofundamento em redação e leitura. Formadora de professores em 2024, Já participei do projeto de professora orientadora de convivência e atualmente como professora articuladora na sala de leitura. | I35: . | J35: B1-B2 (intermediário) | L35: 29 | M35: 5.4008621 | N35: 31 | O35: 2.5104167 | P35: 1.5833333 | Q35: 1.1666667 | R35: 2.9166667 | S35: 2.4166667 | T35: 21 | U35: 7.4411765 | Y35: EMEFAF | AB35: Elaborar um bom planejamento de aula, estudar o material que o colégio utiliza. | AC35: 3 | AD35: 0 | AE35: 5 | AF35: 6 | AG35: 3.425 | AH35: Prova objetiva, produção de textos, diário de bordo. | AI35: 16 | AJ35: 6 | AK35: 12 | AL35: 6 | AM35: 12.05 | AN35: Mapa mental, resumo. | AP35: 2 | AQ35: 7 | AR35: 6 | AS35: 5.15 | AT35: Procuro acompanhar os resultados para fazer replanejamento de aulas. Aplicar metodologias ativas e sempre que possível atividades de mão na massa. | AV35: 6 | AW35: 11 | AX35: 11 | AY35: 9.5 | BB35: 15 | BC35: 6 | BD35: 2 | BE35: 0 | BF35: 3 | BG35: 5 | BH35: 15 | BI35: 4 | BJ35: 10 | BK35: 0.5 | BL35: 7.5 | BM35: 6 | BN35: 6 | BO35: 1.5 | BP35: 5 | BQ35: 2.5 | BR35: 15 | BS35: 7.5 | BT35: 15 | BV35: =IFERROR(AVERAGEIF(AULAS_TESTE!$F:$F,$B35,AULAS_TESTE!G:G),"") -> 6.7941176 | BW35: =IFERROR(AVERAGEIF(AULAS_TESTE!$F:$F,$B35,AULAS_TESTE!H:H),"") -> 7.3529412 | BX35: =IFERROR(AVERAGEIF(AULAS_TESTE!$F:$F,$B35,AULAS_TESTE!I:I),"") -> 8.1764706 | BY35: =IFERROR(AVERAGEIF(AULAS_TESTE!$F:$F,$B35,AULAS_TESTE!J:J),"") -> 7.65625 | BZ35: =IFERROR(AVERAGEIF(AULAS_TESTE!$F:$F,$B35,AULAS_TESTE!K:K),"") -> 7.7333333 | CA35: =IFERROR(AVERAGEIF(AULAS_TESTE!$F:$F,$B35,AULAS_TESTE!L:L),"") -> 6.8076923 | CB35: =IFERROR(AVERAGEIF(AULAS_TESTE!$F:$F,$B35,AULAS_TESTE!M:M),"") -> 8.1176471 | CC35: =IFERROR(AVERAGEIF(AULAS_TESTE!$F:$F,$B35,AULAS_TESTE!N:N),"") -> 8.3125 | CD35: =IFERROR(AVERAGEIF(AULAS_TESTE!$F:$F,$B35,AULAS_TESTE!O:O),"") -> 7.5588235 | CE35: =IFERROR(AVERAGEIF(AULAS_TESTE!$F:$F,$B35,AULAS_TESTE!P:P),"") -> 7.6875 | CF35: =IFERROR(AVERAGEIF(AULAS_TESTE!$F:$F,$B35,AULAS_TESTE!Q:Q),"") -> 7.5 | CG35: =IFERROR(AVERAGEIF(AULAS_TESTE!$F:$F,$B35,AULAS_TESTE!R:R),"") -> 6.2727273 | CH35: =IFERROR(AVERAGEIF(AULAS_TESTE!$F:$F,$B35,AULAS_TESTE!S:S),"") -> 8.0625 | CI35: =IFERROR(AVERAGEIF(AULAS_TESTE!$F:$F,$B35,AULAS_TESTE!T:T),"") -> 7.59375
A36: 0 | B36: Nome do Candidato | C36: emaildocandidato@email.com | D36: 11999999999 | E36: Matemática | F36: https://drive.google.com/open?id=1Q2aIFG0nsX_IXuxplHjogynCBRblero6 | G36: https://drive.google.com/open?id=1L9sdWSQNmseIyBwX91Y404Z61a_caysc | H36: Não mencionei no vídeo que atualmente faço um Pós-Graduação (Latu Sensu) no Sesi em práticas no Ensino da Matemática. Acredito também ser relevante uma reportagem que fizeram comigo e meus alunos do Ensino Técnico em Administração no SEBRAE em Santo André. https://abcdoabc.com.br/alunos-de-escola-publica-de-santo-andre-visitam-o-sebrae-sp-do-grande-abc/#fechar-aviso No Ensino Técnico além de ser professor, sou PAEET - Professor de Apoio ao Estudante do Ensino Técnico. Nesta função tenho algumas atribuições como: Organizar visitas técnicas, mentorias, estágios e projetos multidisciplinares é uma das atribuições mais estratégicas do docente do PAEET. PAEET não é apenas um executor de rotinas escolares, mas um agente articulador de práticas pedagógicas que promovem o desenvolvimento integral dos estudantes. A escuta ativa, o acolhimento, o uso intencional de dados educacionais, os encaminhamentos formativos e o fortalecimento de vínculos não são tarefas isoladas, são estratégias estruturantes de uma escola comprometida com a permanência, com a qualidade, a equidade e a construção de projetos de vida significativos. | J36: A1-A2 (básico) | L36: 13 | M36: 6.2543103 | N36: 14 | O36: 4.6979167 | P36: 1 | Q36: 4.3333333 | R36: 5.5833333 | S36: 3.6666667 | T36: 18 | U36: 7.3529412 | Y36: EMEFAF | AB36: Uma das minhas estratégias é o plano de aula feito de maneira antecipada. O mesmo inclui definir objetivos claros e organizados, selecionar materiais e recursos adequados, e estabelecer um cronograma para cada atividade. | AD36: 11 | AE36: 12 | AF36: 8 | AG36: 10.3 | AH36: Durante o processo letivo, obtenho a confirmação do domínio das habilidades ou conceitos trabalhados em aula por meio de avaliações, lista de exercícios, trabalhos práticos (a depender do conteúdo), discussões em grupo e observações em sala de aula. | AI36: 12 | AJ36: 5 | AK36: 12 | AL36: 7 | AM36: 10.075 | AN36: Ensino meus alunos a se organizarem, definirem metas e priorizarem tarefas, utilizando metodologias ativas como Resolução de Problemas, para que desenvolvam habilidades matemáticas e sejam protagonistas do seu aprendizado. | AP36: 11 | AQ36: 20 | AR36: 10 | AS36: 13.8 | AT36: Trabalho buscando sempre aplicar técnicas eficazes como as apresentadas por Doug Lemov, além de metodologias ativas como Aprendizagem Baseada em Projetos e Resolução de Problemas. Busco inspiração em autores que fundamentam práticas pedagógicas inovadoras, adaptando-as às necessidades dos meus alunos para promover um aprendizado significativo. | AV36: 25 | AW36: 23 | AX36: 19 | AY36: 22.2 | BB36: 15 | BC36: 8 | BD36: 8 | BE36: 0 | BF36: 4 | BG36: 3 | BH36: 9 | BI36: 8 | BJ36: 4 | BK36: 0.5 | BL36: 6 | BM36: 10 | BN36: 3 | BO36: 1.5 | BP36: 5 | BQ36: 2.5 | BR36: 15 | BS36: 7.5 | BT36: 15 | BV36: =IFERROR(AVERAGEIF(AULAS_TESTE!$F:$F,$B36,AULAS_TESTE!G:G),"") -> 6.7941176 | BW36: =IFERROR(AVERAGEIF(AULAS_TESTE!$F:$F,$B36,AULAS_TESTE!H:H),"") -> 7.3529412 | BX36: =IFERROR(AVERAGEIF(AULAS_TESTE!$F:$F,$B36,AULAS_TESTE!I:I),"") -> 8.1764706 | BY36: =IFERROR(AVERAGEIF(AULAS_TESTE!$F:$F,$B36,AULAS_TESTE!J:J),"") -> 7.65625 | BZ36: =IFERROR(AVERAGEIF(AULAS_TESTE!$F:$F,$B36,AULAS_TESTE!K:K),"") -> 7.7333333 | CA36: =IFERROR(AVERAGEIF(AULAS_TESTE!$F:$F,$B36,AULAS_TESTE!L:L),"") -> 6.8076923 | CB36: =IFERROR(AVERAGEIF(AULAS_TESTE!$F:$F,$B36,AULAS_TESTE!M:M),"") -> 8.1176471 | CC36: =IFERROR(AVERAGEIF(AULAS_TESTE!$F:$F,$B36,AULAS_TESTE!N:N),"") -> 8.3125 | CD36: =IFERROR(AVERAGEIF(AULAS_TESTE!$F:$F,$B36,AULAS_TESTE!O:O),"") -> 7.5588235 | CE36: =IFERROR(AVERAGEIF(AULAS_TESTE!$F:$F,$B36,AULAS_TESTE!P:P),"") -> 7.6875 | CF36: =IFERROR(AVERAGEIF(AULAS_TESTE!$F:$F,$B36,AULAS_TESTE!Q:Q),"") -> 7.5 | CG36: =IFERROR(AVERAGEIF(AULAS_TESTE!$F:$F,$B36,AULAS_TESTE!R:R),"") -> 6.2727273 | CH36: =IFERROR(AVERAGEIF(AULAS_TESTE!$F:$F,$B36,AULAS_TESTE!S:S),"") -> 8.0625 | CI36: =IFERROR(AVERAGEIF(AULAS_TESTE!$F:$F,$B36,AULAS_TESTE!T:T),"") -> 7.59375
A37: 0 | B37: Nome do Candidato | C37: emaildocandidato@email.com | D37: 11999999999 | E37: Geografia | F37: https://drive.google.com/open?id=1GsttLuCoAMsozAFuK2N5DmiC_iDH-BwV | G37: https://drive.google.com/open?id=1ArTeePx-n7DT7TkWnhG1nvEniA3pty5g | H37: Coordenação de simulação de Assembleias da ONU. Professor responsável pela organização das olimpíadas de Geografia. Elaborador de questões adaptadas para alunos neuroatípicos | J37: B1-B2 (intermediário) | L37: 7 | M37: 6.4275862 | N37: 6 | O37: 5.2833333 | P37: 1.5833333 | Q37: 5.0833333 | R37: 5.0833333 | S37: 4.8333333 | T37: 13 | U37: 7.2352941 | V37: 9 | W37: 5.7 | X37: 6.8 | Y37: EMEFAF | AB37: Para otimizar o tempo em sala de aula, o professor deve planejar objetivos claros e organizar a aula em blocos de tempo. Rotinas bem definidas evitam dispersão e facilitam as transições entre atividades. O desenvolvimento de metodologias ativas, como trabalhos em grupo aumenta o engajamento. Materiais preparados previamente e instruções objetivas reduzem perdas de tempo. O uso de tecnologias pode apoiar na organização e no acompanhamento da aprendizagem. | AD37: 20 | AE37: 15 | AF37: 12 | AG37: 15.45 | AH37: Para confirmar o domínio de conceitos e habilidades, utilizo avaliações parciais como perguntas orais, exercícios curtos e atividades em grupo. Também observo a aplicação prática e incentivo a autoavaliação dos alunos. Essas estratégias permitem identificar dificuldades rapidamente e ajustar o ensino, garantindo avanços no processo de aprendizagem. | AI37: 19 | AJ37: 10 | AK37: 12 | AL37: 14 | AM37: 15.55 | AN37: Creio que seja importante desenvolver técnicas que promovem autonomia, como a organização de resumos e mapas mentais, praticar a autoexplicação e revisar conteúdos periodicamente. Também incentivo a definição de metas e o registro de dúvidas. Essas práticas ajudam o aluno a gerir seus estudos, acompanhar o próprio progresso e assumir responsabilidade pelo aprendizado. | AP37: 20 | AQ37: 23 | AR37: 18 | AS37: 20.35 | AT37: Renovo minhas técnicas de sala de aula por meio de formações continuadas, trocas com colegas, observação crítica da prática e atualização em pesquisas educacionais. Apoio-me em referências como Paulo Freire, com a educação dialógica, buscando uma aprendizagem ativa com aulas mais participativas e significativas. | AV37: 11 | AW37: 11 | AX37: 14 | AY37: 12.05 | BB37: 15 | BC37: 4 | BD37: 4 | BE37: 0 | BF37: 2 | BG37: 5 | BH37: 15 | BI37: 4 | BJ37: 10 | BK37: 0.5 | BL37: 6 | BM37: 8 | BN37: 9 | BO37: 1.5 | BP37: 5 | BQ37: 2.5 | BR37: 9 | BS37: 7.5 | BT37: 15 | BV37: =IFERROR(AVERAGEIF(AULAS_TESTE!$F:$F,$B37,AULAS_TESTE!G:G),"") -> 6.7941176 | BW37: =IFERROR(AVERAGEIF(AULAS_TESTE!$F:$F,$B37,AULAS_TESTE!H:H),"") -> 7.3529412 | BX37: =IFERROR(AVERAGEIF(AULAS_TESTE!$F:$F,$B37,AULAS_TESTE!I:I),"") -> 8.1764706 | BY37: =IFERROR(AVERAGEIF(AULAS_TESTE!$F:$F,$B37,AULAS_TESTE!J:J),"") -> 7.65625 | BZ37: =IFERROR(AVERAGEIF(AULAS_TESTE!$F:$F,$B37,AULAS_TESTE!K:K),"") -> 7.7333333 | CA37: =IFERROR(AVERAGEIF(AULAS_TESTE!$F:$F,$B37,AULAS_TESTE!L:L),"") -> 6.8076923 | CB37: =IFERROR(AVERAGEIF(AULAS_TESTE!$F:$F,$B37,AULAS_TESTE!M:M),"") -> 8.1176471 | CC37: =IFERROR(AVERAGEIF(AULAS_TESTE!$F:$F,$B37,AULAS_TESTE!N:N),"") -> 8.3125 | CD37: =IFERROR(AVERAGEIF(AULAS_TESTE!$F:$F,$B37,AULAS_TESTE!O:O),"") -> 7.5588235 | CE37: =IFERROR(AVERAGEIF(AULAS_TESTE!$F:$F,$B37,AULAS_TESTE!P:P),"") -> 7.6875 | CF37: =IFERROR(AVERAGEIF(AULAS_TESTE!$F:$F,$B37,AULAS_TESTE!Q:Q),"") -> 7.5 | CG37: =IFERROR(AVERAGEIF(AULAS_TESTE!$F:$F,$B37,AULAS_TESTE!R:R),"") -> 6.2727273 | CH37: =IFERROR(AVERAGEIF(AULAS_TESTE!$F:$F,$B37,AULAS_TESTE!S:S),"") -> 8.0625 | CI37: =IFERROR(AVERAGEIF(AULAS_TESTE!$F:$F,$B37,AULAS_TESTE!T:T),"") -> 7.59375
A38: 0 | B38: Nome do Candidato | C38: emaildocandidato@email.com | D38: 11999999999 | E38: Biologia | F38: https://drive.google.com/open?id=1AqD1chLslneTCCMq1aJ1ASO0MIWHPq9I | G38: https://drive.google.com/open?id=1B1YIC-9_g6FRm-c-qCQX-PrOnpHr7jJk | J38: B1-B2 (intermediário) | L38: 20 | M38: 5.8827586 | N38: 13 | O38: 4.55 | P38: 1.75 | Q38: 2.8333333 | R38: 5.8333333 | S38: 3.4166667 | T38: 31 | U38: 6.8235294 | Y38: EMEFAF | AB38: Todas as aulas sempre têm um objetivo claro de acordo com um planejamento detalhado. Os alunos sabem onde estamos e onde devemos chegar. Isso inclui a rotina de organização da sala que ao inicio do ano letivo é combinada com os próprios alunos. Sempre levo em consideração suas opiniões e em conversa acordamos como será a rotina de início e término das aulas para que não seja algo imposto, mas sim de comum acordo. | AD38: 13 | AE38: 22 | AF38: 11 | AG38: 15.45 | AH38: Costumo utilizar diferentes formas de avaliação. Trabalho bastante com mini projetos que incluem seminários, dramatização, cartazes, desenhos, maquetes e autoavaliação. Utilizo também pequenos questionários de sala em pares ou quando sinto a necessidade, individuais. Gosto também de fazer aulas de estudos, onde em pares os alunos podem contribuir uns com os outros. Todas essas estratégias são sempre avaliadas durante as aulas para que os alunos tenham feedback de como estão evoluindo e se absorveram corretamente os conteúdos abordados. | AI38: 21 | AJ38: 5 | AK38: 15 | AL38: 9 | AM38: 15.45 | AN38: Costumo trabalhar bastante a autonomia, responsabilidade, gestão de tempo, colaboração e confiança. Tenho o hábito de incentivá-los e compreender que são os protagonistas da sua aprendizagem. Trabalhos individuais, em grupos ou em pares são essenciais para o desenvolvimento dessas habilidades. Incentivo-os também a trabalhar com pessoas que normalmente não trabalhariam, porque todos tem algo a ensinar e aprender. Tais habilidades, inicialmente, são explicadas e direcionadas por mim, mas com o passar do tempo e com os objetivos estabelecidos em aula, cada um deve utilizar o que aprendeu para que assim minha atuação seja como mediadora. | AP38: 7 | AQ38: 22 | AR38: 12 | AS38: 14 | AT38: Em minhas aulas utilizo muito as técnicas de Paulo Freire e Piaget para garantir uma abordagem de diálogo aberto, respeito ao conhecimentos já adquiridos pelos alunos, feedback construtivo e respeito as diferenças, proporcionando um espaço de aprendizagem colaborativo e participativo onde cada aluno compreenda que é único, mas também faz parte de um todo. A renovação se dá através das características do grupo e a forma como essas técnicas serão abordadas, para assim criar um ambiente acolhedor e de confiança para os alunos. | AV38: 9 | AW38: 11 | AX38: 9 | AY38: 9.7 | BB38: 15 | BC38: 2 | BD38: 2 | BE38: 0 | BF38: 1 | BG38: 5 | BH38: 15 | BI38: 6 | BJ38: 6 | BK38: 1 | BL38: 7.5 | BM38: 6 | BN38: 3 | BO38: 1.5 | BP38: 5 | BQ38: 2.5 | BR38: 15 | BS38: 7.5 | BT38: 15 | BV38: =IFERROR(AVERAGEIF(AULAS_TESTE!$F:$F,$B38,AULAS_TESTE!G:G),"") -> 6.7941176 | BW38: =IFERROR(AVERAGEIF(AULAS_TESTE!$F:$F,$B38,AULAS_TESTE!H:H),"") -> 7.3529412 | BX38: =IFERROR(AVERAGEIF(AULAS_TESTE!$F:$F,$B38,AULAS_TESTE!I:I),"") -> 8.1764706 | BY38: =IFERROR(AVERAGEIF(AULAS_TESTE!$F:$F,$B38,AULAS_TESTE!J:J),"") -> 7.65625 | BZ38: =IFERROR(AVERAGEIF(AULAS_TESTE!$F:$F,$B38,AULAS_TESTE!K:K),"") -> 7.7333333 | CA38: =IFERROR(AVERAGEIF(AULAS_TESTE!$F:$F,$B38,AULAS_TESTE!L:L),"") -> 6.8076923 | CB38: =IFERROR(AVERAGEIF(AULAS_TESTE!$F:$F,$B38,AULAS_TESTE!M:M),"") -> 8.1176471 | CC38: =IFERROR(AVERAGEIF(AULAS_TESTE!$F:$F,$B38,AULAS_TESTE!N:N),"") -> 8.3125 | CD38: =IFERROR(AVERAGEIF(AULAS_TESTE!$F:$F,$B38,AULAS_TESTE!O:O),"") -> 7.5588235 | CE38: =IFERROR(AVERAGEIF(AULAS_TESTE!$F:$F,$B38,AULAS_TESTE!P:P),"") -> 7.6875 | CF38: =IFERROR(AVERAGEIF(AULAS_TESTE!$F:$F,$B38,AULAS_TESTE!Q:Q),"") -> 7.5 | CG38: =IFERROR(AVERAGEIF(AULAS_TESTE!$F:$F,$B38,AULAS_TESTE!R:R),"") -> 6.2727273 | CH38: =IFERROR(AVERAGEIF(AULAS_TESTE!$F:$F,$B38,AULAS_TESTE!S:S),"") -> 8.0625 | CI38: =IFERROR(AVERAGEIF(AULAS_TESTE!$F:$F,$B38,AULAS_TESTE!T:T),"") -> 7.59375
A39: 0 | B39: Nome do Candidato | C39: emaildocandidato@email.com | D39: 11999999999 | E39: Português (Literatura) | F39: https://drive.google.com/open?id=1JqQWLKnnfiAmnGiouqeAxy48b5KYXa-o | G39: https://drive.google.com/open?id=1F53cw1x0zNNR7AtbY4h6iz6EFwstkKZj | H39: Estar sempre atualizado | I39: Gosto de usar a criatividade ao meu favor. | J39: A1-A2 (básico) | L39: 12 | M39: 4.162069 | N39: 11 | O39: 2.0583333 | P39: 1.1666667 | Q39: 0.66666667 | R39: 3 | S39: 1.3333333 | T39: 12 | U39: 5.6470588 | Y39: EMEFAF | AB39: Fazer sala invertida | AD39: 4 | AE39: 8 | AF39: 4 | AG39: 5.4 | AH39: Fazer exercícios de fixação diariamente | AI39: 14 | AJ39: 3 | AK39: 10 | AL39: 4 | AM39: 9.9 | AN39: Estudar por palavras chaves | AP39: 1 | AQ39: 11 | AR39: 2 | AS39: 4.85 | AT39: Sempre fazendo o conteúdo ter sentido dentro da realidade do aluno. | AV39: 0 | AW39: 7 | AX39: 6 | AY39: 4.55 | BB39: 9 | BC39: 8 | BD39: 6 | BE39: 0 | BF39: 4 | BG39: 2 | BH39: 9 | BI39: 8 | BJ39: 4 | BK39: 1.5 | BL39: 4.5 | BM39: 6 | BN39: 9 | BO39: 1.5 | BP39: 4 | BQ39: 1.5 | BR39: 6 | BS39: 6 | BT39: 6 | BV39: =IFERROR(AVERAGEIF(AULAS_TESTE!$F:$F,$B39,AULAS_TESTE!G:G),"") -> 6.7941176 | BW39: =IFERROR(AVERAGEIF(AULAS_TESTE!$F:$F,$B39,AULAS_TESTE!H:H),"") -> 7.3529412 | BX39: =IFERROR(AVERAGEIF(AULAS_TESTE!$F:$F,$B39,AULAS_TESTE!I:I),"") -> 8.1764706 | BY39: =IFERROR(AVERAGEIF(AULAS_TESTE!$F:$F,$B39,AULAS_TESTE!J:J),"") -> 7.65625 | BZ39: =IFERROR(AVERAGEIF(AULAS_TESTE!$F:$F,$B39,AULAS_TESTE!K:K),"") -> 7.7333333 | CA39: =IFERROR(AVERAGEIF(AULAS_TESTE!$F:$F,$B39,AULAS_TESTE!L:L),"") -> 6.8076923 | CB39: =IFERROR(AVERAGEIF(AULAS_TESTE!$F:$F,$B39,AULAS_TESTE!M:M),"") -> 8.1176471 | CC39: =IFERROR(AVERAGEIF(AULAS_TESTE!$F:$F,$B39,AULAS_TESTE!N:N),"") -> 8.3125 | CD39: =IFERROR(AVERAGEIF(AULAS_TESTE!$F:$F,$B39,AULAS_TESTE!O:O),"") -> 7.5588235 | CE39: =IFERROR(AVERAGEIF(AULAS_TESTE!$F:$F,$B39,AULAS_TESTE!P:P),"") -> 7.6875 | CF39: =IFERROR(AVERAGEIF(AULAS_TESTE!$F:$F,$B39,AULAS_TESTE!Q:Q),"") -> 7.5 | CG39: =IFERROR(AVERAGEIF(AULAS_TESTE!$F:$F,$B39,AULAS_TESTE!R:R),"") -> 6.2727273 | CH39: =IFERROR(AVERAGEIF(AULAS_TESTE!$F:$F,$B39,AULAS_TESTE!S:S),"") -> 8.0625 | CI39: =IFERROR(AVERAGEIF(AULAS_TESTE!$F:$F,$B39,AULAS_TESTE!T:T),"") -> 7.59375
A40: 0 | B40: Nome do Candidato | C40: emaildocandidato@email.com | D40: 11999999999 | E40: Biologia | F40: https://drive.google.com/open?id=1AOdRX_LhYBXQyGheMcHUDOZ4pFLTd0GY | G40: https://drive.google.com/open?id=1DBUYc0wsIWHChEgCeXs3rbGH_sZNJlgQ | H40: Sempre me atualizo nas questões da minha área de aprendizagem e afins, já realizei entrevistas para canais como a band e a globo quanto a questão de saúde e bem estar e quanto a cursos sempre que possível estou fazendo para ampliar meu currículo. | J40: A1-A2 (básico) | L40: 27 | M40: 5.2387931 | N40: 30 | O40: 2.6604167 | P40: 0.083333333 | Q40: 2.5833333 | R40: 3.5833333 | S40: 2.25 | T40: 24 | U40: 7.0588235 | V40: 5.5 | Y40: EMEFAF | AB40: Sou dinâmico com as atividades incluindo atividades experimentais ! | AD40: 0 | AE40: 5 | AF40: 5 | AG40: 3.5 | AH40: Participação em aula invertida sendo elas dinâmicas com contraproposta explorando as habilidades dos alunos! | AI40: 1 | AJ40: 3 | AK40: 6 | AL40: 5 | AM40: 2.875 | AN40: Técnica do fazer e fazer direito, auxiliar em sala de como fazer as atividades desenvolvendo com eles formas de resoluções invertidas onde eles me mostrem como eles chegaram ao resultado esperado! | AP40: 25 | AQ40: 21 | AR40: 11 | AS40: 18.7 | AT40: Toda habilidade possui uma técnica diferente do que você conheceu, buscou e aprendeu em sua vida, pois o mundo está em constante evolução e para mantermos o interesse do aluno e lutando contra a tecnologia devemos trazer os alunos e a tecnologia até nos, hoje aprendi que a melhor maneira é expor as habilidades dos alunos para com eles mesmos pois as linguagens próximas trazem contextos novos e formas inovadoras de aprendizagem! O futuro está em como nós iremos daqui para frente mostrar os valores da educação lutando contra a tecnologia ou sendo a favor dela para nos respaldar-mos para com eles! | AV40: 3 | AW40: 11 | AX40: 6 | AY40: 6.85 | BB40: 12 | BC40: 2 | BD40: 4 | BE40: 0 | BF40: 1 | BG40: 4 | BH40: 15 | BI40: 6 | BJ40: 8 | BK40: 0.5 | BL40: 6 | BM40: 8 | BN40: 12 | BO40: 0.5 | BP40: 1 | BQ40: 2.5 | BR40: 15 | BS40: 7.5 | BT40: 15 | BV40: =IFERROR(AVERAGEIF(AULAS_TESTE!$F:$F,$B40,AULAS_TESTE!G:G),"") -> 6.7941176 | BW40: =IFERROR(AVERAGEIF(AULAS_TESTE!$F:$F,$B40,AULAS_TESTE!H:H),"") -> 7.3529412 | BX40: =IFERROR(AVERAGEIF(AULAS_TESTE!$F:$F,$B40,AULAS_TESTE!I:I),"") -> 8.1764706 | BY40: =IFERROR(AVERAGEIF(AULAS_TESTE!$F:$F,$B40,AULAS_TESTE!J:J),"") -> 7.65625 | BZ40: =IFERROR(AVERAGEIF(AULAS_TESTE!$F:$F,$B40,AULAS_TESTE!K:K),"") -> 7.7333333 | CA40: =IFERROR(AVERAGEIF(AULAS_TESTE!$F:$F,$B40,AULAS_TESTE!L:L),"") -> 6.8076923 | CB40: =IFERROR(AVERAGEIF(AULAS_TESTE!$F:$F,$B40,AULAS_TESTE!M:M),"") -> 8.1176471 | CC40: =IFERROR(AVERAGEIF(AULAS_TESTE!$F:$F,$B40,AULAS_TESTE!N:N),"") -> 8.3125 | CD40: =IFERROR(AVERAGEIF(AULAS_TESTE!$F:$F,$B40,AULAS_TESTE!O:O),"") -> 7.5588235 | CE40: =IFERROR(AVERAGEIF(AULAS_TESTE!$F:$F,$B40,AULAS_TESTE!P:P),"") -> 7.6875 | CF40: =IFERROR(AVERAGEIF(AULAS_TESTE!$F:$F,$B40,AULAS_TESTE!Q:Q),"") -> 7.5 | CG40: =IFERROR(AVERAGEIF(AULAS_TESTE!$F:$F,$B40,AULAS_TESTE!R:R),"") -> 6.2727273 | CH40: =IFERROR(AVERAGEIF(AULAS_TESTE!$F:$F,$B40,AULAS_TESTE!S:S),"") -> 8.0625 | CI40: =IFERROR(AVERAGEIF(AULAS_TESTE!$F:$F,$B40,AULAS_TESTE!T:T),"") -> 7.59375
A41: 0 | B41: Nome do Candidato | C41: emaildocandidato@email.com | D41: 11999999999 | E41: Português (Literatura) | F41: https://drive.google.com/open?id=1YOFALpN21inumXALoe4JuqXoA9Ta3i9Q | G41: https://drive.google.com/open?id=1yTXjTCIPdNGY16ahJAXwfOWRA8AsiJdX | H41: Minhas especializações. | J41: A1-A2 (básico) | L41: 8 | M41: 5.2568966 | N41: 8 | O41: 3.7458333 | P41: 0 | Q41: 2.0833333 | R41: 5.3333333 | S41: 3.5833333 | T41: 10 | U41: 6.3235294 | Y41: EMEFAF | AB41: Em minha concepção é possível utilizar algumas estratégias como: Planejamento, um dos principais pilares, pois a partir disso, viabiliza-se recursos que serão utilizados, a rotina em sala de aula. Saber gerir o tempo, com explicações objetivas e claras. | AD41: 8 | AE41: 12 | AF41: 6 | AG41: 8.7 | AH41: A aferição dar-se-á por meio de observação em sala de aula, trabalhos com apresentações, atividades avaliativas, e sempre um feedback a fim de analisar e refletir o processo de ensino- aprendizagem. | AJ41: 1 | AK41: 12 | AL41: 7 | AM41: 6.95 | AN41: Que o estudante possa refletir, aferir sobre seu aprendizado, que não seja mero ouvinte, que possa questionar e apresentar seu ponto de vista, que saiba utilizar roteiros, mapas mentais, incluindo a autogestão, que consigam gerir o tempo em que foi proporcionado para otimizar o aprendizado. | AP41: 13 | AQ41: 21 | AR41: 17 | AS41: 17.2 | AT41: Gosto de iniciar um conteúdo sempre ativando o conhecimento prévio do aluno, que ele faça associações. Segundo Howard Garder " O aprendizado é otimizado quando se associa o conteúdo em diferentes inteligências" Sendo assim, o aprendizado significativo ocorre quando o aluno consegue relacionar o novo com aquilo que já sabe. | AV41: 3 | AW41: 19 | AX41: 13 | AY41: 12.1 | BB41: 15 | BC41: 2 | BD41: 2 | BE41: 0 | BF41: 3 | BG41: 3 | BH41: 6 | BI41: 6 | BJ41: 6 | BK41: 0.5 | BL41: 4.5 | BM41: 10 | BN41: 9 | BO41: 1.5 | BP41: 5 | BQ41: 2.5 | BR41: 9 | BS41: 7.5 | BT41: 15 | BV41: =IFERROR(AVERAGEIF(AULAS_TESTE!$F:$F,$B41,AULAS_TESTE!G:G),"") -> 6.7941176 | BW41: =IFERROR(AVERAGEIF(AULAS_TESTE!$F:$F,$B41,AULAS_TESTE!H:H),"") -> 7.3529412 | BX41: =IFERROR(AVERAGEIF(AULAS_TESTE!$F:$F,$B41,AULAS_TESTE!I:I),"") -> 8.1764706 | BY41: =IFERROR(AVERAGEIF(AULAS_TESTE!$F:$F,$B41,AULAS_TESTE!J:J),"") -> 7.65625 | BZ41: =IFERROR(AVERAGEIF(AULAS_TESTE!$F:$F,$B41,AULAS_TESTE!K:K),"") -> 7.7333333 | CA41: =IFERROR(AVERAGEIF(AULAS_TESTE!$F:$F,$B41,AULAS_TESTE!L:L),"") -> 6.8076923 | CB41: =IFERROR(AVERAGEIF(AULAS_TESTE!$F:$F,$B41,AULAS_TESTE!M:M),"") -> 8.1176471 | CC41: =IFERROR(AVERAGEIF(AULAS_TESTE!$F:$F,$B41,AULAS_TESTE!N:N),"") -> 8.3125 | CD41: =IFERROR(AVERAGEIF(AULAS_TESTE!$F:$F,$B41,AULAS_TESTE!O:O),"") -> 7.5588235 | CE41: =IFERROR(AVERAGEIF(AULAS_TESTE!$F:$F,$B41,AULAS_TESTE!P:P),"") -> 7.6875 | CF41: =IFERROR(AVERAGEIF(AULAS_TESTE!$F:$F,$B41,AULAS_TESTE!Q:Q),"") -> 7.5 | CG41: =IFERROR(AVERAGEIF(AULAS_TESTE!$F:$F,$B41,AULAS_TESTE!R:R),"") -> 6.2727273 | CH41: =IFERROR(AVERAGEIF(AULAS_TESTE!$F:$F,$B41,AULAS_TESTE!S:S),"") -> 8.0625 | CI41: =IFERROR(AVERAGEIF(AULAS_TESTE!$F:$F,$B41,AULAS_TESTE!T:T),"") -> 7.59375
A42: 0 | B42: Nome do Candidato | C42: emaildocandidato@email.com | D42: 11999999999 | E42: Geografia | F42: https://drive.google.com/open?id=1UUMfMwULbNWMrTEnKFqLKMi9Mkwd_lYp | G42: https://drive.google.com/open?id=18rroTfHKI8jHZF4OoDkeFYVbU37YsFa9 | H42: O link para o padlet, onde contém minhas práticas pedagógicas. | J42: C1-C2 (avançado/fluente) | L42: 12 | M42: 5.8931034 | N42: 13 | O42: 4.075 | P42: 0 | Q42: 3.0833333 | R42: 4.8333333 | S42: 4.1666667 | T42: 16 | U42: 7.1764706 | V42: 6 | Y42: EMEFAF | AB42: Examino o conteúdo e preparo as aulas previamente conforme os objetivos a serem atingidos. Para tanto, faço um roteiro da introdução ou retomada de conteúdo, do desenvolvimento da aula - que varia de momento expositivos, de participação ativa dos alunos e de prática. Desta forma, é possível obter um aproveitamento do tempo de aula, embora, por vezes, o improviso seja necessário quando algo não acontece conforme o planejado. | AD42: 12 | AE42: 15 | AF42: 12 | AG42: 13.05 | AH42: Ao longo do processo, faço avaliações contínuas como perguntas orais ou quiz durante aulas expositivas, trabalhos em grupo de desenvolvimento na sala - assim consigo acompanhar as discussões e a realização das atividades - bem como pesquisas e seminários com preparação extra classe, também gosto de promover rodas de conversa onde consigo maior proximidade com os alunos. Quando noto alguma dificuldade, retomo o conceito de uma forma diferente. | AJ42: 11 | AK42: 12 | AL42: 14 | AM42: 12.4 | AN42: Prezo que o aluno sempre tenha o seu caderno em dia e organizado, bem como que acompanhe sempre o conteúdo e atividades desenvolvidas em apostila. Oriento que as anotações do caderno sejam revistas com uma certa frequência, pois é uma forma de fixar os principais conceitos que o ajudarão a aprender da melhor forma o previsto na sequência didática. Conscientizo o aluno que a elaboração de resumos e mapas mentais são de grande importância no processo e garantem a sua autonomia nos estudos. Verifico os cadernos e apostilas com regularidade para checar se essa organização é cumprida. | AP42: 3 | AQ42: 11 | AR42: 10 | AS42: 8.25 | AT42: Acredito que a formação continuada é essencial para o professor se manter atualizado, conhecer novas estratégias didáticas e recordar outras fundamentais. Em um cenário onde o jovem é cada vez mais dinâmico, é necessário que o professor busque formas de compreender como a mente do jovem aprende. Iniciei minha carreira docente no início de 2024, neste curto período, retomei os estudos com a segunda licenciatura em Letras e participei de formações como o curso de atualização "Multiplica" e o curso de extensão "Bem-estar e convivência - práticas para o desenvolvimento socioemocional". | AV42: 11 | AW42: 20 | AX42: 14 | AY42: 15.2 | BB42: 15 | BC42: 2 | BD42: 4 | BE42: 0 | BF42: 2 | BG42: 2 | BH42: 15 | BI42: 4 | BJ42: 6 | BK42: 1.5 | BL42: 4.5 | BM42: 10 | BN42: 12 | BO42: 2 | BP42: 5 | BQ42: 2.5 | BR42: 12 | BS42: 7.5 | BT42: 15 | BV42: =IFERROR(AVERAGEIF(AULAS_TESTE!$F:$F,$B42,AULAS_TESTE!G:G),"") -> 6.7941176 | BW42: =IFERROR(AVERAGEIF(AULAS_TESTE!$F:$F,$B42,AULAS_TESTE!H:H),"") -> 7.3529412 | BX42: =IFERROR(AVERAGEIF(AULAS_TESTE!$F:$F,$B42,AULAS_TESTE!I:I),"") -> 8.1764706 | BY42: =IFERROR(AVERAGEIF(AULAS_TESTE!$F:$F,$B42,AULAS_TESTE!J:J),"") -> 7.65625 | BZ42: =IFERROR(AVERAGEIF(AULAS_TESTE!$F:$F,$B42,AULAS_TESTE!K:K),"") -> 7.7333333 | CA42: =IFERROR(AVERAGEIF(AULAS_TESTE!$F:$F,$B42,AULAS_TESTE!L:L),"") -> 6.8076923 | CB42: =IFERROR(AVERAGEIF(AULAS_TESTE!$F:$F,$B42,AULAS_TESTE!M:M),"") -> 8.1176471 | CC42: =IFERROR(AVERAGEIF(AULAS_TESTE!$F:$F,$B42,AULAS_TESTE!N:N),"") -> 8.3125 | CD42: =IFERROR(AVERAGEIF(AULAS_TESTE!$F:$F,$B42,AULAS_TESTE!O:O),"") -> 7.5588235 | CE42: =IFERROR(AVERAGEIF(AULAS_TESTE!$F:$F,$B42,AULAS_TESTE!P:P),"") -> 7.6875 | CF42: =IFERROR(AVERAGEIF(AULAS_TESTE!$F:$F,$B42,AULAS_TESTE!Q:Q),"") -> 7.5 | CG42: =IFERROR(AVERAGEIF(AULAS_TESTE!$F:$F,$B42,AULAS_TESTE!R:R),"") -> 6.2727273 | CH42: =IFERROR(AVERAGEIF(AULAS_TESTE!$F:$F,$B42,AULAS_TESTE!S:S),"") -> 8.0625 | CI42: =IFERROR(AVERAGEIF(AULAS_TESTE!$F:$F,$B42,AULAS_TESTE!T:T),"") -> 7.59375
A43: 0 | B43: Nome do Candidato | C43: emaildocandidato@email.com | D43: 11999999999 | E43: Filosofia / Sociologia | F43: https://drive.google.com/open?id=1DOZVHRvxJPStet_McqumfxHooiJqILnO | G43: https://drive.google.com/open?id=1U448jndyCU2KTPP8ZO-qcF7zCWnCh_l9 | H43: Tempo em sala de aula (12 anos), ter cursado disciplinas do Mestrado em Filosofia como aluno especial (UFABC), desenvolvimento de projetos de relevância para a comunidade local ( Direitos Humanos, Consciência Negra ), número de graduações (3), cursos de pós-graduação lato-sensu. | J43: A1-A2 (básico) | L43: 16 | M43: 5.4086207 | N43: 19 | O43: 2.5708333 | P43: 0 | Q43: 2.25 | R43: 2.4166667 | S43: 3 | T43: 9 | U43: 7.4117647 | Y43: EMEFAF | AB43: Planejar a aula antecipadamente tendo como referência a característica da turma com mais de uma possibilidade de intervenção ou atividade. Disponibilizar antecipadamente a correção da lição de casa anterior e deixar programada a próxima lição de casa, ambas no google classroom. | AD43: 18 | AE43: 6 | AF43: 12 | AG43: 11.7 | AH43: Por meio das avaliações oficiais, quizzes, produção de textos e seminários. | AJ43: 4 | AK43: 6 | AL43: 5 | AM43: 5.05 | AN43: Leitura crítica de texto, análise sobre as fontes textuais e sua confiabilidade, capacidade de interpretar e elaborar boas argumentações, correlacionar um texto com os contextos político, econômico, social. | AP43: 3 | AQ43: 7 | AR43: 8 | AS43: 6.15 | AT43: Formação contínua, atualizações constantes em metodologias ativas, reuniões periódicas com a equipe da gestão para feedbacks sobre desenvolvimento individual e corporativo. | AV43: 2 | AW43: 10 | AX43: 11 | AY43: 7.95 | BB43: 15 | BC43: 4 | BD43: 2 | BE43: 0 | BF43: 2 | BG43: 4 | BH43: 12 | BI43: 2 | BJ43: 10 | BK43: 1 | BL43: 7.5 | BM43: 10 | BN43: 12 | BO43: 1.5 | BP43: 3 | BQ43: 2.5 | BR43: 15 | BS43: 7.5 | BT43: 15 | BV43: =IFERROR(AVERAGEIF(AULAS_TESTE!$F:$F,$B43,AULAS_TESTE!G:G),"") -> 6.7941176 | BW43: =IFERROR(AVERAGEIF(AULAS_TESTE!$F:$F,$B43,AULAS_TESTE!H:H),"") -> 7.3529412 | BX43: =IFERROR(AVERAGEIF(AULAS_TESTE!$F:$F,$B43,AULAS_TESTE!I:I),"") -> 8.1764706 | BY43: =IFERROR(AVERAGEIF(AULAS_TESTE!$F:$F,$B43,AULAS_TESTE!J:J),"") -> 7.65625 | BZ43: =IFERROR(AVERAGEIF(AULAS_TESTE!$F:$F,$B43,AULAS_TESTE!K:K),"") -> 7.7333333 | CA43: =IFERROR(AVERAGEIF(AULAS_TESTE!$F:$F,$B43,AULAS_TESTE!L:L),"") -> 6.8076923 | CB43: =IFERROR(AVERAGEIF(AULAS_TESTE!$F:$F,$B43,AULAS_TESTE!M:M),"") -> 8.1176471 | CC43: =IFERROR(AVERAGEIF(AULAS_TESTE!$F:$F,$B43,AULAS_TESTE!N:N),"") -> 8.3125 | CD43: =IFERROR(AVERAGEIF(AULAS_TESTE!$F:$F,$B43,AULAS_TESTE!O:O),"") -> 7.5588235 | CE43: =IFERROR(AVERAGEIF(AULAS_TESTE!$F:$F,$B43,AULAS_TESTE!P:P),"") -> 7.6875 | CF43: =IFERROR(AVERAGEIF(AULAS_TESTE!$F:$F,$B43,AULAS_TESTE!Q:Q),"") -> 7.5 | CG43: =IFERROR(AVERAGEIF(AULAS_TESTE!$F:$F,$B43,AULAS_TESTE!R:R),"") -> 6.2727273 | CH43: =IFERROR(AVERAGEIF(AULAS_TESTE!$F:$F,$B43,AULAS_TESTE!S:S),"") -> 8.0625 | CI43: =IFERROR(AVERAGEIF(AULAS_TESTE!$F:$F,$B43,AULAS_TESTE!T:T),"") -> 7.59375
A44: 0 | B44: Nome do Candidato | C44: emaildocandidato@email.com | D44: 11999999999 | E44: Biologia | F44: https://drive.google.com/open?id=1YNKHJLONopIixq2YPo7ys8rWBP92qak5 | G44: https://drive.google.com/open?id=17VRNZsDP_MUcRbUOqKbma-KRp6naAWDg | H44: Realização de estudo do Meio, ou visitas pedagógicas e atividades com parceria com projetos com universidades, conforme realizado: 1. BioBlitz: cooperação com a NatGeo, 2019 no Instituto Butantan com os estudantes da Escola de Aplicação da Faculdade de Educação da USP - https://www.ib.usp.br/mais-noticias/3012-projeto-bioblitz-ib-usp.html e https://www.youtube.com/watch?v=Db2W5bcUs9w e projetos de extensão universitária (ex: Projeto Ecossistemas Costeiros - https://www.ib.usp.br/mais-noticias/2400-projeto-ecossistemas-costeiros.html). Avaliadora FERBACE, desde 2023 | I44: Fiz parte do Movimento Bandeirante (Núcleo Bororos, São Paulo - SP) como membro juvenil e como voluntária. O Movimento Bandeirante foi fundamental para minha formação, sobretudo no que diz respeito ao trabalho em equipe, liderança, coletividade, cidadania e relação com o meio ambiente. Atuei como voluntária por mais de 5 anos (entre 2014 e 2020), coordenando um grupo de jovens entre 12 e 18 anos, trabalhando habilidades sociais entre elas: respeito, escuta, companheirismo, trabalho em equipe, cooperação, resolução de questões socioambientais e participação efetiva do jovem na sociedade. Destaco algumas de minhas habilidades: Formação continua, comprometimento, criatividade, organização e planejamento, além de parcerias com projetos inter e transdisciplinares | J44: B1-B2 (intermediário) | L44: 13 | M44: 6.1206897 | N44: 10 | O44: 4.625 | P44: 0 | Q44: 3.75 | R44: 5.25 | S44: 4.75 | T44: 22 | U44: 7.1764706 | V44: 7 | W44: 8.25 | X44: 7.8333333 | Y44: EMEFAF | AB44: Faço uso de estratégias diversificadas, para atingir o máximo de alunos, mesclo aulas expositivas, com atividades práticas, leituras e desafios em pequenos grupos, jogos, dinâmicas, resolução de exercícios, entre outras abordagens. Finalidade de deixar o aprendizado mais dinâmico e favorecer diferentes perfis de estudantes. | AD44: 4 | AE44: 8 | AF44: 6 | AG44: 6.1 | AH44: Para verificar o domínio de habilidade ou conceito, durante as aulas faço perguntas e espero a resposta, quando passo lição de casa, na hora de vistar a lição, verifico onde estão as maiores dúvidas e nas avalições formais. Ao longo das aulas, mantenho o diálogo e esclarecimentos de dúvidas sempre aberto, e faço aferição, com aplicabilidade do conceito ou habilidades trabalhadas, favorecendo o estabelecimento de relações feita pelos estudantes | AJ44: 7 | AK44: 10 | AL44: 9 | AM44: 8.75 | AN44: Procuro sempre orientar os estudantes e analisarem como eles estudam e eles próprios perceberem que técnicas funcionam melhor para eles, incentivar a metacognição, organizar e prestar atenção como é o estudo deles. Ofereço alguns subsídios, como elaboração de perguntas sobre determinado assunto e procurar responder no outro dia (revisão espaçada), oriento sobre a organização do espaço e tempo para estudo, incentivo que eles expliquem o que entenderam entre eles ou até para seus familiares e sempre oriento a compreendera explicação do professor, mas não necessariamente fazer cópia, fazer os registros com suas palavras. | AP44: 23 | AQ44: 23 | AR44: 21 | AS44: 22.3 | AT44: Estou sempre em busca de formação complementar, com participação em cursos, oficinas e workshops e procuro identificar o perfil da sala e trazer recursos e metodologias que melhor funciona com determinada turma. Tenho turmas que funcionam bem com atividade de sala de aula invertida, outras já aprendem melhor com jogos e assim vou intercalando para ofertar diferentes estratégias para os diferentes estudantes. Mantenho sempre nas aulas de ciências a prática de Ensino por Investigação e Alfabetização Científica (Batistoni e Sasseron, 2021; Sasseron e Carvalho, 2008) | AV44: 11 | AW44: 22 | AX44: 21 | AY44: 18.35 | BB44: 12 | BC44: 6 | BD44: 8 | BE44: 0 | BF44: 4 | BG44: 3 | BH44: 15 | BI44: 8 | BJ44: 6 | BK44: 1.5 | BL44: 6 | BM44: 8 | BN44: 3 | BO44: 2.5 | BP44: 5 | BQ44: 2.5 | BR44: 9 | BS44: 7.5 | BT44: 15 | BV44: =IFERROR(AVERAGEIF(AULAS_TESTE!$F:$F,$B44,AULAS_TESTE!G:G),"") -> 6.7941176 | BW44: =IFERROR(AVERAGEIF(AULAS_TESTE!$F:$F,$B44,AULAS_TESTE!H:H),"") -> 7.3529412 | BX44: =IFERROR(AVERAGEIF(AULAS_TESTE!$F:$F,$B44,AULAS_TESTE!I:I),"") -> 8.1764706 | BY44: =IFERROR(AVERAGEIF(AULAS_TESTE!$F:$F,$B44,AULAS_TESTE!J:J),"") -> 7.65625 | BZ44: =IFERROR(AVERAGEIF(AULAS_TESTE!$F:$F,$B44,AULAS_TESTE!K:K),"") -> 7.7333333 | CA44: =IFERROR(AVERAGEIF(AULAS_TESTE!$F:$F,$B44,AULAS_TESTE!L:L),"") -> 6.8076923 | CB44: =IFERROR(AVERAGEIF(AULAS_TESTE!$F:$F,$B44,AULAS_TESTE!M:M),"") -> 8.1176471 | CC44: =IFERROR(AVERAGEIF(AULAS_TESTE!$F:$F,$B44,AULAS_TESTE!N:N),"") -> 8.3125 | CD44: =IFERROR(AVERAGEIF(AULAS_TESTE!$F:$F,$B44,AULAS_TESTE!O:O),"") -> 7.5588235 | CE44: =IFERROR(AVERAGEIF(AULAS_TESTE!$F:$F,$B44,AULAS_TESTE!P:P),"") -> 7.6875 | CF44: =IFERROR(AVERAGEIF(AULAS_TESTE!$F:$F,$B44,AULAS_TESTE!Q:Q),"") -> 7.5 | CG44: =IFERROR(AVERAGEIF(AULAS_TESTE!$F:$F,$B44,AULAS_TESTE!R:R),"") -> 6.2727273 | CH44: =IFERROR(AVERAGEIF(AULAS_TESTE!$F:$F,$B44,AULAS_TESTE!S:S),"") -> 8.0625 | CI44: =IFERROR(AVERAGEIF(AULAS_TESTE!$F:$F,$B44,AULAS_TESTE!T:T),"") -> 7.59375
A45: 0 | B45: Nome do Candidato | C45: emaildocandidato@email.com | D45: 11999999999 | E45: História | F45: https://drive.google.com/open?id=1D0b7En1enkGtEXo6RTvVn50h8IVbUO48 | G45: https://drive.google.com/open?id=14JE1ZeuoyeBzjtAxzKBTMoHjWx31eZMe | H45: Conhecimento no pacote office. | J45: A1-A2 (básico) | L45: 49 | M45: 3.5551724 | N45: 44 | O45: 2.0083333 | P45: 0 | Q45: 1.25 | R45: 2.8333333 | S45: 1.8333333 | T45: 48 | U45: 4.6470588 | Y45: EMEFAF | AB45: Acredito que com um bom planejamento antes no início de cada aula, o conteúdo será explícito de maneira adequada dentro do tempo limite de cada aula. | AD45: 4 | AE45: 8 | AF45: 5 | AG45: 5.75 | AH45: No começo de cada aula devo levantar os conhecimentos prévios de meus alunos, fazendo perguntas sobre os conteúdos das aulas passadas para observar aquilo que foi assimilado e aquilo que os estudantes encontram certa dificuldade. É uma boa estratégia para observar o quanto a minha didática está sendo eficiente e também como eles estão recebendo as informações do professor. | AJ45: 8 | AK45: 12 | AL45: 7 | AM45: 9.05 | AN45: Acredito que o tempo dentro de sala de aula infelizmente é muito curto. Devo incentivar meus alunos a fazerem leituras um pouco mais aprofundadas sobre os diversos temas que abordamos dentro de sala de aula. Posso disponibilizar os PDF s de muito desses livros para todos tenham acesso. | AP45: 1 | AQ45: 7 | AR45: 6 | AS45: 4.85 | AT45: Devemos usar cada vez mais o uso das tecnologias em sala de sala. Acredito que posso utilizar muito os canais do YouTube, gameplay de jogos e filmes disponíveis nos catálogos de streamings para sair um pouco das aulas monótonas. Após isso, podemos fazer rodas de conversa sobre aquilo que assistimos, fazer redações e diversões outras atividades ligadas ao uso dessas tecnologias. | AV45: 2 | AW45: 7 | AX45: 4 | AY45: 4.45 | BB45: 6 | BC45: 10 | BD45: 10 | BE45: 0 | BF45: 5 | BG45: 3 | BH45: 3 | BI45: 10 | BJ45: 2 | BK45: 2.5 | BL45: 3 | BM45: 2 | BN45: 9 | BO45: 2.5 | BP45: 3 | BQ45: 0.5 | BR45: 3 | BS45: 1.5 | BT45: 3 | BV45: =IFERROR(AVERAGEIF(AULAS_TESTE!$F:$F,$B45,AULAS_TESTE!G:G),"") -> 6.7941176 | BW45: =IFERROR(AVERAGEIF(AULAS_TESTE!$F:$F,$B45,AULAS_TESTE!H:H),"") -> 7.3529412 | BX45: =IFERROR(AVERAGEIF(AULAS_TESTE!$F:$F,$B45,AULAS_TESTE!I:I),"") -> 8.1764706 | BY45: =IFERROR(AVERAGEIF(AULAS_TESTE!$F:$F,$B45,AULAS_TESTE!J:J),"") -> 7.65625 | BZ45: =IFERROR(AVERAGEIF(AULAS_TESTE!$F:$F,$B45,AULAS_TESTE!K:K),"") -> 7.7333333 | CA45: =IFERROR(AVERAGEIF(AULAS_TESTE!$F:$F,$B45,AULAS_TESTE!L:L),"") -> 6.8076923 | CB45: =IFERROR(AVERAGEIF(AULAS_TESTE!$F:$F,$B45,AULAS_TESTE!M:M),"") -> 8.1176471 | CC45: =IFERROR(AVERAGEIF(AULAS_TESTE!$F:$F,$B45,AULAS_TESTE!N:N),"") -> 8.3125 | CD45: =IFERROR(AVERAGEIF(AULAS_TESTE!$F:$F,$B45,AULAS_TESTE!O:O),"") -> 7.5588235 | CE45: =IFERROR(AVERAGEIF(AULAS_TESTE!$F:$F,$B45,AULAS_TESTE!P:P),"") -> 7.6875 | CF45: =IFERROR(AVERAGEIF(AULAS_TESTE!$F:$F,$B45,AULAS_TESTE!Q:Q),"") -> 7.5 | CG45: =IFERROR(AVERAGEIF(AULAS_TESTE!$F:$F,$B45,AULAS_TESTE!R:R),"") -> 6.2727273 | CH45: =IFERROR(AVERAGEIF(AULAS_TESTE!$F:$F,$B45,AULAS_TESTE!S:S),"") -> 8.0625 | CI45: =IFERROR(AVERAGEIF(AULAS_TESTE!$F:$F,$B45,AULAS_TESTE!T:T),"") -> 7.59375
A46: 0 | B46: Nome do Candidato | C46: emaildocandidato@email.com | D46: 11999999999 | E46: Português (Produção e Interpretação de Texto) | F46: https://drive.google.com/open?id=1Rbv8blDhxnLAcbOKCArZvbgqwi1579SJ | G46: https://drive.google.com/open?id=1Jw0eoWqCsYoT2tz2zHVhkOqY8TWpDLSy | H46: Experiência com EJA (educação de jovens e adultos). Experiência em todas as fases. Educação infantil, ensino fundamental (séries e iniciais e finais) e ensino médio. Experiência com ensino bilíngue. | I46: Disponibilidade imediata. | J46: B1-B2 (intermediário) | L46: 23 | M46: 5.7534483 | N46: 28 | O46: 2.7791667 | P46: 0 | Q46: 2.1666667 | R46: 3.4166667 | S46: 2.6666667 | T46: 12 | U46: 7.8529412 | V46: 4 | Y46: EMEFAF | AB46: Planejamento antecipado das aulas, rotinas claras, metodologias ativas, priorizar conteúdos essenciais e avaliações diagnósticas. | AD46: 11 | AE46: 8 | AF46: 10 | AG46: 9.6 | AH46: Realizando acompanhamento contínuo sobre o desenvolvimento individual de cada aluno, através de observações diárias, trabalhos em grupos, realizações de atividades e exercícios, além de autoavaliações e provas parciais. | AJ46: 6 | AK46: 12 | AL46: 6 | AM46: 8.1 | AN46: Através da organização por cronogramas de estudo baseados em metodologias ativas tais como mapas mentais, revisões, resumos, anotações. Sempre com acompanhamento e orientações diárias. | AP46: 6 | AQ46: 14 | AR46: 10 | AS46: 10.2 | AT46: Formações continuadas, trocas com colegas, grupos de estudos. Além de ficar ligada nas tendencias pedagógicas por meio de estudos atualizados. | AV46: 3 | AW46: 7 | AX46: 6 | AY46: 5.45 | BB46: 15 | BC46: 6 | BD46: 6 | BE46: 0 | BF46: 4 | BG46: 2 | BH46: 15 | BI46: 8 | BJ46: 6 | BK46: 1 | BL46: 7.5 | BM46: 10 | BN46: 6 | BO46: 2 | BP46: 5 | BQ46: 2.5 | BR46: 15 | BS46: 7.5 | BT46: 15 | BV46: =IFERROR(AVERAGEIF(AULAS_TESTE!$F:$F,$B46,AULAS_TESTE!G:G),"") -> 6.7941176 | BW46: =IFERROR(AVERAGEIF(AULAS_TESTE!$F:$F,$B46,AULAS_TESTE!H:H),"") -> 7.3529412 | BX46: =IFERROR(AVERAGEIF(AULAS_TESTE!$F:$F,$B46,AULAS_TESTE!I:I),"") -> 8.1764706 | BY46: =IFERROR(AVERAGEIF(AULAS_TESTE!$F:$F,$B46,AULAS_TESTE!J:J),"") -> 7.65625 | BZ46: =IFERROR(AVERAGEIF(AULAS_TESTE!$F:$F,$B46,AULAS_TESTE!K:K),"") -> 7.7333333 | CA46: =IFERROR(AVERAGEIF(AULAS_TESTE!$F:$F,$B46,AULAS_TESTE!L:L),"") -> 6.8076923 | CB46: =IFERROR(AVERAGEIF(AULAS_TESTE!$F:$F,$B46,AULAS_TESTE!M:M),"") -> 8.1176471 | CC46: =IFERROR(AVERAGEIF(AULAS_TESTE!$F:$F,$B46,AULAS_TESTE!N:N),"") -> 8.3125 | CD46: =IFERROR(AVERAGEIF(AULAS_TESTE!$F:$F,$B46,AULAS_TESTE!O:O),"") -> 7.5588235 | CE46: =IFERROR(AVERAGEIF(AULAS_TESTE!$F:$F,$B46,AULAS_TESTE!P:P),"") -> 7.6875 | CF46: =IFERROR(AVERAGEIF(AULAS_TESTE!$F:$F,$B46,AULAS_TESTE!Q:Q),"") -> 7.5 | CG46: =IFERROR(AVERAGEIF(AULAS_TESTE!$F:$F,$B46,AULAS_TESTE!R:R),"") -> 6.2727273 | CH46: =IFERROR(AVERAGEIF(AULAS_TESTE!$F:$F,$B46,AULAS_TESTE!S:S),"") -> 8.0625 | CI46: =IFERROR(AVERAGEIF(AULAS_TESTE!$F:$F,$B46,AULAS_TESTE!T:T),"") -> 7.59375
A47: 0 | B47: Nome do Candidato | C47: emaildocandidato@email.com | D47: 11999999999 | E47: Filosofia / Sociologia | F47: https://drive.google.com/open?id=1QFqD_xXGzEZYCqbF9hPYeufl--zgDakD | G47: https://drive.google.com/open?id=1wM6z3rTr3IURCmUoVxH_Lf1iszTuOqRM | H47: Destaco a palestra "Ancestralidade e política na África contemporânea " ministrado no dia 12/08/2025, no Centro de Formação e Pesquisa do Sesc SP ( CPF /Sesc), artigos publicados em revistas científicas:DJIKOLDIGAM, MBAIDIGUIM. Hobbes, ou a invenção do soberano representante. INTUITIO (PORTO ALEGRE), v. 17, p. 14, 2024. 2. DJIKOLDIGAM, MBAIDIGUIM. Hobbes, ou a religião como questão política. INSTAURATIO MAGNA, v. 4, p. 22-47, 2024. 3. DJIKOLDIGAM, MBAIDIGUIM. Hobbes e a democracia moderna: regra da maioria e representação política. CADERNOS DE ÉTICA E FILOSOFIA POLÍTICA (USP), v. 40, p. 98-114, 2022. 4. DJIKOLDIGAM, MBAIDIGUIM. Representação Política em Thomas HobbesPolitical Representation in Thomas Hobbesrepresentación política en Thomas Hobbes. REVISTA DE FILOSOFIA MODERNA E CONTEMPORÂNEA, v. 10, p. 239-253, 2022. Membro do JÚRI da I OLIMPÍADA NACIONAL DE FILOSOFIA. MEMBRO DO JÚRI. 2024. | J47: A1-A2 (básico) | L47: 14 | M47: 5.4896552 | N47: 14 | O47: 3.5583333 | P47: 0 | Q47: 2.9166667 | R47: 4.25 | S47: 3.4166667 | T47: 17 | U47: 6.8529412 | V47: 7 | W47: 9 | X47: 8.3333333 | Y47: EMEFAF | AB47: Para otimizar o uso de tempo, eu prezo pelo planejamento das aulas; uso de recursos tecnológicos como slides, plataformas; ter uma rotina bem definida para as aulas com rituais de início e fim e combinados com a turma; foco em estratégias de ensino que privilegia participação dos alunos | AD47: 15 | AE47: 11 | AF47: 12 | AG47: 12.55 | AH47: Minhas estratégias de aferição consistem em mini-avaliações rápidas, que são perguntas orais ou escritas feitas no final de cada aula; seminários ou debates em grupos sobre temas introduzidos em aula; exigência de entrega de um resumo de aula cada unidade estudada. | AJ47: 10 | AK47: 11 | AL47: 15 | AM47: 12.1 | AN47: Organizar de tempo, fichamento de obras lidas, anotações e resumo de cada aula, releitura desses resumos antes do início de cada aula. | AP47: 3 | AQ47: 15 | AR47: 6 | AS47: 8.25 | AT47: Para mim, é importante o docente fazer sempre uma autoavaliação e reflexão sobre a sua prática docente ( Cf. Schön). Além disso, prezo também pela formação continuada. A formação para carreira docente não se finaliza na formatura. Ao contrário, somos sempre desafiados no dia dia no exercício da profissão. O mundo educativativo é muito dinâmico. Precisamos sempre estar atualizado. Como defende Paulo Freire, é necessário o professor estar sempre aprendendo, renovando a escuta e dialogando com a realidade dos estudantes. | AV47: 7 | AW47: 14 | AX47: 8 | AY47: 9.8 | BB47: 15 | BC47: 2 | BD47: 2 | BE47: 0 | BF47: 3 | BG47: 2 | BH47: 15 | BI47: 6 | BJ47: 10 | BK47: 0.5 | BL47: 7.5 | BM47: 6 | BN47: 15 | BO47: 1 | BP47: 5 | BQ47: 2.5 | BR47: 3 | BS47: 6 | BT47: 15 | BV47: =IFERROR(AVERAGEIF(AULAS_TESTE!$F:$F,$B47,AULAS_TESTE!G:G),"") -> 6.7941176 | BW47: =IFERROR(AVERAGEIF(AULAS_TESTE!$F:$F,$B47,AULAS_TESTE!H:H),"") -> 7.3529412 | BX47: =IFERROR(AVERAGEIF(AULAS_TESTE!$F:$F,$B47,AULAS_TESTE!I:I),"") -> 8.1764706 | BY47: =IFERROR(AVERAGEIF(AULAS_TESTE!$F:$F,$B47,AULAS_TESTE!J:J),"") -> 7.65625 | BZ47: =IFERROR(AVERAGEIF(AULAS_TESTE!$F:$F,$B47,AULAS_TESTE!K:K),"") -> 7.7333333 | CA47: =IFERROR(AVERAGEIF(AULAS_TESTE!$F:$F,$B47,AULAS_TESTE!L:L),"") -> 6.8076923 | CB47: =IFERROR(AVERAGEIF(AULAS_TESTE!$F:$F,$B47,AULAS_TESTE!M:M),"") -> 8.1176471 | CC47: =IFERROR(AVERAGEIF(AULAS_TESTE!$F:$F,$B47,AULAS_TESTE!N:N),"") -> 8.3125 | CD47: =IFERROR(AVERAGEIF(AULAS_TESTE!$F:$F,$B47,AULAS_TESTE!O:O),"") -> 7.5588235 | CE47: =IFERROR(AVERAGEIF(AULAS_TESTE!$F:$F,$B47,AULAS_TESTE!P:P),"") -> 7.6875 | CF47: =IFERROR(AVERAGEIF(AULAS_TESTE!$F:$F,$B47,AULAS_TESTE!Q:Q),"") -> 7.5 | CG47: =IFERROR(AVERAGEIF(AULAS_TESTE!$F:$F,$B47,AULAS_TESTE!R:R),"") -> 6.2727273 | CH47: =IFERROR(AVERAGEIF(AULAS_TESTE!$F:$F,$B47,AULAS_TESTE!S:S),"") -> 8.0625 | CI47: =IFERROR(AVERAGEIF(AULAS_TESTE!$F:$F,$B47,AULAS_TESTE!T:T),"") -> 7.59375
A48: 0 | B48: Nome do Candidato | C48: emaildocandidato@email.com | D48: 11999999999 | E48: Biologia | F48: https://drive.google.com/open?id=1Hf0NIbmnYwvRe1UqiOB24snuebQjHZ1E | G48: https://drive.google.com/open?id=1Xh57uU60VI-9W_DISNb-177O6EwRZxbT | H48: Experiência em palestras em etecs e escolas públicas de Sp, fui professor voluntário do Estado, e fui o professor preparador das olimpíada brasileira de biologia em 2024 chegando até a ultima fase. | J48: A1-A2 (básico) | L48: 17 | M48: 6.0068966 | N48: 29 | O48: 2.6833333 | P48: 0 | Q48: 1.1666667 | R48: 4.1666667 | S48: 2.5 | T48: 2 | U48: 8.3529412 | V48: 5.5 | Y48: EMEFAF | AB48: Aulas objetivas e dinâmicas visando a compreensão de conceitos aplicados de maneira prática | AD48: 0 | AE48: 12 | AF48: 6 | AG48: 6.3 | AH48: - Atividades de perguntas e respostas - Modelo de jogo (gamificação), lista de exercícios em sala de aula. | AJ48: 4 | AK48: 5 | AL48: 6 | AM48: 5.05 | AN48: - Organização em relação ao caderno, resumos pontuais sobre a matéria e exercícios para revisar o conteúdo. | AP48: 7 | AQ48: 11 | AR48: 6 | AS48: 8.05 | AT48: Estabelecimento de regras e combinados facilitando o dia a dia, aprendizagem ligada a dopamina (prazer em aprender tornando a aula dinâmica e leve), aulas práticas para visualização do conteúdo visto em sala de aula. | AV48: 3 | AW48: 22 | AX48: 12 | AY48: 12.8 | BB48: 15 | BC48: 6 | BD48: 8 | BE48: 0 | BF48: 5 | BG48: 5 | BH48: 15 | BI48: 10 | BJ48: 6 | BK48: 2 | BL48: 7.5 | BM48: 10 | BN48: 6 | BO48: 1.5 | BP48: 5 | BQ48: 2.5 | BR48: 15 | BS48: 7.5 | BT48: 15 | BV48: =IFERROR(AVERAGEIF(AULAS_TESTE!$F:$F,$B48,AULAS_TESTE!G:G),"") -> 6.7941176 | BW48: =IFERROR(AVERAGEIF(AULAS_TESTE!$F:$F,$B48,AULAS_TESTE!H:H),"") -> 7.3529412 | BX48: =IFERROR(AVERAGEIF(AULAS_TESTE!$F:$F,$B48,AULAS_TESTE!I:I),"") -> 8.1764706 | BY48: =IFERROR(AVERAGEIF(AULAS_TESTE!$F:$F,$B48,AULAS_TESTE!J:J),"") -> 7.65625 | BZ48: =IFERROR(AVERAGEIF(AULAS_TESTE!$F:$F,$B48,AULAS_TESTE!K:K),"") -> 7.7333333 | CA48: =IFERROR(AVERAGEIF(AULAS_TESTE!$F:$F,$B48,AULAS_TESTE!L:L),"") -> 6.8076923 | CB48: =IFERROR(AVERAGEIF(AULAS_TESTE!$F:$F,$B48,AULAS_TESTE!M:M),"") -> 8.1176471 | CC48: =IFERROR(AVERAGEIF(AULAS_TESTE!$F:$F,$B48,AULAS_TESTE!N:N),"") -> 8.3125 | CD48: =IFERROR(AVERAGEIF(AULAS_TESTE!$F:$F,$B48,AULAS_TESTE!O:O),"") -> 7.5588235 | CE48: =IFERROR(AVERAGEIF(AULAS_TESTE!$F:$F,$B48,AULAS_TESTE!P:P),"") -> 7.6875 | CF48: =IFERROR(AVERAGEIF(AULAS_TESTE!$F:$F,$B48,AULAS_TESTE!Q:Q),"") -> 7.5 | CG48: =IFERROR(AVERAGEIF(AULAS_TESTE!$F:$F,$B48,AULAS_TESTE!R:R),"") -> 6.2727273 | CH48: =IFERROR(AVERAGEIF(AULAS_TESTE!$F:$F,$B48,AULAS_TESTE!S:S),"") -> 8.0625 | CI48: =IFERROR(AVERAGEIF(AULAS_TESTE!$F:$F,$B48,AULAS_TESTE!T:T),"") -> 7.59375
A49: 0 | B49: Nome do Candidato | C49: emaildocandidato@email.com | D49: 11999999999 | E49: Geografia | F49: https://drive.google.com/open?id=1xKyo5Ou7sV1zdBemnshpbiCGcuD3teTf | G49: https://drive.google.com/open?id=1H31v04Lh-lB4dSj_h6JRApyXaUQ-PNqI | H49: Trabalho Voluntário | I49: Voltar a fazer parte dessa equipe e escola incrível será uma grande realização...! | J49: B1-B2 (intermediário) | L49: 16 | M49: 5.7775862 | N49: 19 | O49: 3.1708333 | P49: 0 | Q49: 3.0833333 | R49: 3.0833333 | S49: 3.3333333 | T49: 5 | U49: 7.6176471 | V49: 2 | Y49: EMEFAF | AB49: Utilizo planejamento e organização, rotina bem estabelecida, metodologias ativas e monitoramento e flexibilidade são essenciais pra mim. | AD49: 10 | AE49: 8 | AF49: 8 | AG49: 8.6 | AH49: Através da observação, participação e métodos de aprendizagem. Avaliações (como perguntas rápidas, mapas mentais), observação de estratégia de feedback (analisar como os estudantes agem durante as atividades). | AJ49: 13 | AK49: 5 | AL49: 8 | AM49: 8.45 | AN49: Planejamento é fundamental, revisão durante a aula, técnica de Pomodoro. | AP49: 5 | AQ49: 13 | AR49: 6 | AS49: 8.15 | AT49: Paulo Freire, Piaget são importantes pra mim...Feedback dos alunos, auto avaliação, atualização pedagógica, testar metodologias ativas, troca com outros professores, tecnologia educacional | AV49: 9 | AW49: 11 | AX49: 18 | AY49: 12.85 | BB49: 15 | BC49: 4 | BD49: 4 | BE49: 0 | BF49: 1 | BG49: 5 | BH49: 15 | BI49: 4 | BJ49: 8 | BK49: 1 | BL49: 7.5 | BM49: 10 | BN49: 12 | BO49: 1 | BP49: 5 | BQ49: 2.5 | BR49: 12 | BS49: 7.5 | BT49: 15 | BV49: =IFERROR(AVERAGEIF(AULAS_TESTE!$F:$F,$B49,AULAS_TESTE!G:G),"") -> 6.7941176 | BW49: =IFERROR(AVERAGEIF(AULAS_TESTE!$F:$F,$B49,AULAS_TESTE!H:H),"") -> 7.3529412 | BX49: =IFERROR(AVERAGEIF(AULAS_TESTE!$F:$F,$B49,AULAS_TESTE!I:I),"") -> 8.1764706 | BY49: =IFERROR(AVERAGEIF(AULAS_TESTE!$F:$F,$B49,AULAS_TESTE!J:J),"") -> 7.65625 | BZ49: =IFERROR(AVERAGEIF(AULAS_TESTE!$F:$F,$B49,AULAS_TESTE!K:K),"") -> 7.7333333 | CA49: =IFERROR(AVERAGEIF(AULAS_TESTE!$F:$F,$B49,AULAS_TESTE!L:L),"") -> 6.8076923 | CB49: =IFERROR(AVERAGEIF(AULAS_TESTE!$F:$F,$B49,AULAS_TESTE!M:M),"") -> 8.1176471 | CC49: =IFERROR(AVERAGEIF(AULAS_TESTE!$F:$F,$B49,AULAS_TESTE!N:N),"") -> 8.3125 | CD49: =IFERROR(AVERAGEIF(AULAS_TESTE!$F:$F,$B49,AULAS_TESTE!O:O),"") -> 7.5588235 | CE49: =IFERROR(AVERAGEIF(AULAS_TESTE!$F:$F,$B49,AULAS_TESTE!P:P),"") -> 7.6875 | CF49: =IFERROR(AVERAGEIF(AULAS_TESTE!$F:$F,$B49,AULAS_TESTE!Q:Q),"") -> 7.5 | CG49: =IFERROR(AVERAGEIF(AULAS_TESTE!$F:$F,$B49,AULAS_TESTE!R:R),"") -> 6.2727273 | CH49: =IFERROR(AVERAGEIF(AULAS_TESTE!$F:$F,$B49,AULAS_TESTE!S:S),"") -> 8.0625 | CI49: =IFERROR(AVERAGEIF(AULAS_TESTE!$F:$F,$B49,AULAS_TESTE!T:T),"") -> 7.59375
A50: 0 | B50: Nome do Candidato | C50: emaildocandidato@email.com | D50: 11999999999 | E50: Geografia | F50: https://drive.google.com/open?id=173jI4G7jnnV8NXqB5_RS2uLULFuF_iIo | G50: https://drive.google.com/open?id=1e-pC-IBIKKSQePbSFyZaLnEa7y9hQG21 | H50: Meu diferencial é ter experiência em escolas e métodos de ensino diferente, assim com já trabalhei com todas as séries do ensino básico. Estou concluindo minha pós-graduação e tenho uma formação sólida. Além disso, tenho experiência com materiais didáticos, o que me dá a possibilidade de trabalhar com mais diferentes sistemas de ensino se necessário. | I50: - | J50: B1-B2 (intermediário) | L50: 19 | M50: 5.3931034 | N50: 16 | O50: 3.45 | P50: 0 | Q50: 2.75 | R50: 4.4166667 | S50: 3.0833333 | T50: 22 | U50: 6.7647059 | V50: 9 | W50: 8.15 | X50: 8.4333333 | Y50: EMEFAF | AB50: Minha estratégia principal é prepara a aula com antecedência, calculando um tempo eficaz de explicação, buscando ilustrar o conteúdo e abrindo espaço para possíveis questões no final da aula. Além disso, busco manter a ordem e a disciplina da sala de aula, sempre tendo empatia e noção do público que eu estou lidando. | AD50: 10 | AE50: 12 | AF50: 9 | AG50: 10.35 | AH50: A aferição primária vai ser durante a aula, conversando, interagindo e realizando questões aos alunos durante as explicações. Nesse momento, busco um olhar atento a todos os alunos da sala, afim de identificar aqueles que estão com dúvida, vergonha de interagir ou com qualquer dificuldade relativa ao processo de aprendizagem. Outra forma de verificar a aprendizagem vai ser por meio da realização de exercícios ou trabalhos escolares. Por fim, temos a avaliação da disciplina, onde após um processo de aprendizagem, o aluno mostra que compreendeu determinado assunto. | AJ50: 4 | AK50: 10 | AL50: 8 | AM50: 7.5 | AN50: Como leciono geografia, acredito que os alunos devem dominar práticas como elaboração de resumo e fichamentos dos temas propostos, para isso, eu utilizo muito a lousa e passo muito conteúdo escrito. Outra coisa que prezo, é a capacidade de conceber a espacialização dos fenômenos, então para mim é crucial a elaboração e a sobreposição de mapas como meio de compreensão do conteúdo. Por fim, acho que buscar em exemplos concretos do contidiano, das mídias e do plano cultural é essencial para que eles encontrem o que está sendo estudado na vida real. | AP50: 16 | AQ50: 16 | AR50: 11 | AS50: 14.25 | AT50: Para mim, práticas constantes de estudo de técnicas atuais, como gameficação, metodologias ativas, em conjunto do ensino tradicional, são mecanismos que busco aperfeiçoar para melhorar minhas habilidades como docente. | AV50: 3 | AW50: 15 | AX50: 9 | AY50: 9.3 | BB50: 12 | BC50: 4 | BD50: 4 | BE50: 0 | BF50: 2 | BG50: 4 | BH50: 15 | BI50: 2 | BJ50: 10 | BK50: 0.5 | BL50: 7.5 | BM50: 8 | BN50: 6 | BO50: 2.5 | BP50: 5 | BQ50: 2.5 | BR50: 9 | BS50: 6 | BT50: 15 | BV50: =IFERROR(AVERAGEIF(AULAS_TESTE!$F:$F,$B50,AULAS_TESTE!G:G),"") -> 6.7941176 | BW50: =IFERROR(AVERAGEIF(AULAS_TESTE!$F:$F,$B50,AULAS_TESTE!H:H),"") -> 7.3529412 | BX50: =IFERROR(AVERAGEIF(AULAS_TESTE!$F:$F,$B50,AULAS_TESTE!I:I),"") -> 8.1764706 | BY50: =IFERROR(AVERAGEIF(AULAS_TESTE!$F:$F,$B50,AULAS_TESTE!J:J),"") -> 7.65625 | BZ50: =IFERROR(AVERAGEIF(AULAS_TESTE!$F:$F,$B50,AULAS_TESTE!K:K),"") -> 7.7333333 | CA50: =IFERROR(AVERAGEIF(AULAS_TESTE!$F:$F,$B50,AULAS_TESTE!L:L),"") -> 6.8076923 | CB50: =IFERROR(AVERAGEIF(AULAS_TESTE!$F:$F,$B50,AULAS_TESTE!M:M),"") -> 8.1176471 | CC50: =IFERROR(AVERAGEIF(AULAS_TESTE!$F:$F,$B50,AULAS_TESTE!N:N),"") -> 8.3125 | CD50: =IFERROR(AVERAGEIF(AULAS_TESTE!$F:$F,$B50,AULAS_TESTE!O:O),"") -> 7.5588235 | CE50: =IFERROR(AVERAGEIF(AULAS_TESTE!$F:$F,$B50,AULAS_TESTE!P:P),"") -> 7.6875 | CF50: =IFERROR(AVERAGEIF(AULAS_TESTE!$F:$F,$B50,AULAS_TESTE!Q:Q),"") -> 7.5 | CG50: =IFERROR(AVERAGEIF(AULAS_TESTE!$F:$F,$B50,AULAS_TESTE!R:R),"") -> 6.2727273 | CH50: =IFERROR(AVERAGEIF(AULAS_TESTE!$F:$F,$B50,AULAS_TESTE!S:S),"") -> 8.0625 | CI50: =IFERROR(AVERAGEIF(AULAS_TESTE!$F:$F,$B50,AULAS_TESTE!T:T),"") -> 7.59375
A51: 0 | B51: Nome do Candidato | C51: emaildocandidato@email.com | D51: 11999999999 | E51: História | F51: https://drive.google.com/open?id=1aPywMbWXb5OKObcU_JSfhD9CZpcHWwQ1 | G51: https://drive.google.com/open?id=18_BEJt75IOqt4W5QEqq80OGtnhkusMHW | H51: Fui um dos responsáveis por planejar e dar vida a um Podcast e escola especializada em Eletromobilidade. Um outro orgulho profissional é quase sempre ser escolhido pelo alunos como paraninfo ou professor homenageado nas festas de formatura. | J51: A1-A2 (básico) | L51: 29 | M51: 5.3948276 | N51: 27 | O51: 3.0791667 | P51: 0 | Q51: 2 | R51: 4.25 | S51: 2.8333333 | T51: 25 | U51: 7.0294118 | V51: 6 | Y51: EMEFAF | AB51: Aulas bem preparadas, objetividade, prioridade nos assuntos e temas mais importantes. | AD51: 0 | AE51: 8 | AF51: 6 | AG51: 4.9 | AH51: Além das ferramentas avaliativas tradicionais como prova, trabalhos, gosto muito de utilizar atividades avaliativas diversificadas como games (Quizzes), jogos, dinâmicas e atividades com foco na resolução de problemas concretos da realidade. | AJ51: 6 | AK51: 15 | AL51: 9 | AM51: 10.2 | AN51: Incentivo muito a confecção de mapas mentais dos temas estudados. É uma ferramenta pedagógica poderosa na assimilação de conteúdos, principalmente de história. Organizar linhas do tempo também é outra estratégia de estudo muito eficaz, especialmente para temas como Revolução Francesa, Roma, conteúdos cheios de datas, períodos distintos, com muitos personagens e acontecimentos, para ficar em poucos exemplos. Caderno de dúvidas, outro instrumento importante. Registrar e anotar possíveis dúvidas é mais que fundamental: conteúdo visto, precisa significar conteúdo aprendido. | AP51: 13 | AQ51: 17 | AR51: 11 | AS51: 13.7 | AT51: Educação é tradição, mas também movimento. Autores como Zabala, Carla Bassanezi, Marcos Napolitano, Circe Bittencourt, Leandro Karnal, Selva Guimarães Fonseca, Cortella - , entre outros - produziram vários trabalhos nesse sentido. Despertar o interesse dos alunos pelo conhecimento vai muito além de mostrar um slide, copiar resumos, aulas expositivas. Requer engajar alunos cada vez mais conectados as telas, poder de concentração reduzido e foco prejudicado. Sem o entendimento do aluno como protagonista do ensino aprendizagem, as estratégias de ensinos tradicionais tendem ao fracasso. | AV51: 5 | AW51: 11 | AX51: 8 | AY51: 8.15 | BB51: 15 | BC51: 2 | BD51: 2 | BE51: 0 | BF51: 1 | BG51: 4 | BH51: 15 | BI51: 2 | BJ51: 10 | BK51: 0.5 | BL51: 7.5 | BM51: 10 | BN51: 3 | BO51: 2.5 | BP51: 5 | BQ51: 2.5 | BR51: 15 | BS51: 7.5 | BT51: 15 | BV51: =IFERROR(AVERAGEIF(AULAS_TESTE!$F:$F,$B51,AULAS_TESTE!G:G),"") -> 6.7941176 | BW51: =IFERROR(AVERAGEIF(AULAS_TESTE!$F:$F,$B51,AULAS_TESTE!H:H),"") -> 7.3529412 | BX51: =IFERROR(AVERAGEIF(AULAS_TESTE!$F:$F,$B51,AULAS_TESTE!I:I),"") -> 8.1764706 | BY51: =IFERROR(AVERAGEIF(AULAS_TESTE!$F:$F,$B51,AULAS_TESTE!J:J),"") -> 7.65625 | BZ51: =IFERROR(AVERAGEIF(AULAS_TESTE!$F:$F,$B51,AULAS_TESTE!K:K),"") -> 7.7333333 | CA51: =IFERROR(AVERAGEIF(AULAS_TESTE!$F:$F,$B51,AULAS_TESTE!L:L),"") -> 6.8076923 | CB51: =IFERROR(AVERAGEIF(AULAS_TESTE!$F:$F,$B51,AULAS_TESTE!M:M),"") -> 8.1176471 | CC51: =IFERROR(AVERAGEIF(AULAS_TESTE!$F:$F,$B51,AULAS_TESTE!N:N),"") -> 8.3125 | CD51: =IFERROR(AVERAGEIF(AULAS_TESTE!$F:$F,$B51,AULAS_TESTE!O:O),"") -> 7.5588235 | CE51: =IFERROR(AVERAGEIF(AULAS_TESTE!$F:$F,$B51,AULAS_TESTE!P:P),"") -> 7.6875 | CF51: =IFERROR(AVERAGEIF(AULAS_TESTE!$F:$F,$B51,AULAS_TESTE!Q:Q),"") -> 7.5 | CG51: =IFERROR(AVERAGEIF(AULAS_TESTE!$F:$F,$B51,AULAS_TESTE!R:R),"") -> 6.2727273 | CH51: =IFERROR(AVERAGEIF(AULAS_TESTE!$F:$F,$B51,AULAS_TESTE!S:S),"") -> 8.0625 | CI51: =IFERROR(AVERAGEIF(AULAS_TESTE!$F:$F,$B51,AULAS_TESTE!T:T),"") -> 7.59375
A52: 0 | B52: Nome do Candidato | C52: emaildocandidato@email.com | D52: 11999999999 | E52: História | F52: https://drive.google.com/open?id=1t_55Mjr7pVyFoI5v5HdxoXuYOYCK6WJL | G52: https://drive.google.com/open?id=1aEgG4x28NhTByYASEjyVOHtxQOfDtL6P | H52: Habilidade em producao de projetos. | I52: Disponibilidade imediata para vaga | J52: A1-A2 (básico) | L52: 25 | M52: 5.5465517 | N52: 25 | O52: 3.1541667 | P52: 0 | Q52: 2.25 | R52: 4.3333333 | S52: 2.75 | T52: 17 | U52: 7.2352941 | Y52: EMEFAF | AB52: Utilizando recursos tecnológicos, metodologias ativas para o melhor aproveitamento do tempo em sala. | AD52: 2 | AE52: 5 | AF52: 2 | AG52: 3.05 | AH52: Faço uso de aula invertida, debates, seminário e todas de conversas para uma análise do entendimento do foi aprendido. | AJ52: 0 | AK52: 8 | AL52: 6 | AM52: 4.9 | AN52: Na disciplina que leciono gosto de utilizar a gestão de tempo, mapas mentais, auto explicação e debates e discussões dirigidas. Essas práticas permitem que os alunos definam objetivos e o tempo para execução, façam sua interpretação para si mesmo e em seguida compartilhem suas opiniões sobre o conteúdo. | AP52: 19 | AQ52: 23 | AR52: 14 | AS52: 18.65 | AT52: Eu uso como base a BNCC que dita que o processo de aprendizagem deve ser protagonizado pelo discente, gosto de criar projetos, o que permite que os alunos estejam inseridos totalmente no seu processo de produção, tenho um carinho especial pela aula invertida e pela toda de conversa no qual os alunos demonstram suas habilidades e conhecimentos em relação ao conteúdo aprendido. Gosto de comunicação, que o aluno fale, discorra e problematize e até mesmo desconstrua e resignifique questões pertinentes ao tema estudado. É sempre válido unir teoria a prática, com a criação de atividades criativas tendo como suporte a utilização de tecnologias. | AV52: 6 | AW52: 16 | AX52: 11 | AY52: 11.25 | BB52: 15 | BC52: 2 | BD52: 2 | BE52: 0 | BF52: 5 | BG52: 3 | BH52: 15 | BI52: 6 | BJ52: 10 | BK52: 0.5 | BL52: 7.5 | BM52: 8 | BN52: 9 | BO52: 1 | BP52: 5 | BQ52: 2.5 | BR52: 9 | BS52: 7.5 | BT52: 15 | BV52: =IFERROR(AVERAGEIF(AULAS_TESTE!$F:$F,$B52,AULAS_TESTE!G:G),"") -> 6.7941176 | BW52: =IFERROR(AVERAGEIF(AULAS_TESTE!$F:$F,$B52,AULAS_TESTE!H:H),"") -> 7.3529412 | BX52: =IFERROR(AVERAGEIF(AULAS_TESTE!$F:$F,$B52,AULAS_TESTE!I:I),"") -> 8.1764706 | BY52: =IFERROR(AVERAGEIF(AULAS_TESTE!$F:$F,$B52,AULAS_TESTE!J:J),"") -> 7.65625 | BZ52: =IFERROR(AVERAGEIF(AULAS_TESTE!$F:$F,$B52,AULAS_TESTE!K:K),"") -> 7.7333333 | CA52: =IFERROR(AVERAGEIF(AULAS_TESTE!$F:$F,$B52,AULAS_TESTE!L:L),"") -> 6.8076923 | CB52: =IFERROR(AVERAGEIF(AULAS_TESTE!$F:$F,$B52,AULAS_TESTE!M:M),"") -> 8.1176471 | CC52: =IFERROR(AVERAGEIF(AULAS_TESTE!$F:$F,$B52,AULAS_TESTE!N:N),"") -> 8.3125 | CD52: =IFERROR(AVERAGEIF(AULAS_TESTE!$F:$F,$B52,AULAS_TESTE!O:O),"") -> 7.5588235 | CE52: =IFERROR(AVERAGEIF(AULAS_TESTE!$F:$F,$B52,AULAS_TESTE!P:P),"") -> 7.6875 | CF52: =IFERROR(AVERAGEIF(AULAS_TESTE!$F:$F,$B52,AULAS_TESTE!Q:Q),"") -> 7.5 | CG52: =IFERROR(AVERAGEIF(AULAS_TESTE!$F:$F,$B52,AULAS_TESTE!R:R),"") -> 6.2727273 | CH52: =IFERROR(AVERAGEIF(AULAS_TESTE!$F:$F,$B52,AULAS_TESTE!S:S),"") -> 8.0625 | CI52: =IFERROR(AVERAGEIF(AULAS_TESTE!$F:$F,$B52,AULAS_TESTE!T:T),"") -> 7.59375
A53: 0 | B53: Nome do Candidato | C53: emaildocandidato@email.com | D53: 11999999999 | E53: Matemática | F53: https://drive.google.com/open?id=1Vfr7aaJvEJpCCo52VDlSUEcAqOoACcCk | G53: https://drive.google.com/open?id=1a7_RHQtzJcOaQeE8x-WKETKSNeMGnugA | H53: Eu gosto de conhecer áreas novas como a neurociência, com o objetivo de nao ficar apenas no campo da matemática, mas sim, mesclar conhecimentos distintos visando a melhorar minhas aulas e levar maior significado para os alunos. | J53: A1-A2 (básico) | L53: 19 | M53: 5.9137931 | N53: 9 | O53: 5.125 | P53: 0 | Q53: 4.8333333 | R53: 6.8333333 | S53: 3.6666667 | T53: 29 | U53: 6.4705882 | V53: 6.5 | W53: 0.5 | X53: 2.5 | Y53: EMEFAF | AB53: Separo a aula em três etapas: explicação teórica, atividade e aprofundamento com exercícios. Em aulas pertinentes desenvolvo primeiro a atividade de assimilação e depois consolido com parte teórica. | AD53: 7 | AE53: 15 | AF53: 9 | AG53: 10.5 | AH53: Dentro das habilidades da BNCC eu separo critérios que pretendo trabalhar e posteriormente avaliar se o estudante compreendeu. EX.: em EF07MA03 eu consigo avaliar detalhes como: 1) reconhecer números negativos em diferentes contextos, 2)representar números negativos na reta numérica, 3) compreender o conceito de oposto de um número inteiro e etc tudo em atividades em duplas, individuais, digitais ou teóricas. | AJ53: 8 | AK53: 22 | AL53: 11 | AM53: 13.95 | AN53: Orientou que para resolver um problema devemos sempre interpretá-lo pela ótica de uma situação em que temos maior domínio e após compreender o problema podemos generalizar para outras situações. | AP53: 22 | AQ53: 23 | AR53: 10 | AS53: 18.15 | AT53: Sigo muito os ensinamentos de John A. Van de Walle que são de extrema valia em uma sala de aula do ensino fundamental e as estratégias de Jo Boaler para turmas do Ensino Médio. Ambos os autores demonstram que uma aula significativa de matemática deve conter uma atividade simples, mas com potencial de chegar a níveis muito elevados. | AV53: 21 | AW53: 22 | AX53: 14 | AY53: 18.9 | BB53: 12 | BC53: 2 | BD53: 2 | BE53: 0 | BF53: 2 | BG53: 4 | BH53: 15 | BI53: 8 | BJ53: 6 | BK53: 1.5 | BL53: 6 | BM53: 4 | BN53: 9 | BO53: 2.5 | BP53: 5 | BQ53: 2.5 | BR53: 6 | BS53: 7.5 | BT53: 15 | BV53: =IFERROR(AVERAGEIF(AULAS_TESTE!$F:$F,$B53,AULAS_TESTE!G:G),"") -> 6.7941176 | BW53: =IFERROR(AVERAGEIF(AULAS_TESTE!$F:$F,$B53,AULAS_TESTE!H:H),"") -> 7.3529412 | BX53: =IFERROR(AVERAGEIF(AULAS_TESTE!$F:$F,$B53,AULAS_TESTE!I:I),"") -> 8.1764706 | BY53: =IFERROR(AVERAGEIF(AULAS_TESTE!$F:$F,$B53,AULAS_TESTE!J:J),"") -> 7.65625 | BZ53: =IFERROR(AVERAGEIF(AULAS_TESTE!$F:$F,$B53,AULAS_TESTE!K:K),"") -> 7.7333333 | CA53: =IFERROR(AVERAGEIF(AULAS_TESTE!$F:$F,$B53,AULAS_TESTE!L:L),"") -> 6.8076923 | CB53: =IFERROR(AVERAGEIF(AULAS_TESTE!$F:$F,$B53,AULAS_TESTE!M:M),"") -> 8.1176471 | CC53: =IFERROR(AVERAGEIF(AULAS_TESTE!$F:$F,$B53,AULAS_TESTE!N:N),"") -> 8.3125 | CD53: =IFERROR(AVERAGEIF(AULAS_TESTE!$F:$F,$B53,AULAS_TESTE!O:O),"") -> 7.5588235 | CE53: =IFERROR(AVERAGEIF(AULAS_TESTE!$F:$F,$B53,AULAS_TESTE!P:P),"") -> 7.6875 | CF53: =IFERROR(AVERAGEIF(AULAS_TESTE!$F:$F,$B53,AULAS_TESTE!Q:Q),"") -> 7.5 | CG53: =IFERROR(AVERAGEIF(AULAS_TESTE!$F:$F,$B53,AULAS_TESTE!R:R),"") -> 6.2727273 | CH53: =IFERROR(AVERAGEIF(AULAS_TESTE!$F:$F,$B53,AULAS_TESTE!S:S),"") -> 8.0625 | CI53: =IFERROR(AVERAGEIF(AULAS_TESTE!$F:$F,$B53,AULAS_TESTE!T:T),"") -> 7.59375
A54: 0 | B54: Nome do Candidato | C54: emaildocandidato@email.com | D54: 11999999999 | E54: Matemática | F54: https://drive.google.com/open?id=1t_EBiKQSYuTJIP_m1OuyuMkJbK33oHOP | G54: https://drive.google.com/open?id=11d5hyETmE0JzHSY0Fqz1Jvk84LyZEnC- | J54: A1-A2 (básico) | L54: 29 | M54: 5.1086207 | N54: 32 | O54: 1.7208333 | P54: 0 | Q54: 0.58333333 | R54: 2.8333333 | S54: 1.5833333 | T54: 14 | U54: 7.5 | V54: 7.5 | W54: 3.2 | X54: 4.6333333 | Y54: EMEFAF | AB54: Cada aula é uma aula diferenciada.Divido muitas vezes em aulas teóricas, em aulas de correção de exercícios e aulas práticas. | AD54: 0 | AE54: 5 | AF54: 4 | AG54: 3.15 | AH54: Minhas aulas são muito interativas. Procuro deixar a classe participar e incentivo muito a participação de todos os alunos, sempre procurando fazer perguntas e elogiando os alunos, mesmo aqueles com dificuldades. | AJ54: 0 | AK54: 7 | AL54: 4 | AM54: 3.85 | AN54: Na minha disciplina, é essencial o treino e o hábito de praticar a resolução de exercícios, sendo que cobro constantemente os alunos em relação a responsabilidade de manter seus estudos sempre em dia. | AP54: 5 | AQ54: 14 | AR54: 5 | AS54: 8.15 | AT54: Sou um professor com uma bagagem considerável. Já trabalho em sala de aula por mais de 30 anos. Conheço bem as dificuldades de cada aluno, e isto me incentiva a cada aula. Cada aula é uma aula nova, nunca uma aula é igual a outra, isto me renova a cada dia. | AV54: 2 | AW54: 8 | AX54: 6 | AY54: 5.5 | BB54: 15 | BC54: 4 | BD54: 4 | BE54: 0 | BF54: 3 | BG54: 4 | BH54: 12 | BI54: 6 | BJ54: 8 | BK54: 1 | BL54: 7.5 | BM54: 10 | BN54: 12 | BO54: 1.5 | BP54: 1 | BQ54: 2.5 | BR54: 15 | BS54: 6 | BT54: 15 | BV54: =IFERROR(AVERAGEIF(AULAS_TESTE!$F:$F,$B54,AULAS_TESTE!G:G),"") -> 6.7941176 | BW54: =IFERROR(AVERAGEIF(AULAS_TESTE!$F:$F,$B54,AULAS_TESTE!H:H),"") -> 7.3529412 | BX54: =IFERROR(AVERAGEIF(AULAS_TESTE!$F:$F,$B54,AULAS_TESTE!I:I),"") -> 8.1764706 | BY54: =IFERROR(AVERAGEIF(AULAS_TESTE!$F:$F,$B54,AULAS_TESTE!J:J),"") -> 7.65625 | BZ54: =IFERROR(AVERAGEIF(AULAS_TESTE!$F:$F,$B54,AULAS_TESTE!K:K),"") -> 7.7333333 | CA54: =IFERROR(AVERAGEIF(AULAS_TESTE!$F:$F,$B54,AULAS_TESTE!L:L),"") -> 6.8076923 | CB54: =IFERROR(AVERAGEIF(AULAS_TESTE!$F:$F,$B54,AULAS_TESTE!M:M),"") -> 8.1176471 | CC54: =IFERROR(AVERAGEIF(AULAS_TESTE!$F:$F,$B54,AULAS_TESTE!N:N),"") -> 8.3125 | CD54: =IFERROR(AVERAGEIF(AULAS_TESTE!$F:$F,$B54,AULAS_TESTE!O:O),"") -> 7.5588235 | CE54: =IFERROR(AVERAGEIF(AULAS_TESTE!$F:$F,$B54,AULAS_TESTE!P:P),"") -> 7.6875 | CF54: =IFERROR(AVERAGEIF(AULAS_TESTE!$F:$F,$B54,AULAS_TESTE!Q:Q),"") -> 7.5 | CG54: =IFERROR(AVERAGEIF(AULAS_TESTE!$F:$F,$B54,AULAS_TESTE!R:R),"") -> 6.2727273 | CH54: =IFERROR(AVERAGEIF(AULAS_TESTE!$F:$F,$B54,AULAS_TESTE!S:S),"") -> 8.0625 | CI54: =IFERROR(AVERAGEIF(AULAS_TESTE!$F:$F,$B54,AULAS_TESTE!T:T),"") -> 7.59375
A55: 0 | B55: Nome do Candidato | C55: emaildocandidato@email.com | D55: 11999999999 | E55: Física | F55: https://drive.google.com/open?id=1U17JSb6JuXIuORQhvKLQed-dAmJm_QkW | G55: https://drive.google.com/open?id=1i_N0Uq4clk12SW24Dj4_lvqxWjJwNtZH | I55: Locomoção: trólebus + ônibus ou Uber | J55: C1-C2 (avançado/fluente) | L55: 8 | M55: 5.8827586 | N55: 7 | O55: 4.0083333 | P55: 0 | Q55: 3.25 | R55: 4.5 | S55: 4.1666667 | T55: 8 | U55: 7.2058824 | Y55: EMEFAF | AB55: Aulas divididas em blocos (com blocos de estudos com tempo maior para os alunos fazerem exercícios). Metodologias ativas (aluno protagonista) e rotinas claras de como são as dinâmicas de aulas para os alunos | AD55: 15 | AE55: 15 | AF55: 13 | AG55: 14.3 | AH55: Avaliações diagnósticas (lista de exercícios), produções práticas (cartazes, textos) e feedback contínuo (perguntas diretas aos alunos) | AJ55: 12 | AK55: 10 | AL55: 9 | AM55: 10.25 | AN55: Organização do tempo (estabelecimento de rotina, agenda física, técnica polidoro de estudo), aprendizado ativo (escrita em caderno, construção de mapas mentais) e autoavaliação (reflexão sobre o processo de aprendizado ao longo dos dias e bimestre) | AP55: 11 | AQ55: 21 | AR55: 18 | AS55: 16.95 | AT55: Formação continuada (cursos livres e de pós-graduação), leituras de livros didáticos (antigos e atuais) e conversas entre corpo docente e coordenação | AV55: 1 | AW55: 8 | AX55: 10 | AY55: 6.6 | BB55: 15 | BC55: 2 | BD55: 4 | BE55: 0 | BF55: 3 | BG55: 4 | BH55: 15 | BI55: 6 | BJ55: 10 | BK55: 2 | BL55: 7.5 | BM55: 10 | BN55: 3 | BO55: 2 | BP55: 5 | BQ55: 2.5 | BR55: 9 | BS55: 7.5 | BT55: 15 | BV55: =IFERROR(AVERAGEIF(AULAS_TESTE!$F:$F,$B55,AULAS_TESTE!G:G),"") -> 6.7941176 | BW55: =IFERROR(AVERAGEIF(AULAS_TESTE!$F:$F,$B55,AULAS_TESTE!H:H),"") -> 7.3529412 | BX55: =IFERROR(AVERAGEIF(AULAS_TESTE!$F:$F,$B55,AULAS_TESTE!I:I),"") -> 8.1764706 | BY55: =IFERROR(AVERAGEIF(AULAS_TESTE!$F:$F,$B55,AULAS_TESTE!J:J),"") -> 7.65625 | BZ55: =IFERROR(AVERAGEIF(AULAS_TESTE!$F:$F,$B55,AULAS_TESTE!K:K),"") -> 7.7333333 | CA55: =IFERROR(AVERAGEIF(AULAS_TESTE!$F:$F,$B55,AULAS_TESTE!L:L),"") -> 6.8076923 | CB55: =IFERROR(AVERAGEIF(AULAS_TESTE!$F:$F,$B55,AULAS_TESTE!M:M),"") -> 8.1176471 | CC55: =IFERROR(AVERAGEIF(AULAS_TESTE!$F:$F,$B55,AULAS_TESTE!N:N),"") -> 8.3125 | CD55: =IFERROR(AVERAGEIF(AULAS_TESTE!$F:$F,$B55,AULAS_TESTE!O:O),"") -> 7.5588235 | CE55: =IFERROR(AVERAGEIF(AULAS_TESTE!$F:$F,$B55,AULAS_TESTE!P:P),"") -> 7.6875 | CF55: =IFERROR(AVERAGEIF(AULAS_TESTE!$F:$F,$B55,AULAS_TESTE!Q:Q),"") -> 7.5 | CG55: =IFERROR(AVERAGEIF(AULAS_TESTE!$F:$F,$B55,AULAS_TESTE!R:R),"") -> 6.2727273 | CH55: =IFERROR(AVERAGEIF(AULAS_TESTE!$F:$F,$B55,AULAS_TESTE!S:S),"") -> 8.0625 | CI55: =IFERROR(AVERAGEIF(AULAS_TESTE!$F:$F,$B55,AULAS_TESTE!T:T),"") -> 7.59375
A56: 0 | B56: Nome do Candidato | C56: emaildocandidato@email.com | D56: 11999999999 | E56: Química | F56: https://drive.google.com/open?id=1ZEfyj2ijz8AyQsnp6taQhZ1FCVg58M3T | G56: https://drive.google.com/open?id=1I09F2NILlLqked-Bu1-T8VzbmHXMe64t | J56: B1-B2 (intermediário) | L56: 13 | M56: 5.9413793 | N56: 10 | O56: 4.4416667 | P56: 0 | Q56: 3.9166667 | R56: 5.4166667 | S56: 3.9166667 | T56: 13 | U56: 7 | V56: 8.5 | Y56: EMEFAF | AB56: Tenho todas minhas aulas preparadas antecipadamente de forma digital em slides com animações para garantir o dinamismo da aula, envio listas de exercícios antes das aulas para que os alunos já venham preparados e a aula flua melhor. | AD56: 12 | AE56: 15 | AF56: 9 | AG56: 12 | AH56: Sempre separo aulas para que os alunos resolvam exercícios na lousa e me expliquem o raciocínio (fazendo aulas invertidas) e também costumo acompanhar de perto a resolução dos exercícios com os alunos, sempre andando pela sala e conversando com eles sobre a atividade que estão realizando. | AJ56: 13 | AK56: 22 | AL56: 10 | AM56: 15.1 | AN56: Organização semanal dos estudos, a partir da resolução de listas de exercícios, sempre estimulando a autonomia dos alunos. Revisão ao final de cada conteúdo com elaboração de mapas mentais e/ou apresentação expositiva de conteúdos. | AP56: 16 | AQ56: 20 | AR56: 12 | AS56: 16 | AT56: Gosto de ler e trocar experiências com colegas de profissão. Sempre pesquiso métodos para ensinar por meio de experiências e química do cotidiano. | AV56: 6 | AW56: 8 | AX56: 16 | AY56: 10.2 | BB56: 9 | BC56: 4 | BD56: 2 | BE56: 0 | BF56: 3 | BG56: 3 | BH56: 15 | BI56: 8 | BJ56: 8 | BK56: 0.5 | BL56: 7.5 | BM56: 10 | BN56: 6 | BO56: 1 | BP56: 2 | BQ56: 2.5 | BR56: 15 | BS56: 7.5 | BT56: 15 | BV56: =IFERROR(AVERAGEIF(AULAS_TESTE!$F:$F,$B56,AULAS_TESTE!G:G),"") -> 6.7941176 | BW56: =IFERROR(AVERAGEIF(AULAS_TESTE!$F:$F,$B56,AULAS_TESTE!H:H),"") -> 7.3529412 | BX56: =IFERROR(AVERAGEIF(AULAS_TESTE!$F:$F,$B56,AULAS_TESTE!I:I),"") -> 8.1764706 | BY56: =IFERROR(AVERAGEIF(AULAS_TESTE!$F:$F,$B56,AULAS_TESTE!J:J),"") -> 7.65625 | BZ56: =IFERROR(AVERAGEIF(AULAS_TESTE!$F:$F,$B56,AULAS_TESTE!K:K),"") -> 7.7333333 | CA56: =IFERROR(AVERAGEIF(AULAS_TESTE!$F:$F,$B56,AULAS_TESTE!L:L),"") -> 6.8076923 | CB56: =IFERROR(AVERAGEIF(AULAS_TESTE!$F:$F,$B56,AULAS_TESTE!M:M),"") -> 8.1176471 | CC56: =IFERROR(AVERAGEIF(AULAS_TESTE!$F:$F,$B56,AULAS_TESTE!N:N),"") -> 8.3125 | CD56: =IFERROR(AVERAGEIF(AULAS_TESTE!$F:$F,$B56,AULAS_TESTE!O:O),"") -> 7.5588235 | CE56: =IFERROR(AVERAGEIF(AULAS_TESTE!$F:$F,$B56,AULAS_TESTE!P:P),"") -> 7.6875 | CF56: =IFERROR(AVERAGEIF(AULAS_TESTE!$F:$F,$B56,AULAS_TESTE!Q:Q),"") -> 7.5 | CG56: =IFERROR(AVERAGEIF(AULAS_TESTE!$F:$F,$B56,AULAS_TESTE!R:R),"") -> 6.2727273 | CH56: =IFERROR(AVERAGEIF(AULAS_TESTE!$F:$F,$B56,AULAS_TESTE!S:S),"") -> 8.0625 | CI56: =IFERROR(AVERAGEIF(AULAS_TESTE!$F:$F,$B56,AULAS_TESTE!T:T),"") -> 7.59375
